Workbook

Sheet PUNTUALIDAD
A1: id | B1: id_servicio | C1: business_unit | D1: des | E1: Tipo de Viaje | F1: ID Ruta | G1: desc_adicional | H1: car | I1: status | J1: shift | K1: group | L1: start_date | M1: start_time | N1: start_eta | O1: start_status | P1: end_date | Q1: end_time | R1: end_eta | S1: end_status | T1: record_quality | U1: km cotizado | V1: km promedio | W1: km_calc | X1: km_calc + vac | Y1: km_vac_inicial | Z1: km_vac_final | AA1: driver | AB1: worker_id | AC1: operador | AD1: no. de nomina | AE1: usuario | AF1: Fecha de creación (Tiempo de Servidor) | AG1: momento | AH1: Sem Via | AI1: Sol Viaje | AJ1: Diagnostico Viaje | AK1: $ Viaje | AL1: $ Viaje Fijo | AM1: Tipo de Facturación | AN1: Periodo de Facturación | AO1: Fecha de creación (Tiempo de Unidad de Negocios) | AP1: Aforo | AQ1: SALIDA | AR1: LLEGADA | AS1: Estatus Salida | AT1: Estatus Llegada | AU1: Estatus | AV1: Semana | AW1: Puntualidad | AX1: concat | AY1: supervisor2 | AZ1: gte | BA1: CONCAT2 | BB1: ID Ruta | BC1: Turno | BD1: Dashtrax
A2: 176541809 | B2: E-HER-T1-R0017 | C2: LIPU Guadalajara | D2: Arenales | E2: N | F2: 17 | H2: 15192 | I2: 6 | J2: IN | K2: HERSHEYS | L2: 46265 | M2: 0.19444444 | N2: 0.19791667 | O2: done | P2: 46265 | Q2: 0.25 | R2: 0.24675926 | S2: done | T2: 1 | U2: 37 | V2: 33.03 | W2: 34.41 | X2: - | Y2: - | Z2: - | AA2: ZUÑIGA CARRILLO CHRISTIAN ALEJ | AB2: 14122103 | AC2: ZUÑIGA CARRILLO CHRISTIAN ALEJ | AD2: 14122103 | AE2: SISTEMA | AF2: AUTOMÁTICO | AG2: AUTOMÁTICO | AH2: 36 | AI2: Ok | AJ2: Retrasado,A tiempo | AK2: 815 | AL2: N/A | AM2: Variable por Ruta | AN2: Sin asignar | AO2: AUTOMÁTICO | AP2: - | AQ2: 0.0034722222 | AR2: -0.0032407407 | AS2: Inicia tarde | AT2: Llega a Tiempo | AU2: Inicia tarde-Llega a Tiempo | AV2: 36 | AW2: No | AX2: ArenalesHERSHEYS | AY2: CARLOS C. | AZ2: Ilse M. | BA2: HERSHEYSArenales | BB2: E-HER-R0017 | BC2: T1 | BD2: Arenales-R0017-04:40
A3: 176536422 | B3: E-SAN-T1-R0317 | C3: LIPU Guadalajara | D3: Angel Leaño T1 | E3: N | F3: 317 | H3: 13900 | I3: 6 | J3: IN | K3: SANMINA GDL | L3: 46265 | M3: 0.20138889 | N3: 0.20555556 | O3: done | P3: 46265 | Q3: 0.26736111 | R3: 0.24967593 | S3: done | T3: 1 | U3: 47 | V3: 41.37 | W3: 43.66 | X3: - | Y3: - | Z3: - | AA3: PEREZ CORREA LUIS CARLOS | AB3: 14123635 | AC3: PEREZ CORREA LUIS CARLOS | AD3: 14123635 | AE3: SISTEMA | AF3: AUTOMÁTICO | AG3: AUTOMÁTICO | AH3: 36 | AI3: Ok | AJ3: Retrasado,A tiempo | AK3: 530.63 | AL3: N/A | AM3: Variable por Ruta | AN3: Sin asignar | AO3: AUTOMÁTICO | AP3: 24 | AQ3: 0.0041666667 | AR3: -0.017685185 | AS3: Inicia tarde | AT3: Llega a Tiempo | AU3: Inicia tarde-Llega a Tiempo | AV3: 36 | AW3: No | AX3: Angel Leaño T1SANMINA GDL | AY3: PABLO F. | AZ3: Felipe M. | BA3: SANMINA GDLAngel Leaño T1 | BB3: E-SAN-R0317 | BC3: T1 | BD3: Angel Leaño T1-R0317-04:50
A4: 176543622 | B4: E-MOL-T1-R0024 | C4: LIPU Guadalajara | D4: Tetlán | E4: N | F4: 24 | H4: 15786 | I4: 6 | J4: IN | K4: MOLEX | L4: 46265 | M4: 0.20138889 | N4: 0.20694444 | O4: done | P4: 46265 | Q4: 0.26041667 | R4: 0.25042824 | S4: done | T4: 1 | U4: 67 | V4: 59.86 | W4: 59.45 | X4: - | Y4: - | Z4: - | AA4: RUVALCABA CORTEZ NOE | AB4: 14118501 | AC4: RUVALCABA CORTEZ NOE | AD4: 14118501 | AE4: SISTEMA | AF4: AUTOMÁTICO | AG4: AUTOMÁTICO | AH4: 36 | AI4: Ok | AJ4: Retrasado,A tiempo | AK4: 0 | AL4: N/A | AM4: Variable por Ruta | AN4: Sin asignar | AO4: AUTOMÁTICO | AP4: - | AQ4: 0.0055555556 | AR4: -0.0099884259 | AS4: Inicia tarde | AT4: Llega a Tiempo | AU4: Inicia tarde-Llega a Tiempo | AV4: 36 | AW4: No | AX4: TetlánMOLEX | AY4: VICTOR C. | AZ4: Leopoldo V. | BA4: MOLEXTetlán | BB4: E-MOL-R0024 | BC4: T1 | BD4: Tetlán-R0024-04:50
A5: 176549835 | B5: E-SAN-T1-R0503 | C5: LIPU Guadalajara | D5: Tabachines T1 | E5: N | F5: 503 | H5: 13416 | I5: 6 | J5: IN | K5: SANMINA GDL | L5: 46265 | M5: 0.20138889 | N5: 0.24097222 | O5: done | P5: 46265 | Q5: 0.26736111 | R5: 0.30763889 | S5: done | T5: 1 | U5: 42 | V5: 35.33 | W5: 34.07 | X5: 56.23 | Y5: 16.91 | Z5: 5.25 | AA5: SANTANA ARAIZA SANTIAGO | AB5: 14106368 | AC5: SANTANA ARAIZA SANTIAGO | AD5: 14106368 | AE5: SISTEMA | AF5: AUTOMÁTICO | AG5: AUTOMÁTICO | AH5: 36 | AI5: Ok | AJ5: Retrasado | AK5: 0 | AL5: N/A | AM5: Variable por Ruta | AN5: Sin asignar | AO5: AUTOMÁTICO | AP5: - | AQ5: 0.039583333 | AR5: 0.040277778 | AS5: Inicia tarde | AT5: Llega tarde | AU5: Inicia tarde-Llega tarde | AV5: 36 | AW5: No | AX5: Tabachines T1SANMINA GDL | AY5: PABLO F. | AZ5: Felipe M. | BA5: SANMINA GDLTabachines T1 | BB5: E-SAN-R0503 | BC5: T1 | BD5: Tabachines T1-R0503-04:50
A6: 176531117 | B6: E-SAN-T1-R0061 | C6: LIPU Guadalajara | D6: Bethel | E6: N | F6: 61 | H6: 16744 | I6: 6 | J6: IN | K6: SANMINA GDL | L6: 46265 | M6: 0.20833333 | N6: 0.21319444 | O6: done | P6: 46265 | Q6: 0.26736111 | R6: 0.25465278 | S6: done | T6: 1 | U6: 46 | V6: 42.96 | W6: 40.45 | X6: - | Y6: - | Z6: - | AA6: CASTAÑEDA AGUILAR LUIS ANTONIO | AB6: 14119956 | AC6: CASTAÑEDA AGUILAR LUIS ANTONIO | AD6: 14119956 | AE6: SISTEMA | AF6: AUTOMÁTICO | AG6: AUTOMÁTICO | AH6: 36 | AI6: Ok | AJ6: Retrasado,A tiempo | AK6: 530.63 | AL6: N/A | AM6: Variable por Ruta | AN6: Sin asignar | AO6: AUTOMÁTICO | AP6: - | AQ6: 0.0048611111 | AR6: -0.012708333 | AS6: Inicia tarde | AT6: Llega a Tiempo | AU6: Inicia tarde-Llega a Tiempo | AV6: 36 | AW6: No | AX6: BethelSANMINA GDL | AY6: PABLO F. | AZ6: Felipe M. | BA6: SANMINA GDLBethel | BB6: E-SAN-R0061 | BC6: T1 | BD6: Bethel-R0061-05:00
A7: 176538845 | B7: E-SM4-T1-R0108 | C7: LIPU Guadalajara | D7: San Sebastian 1 Turno 1 | E7: N | F7: 108 | H7: 5672 | I7: 6 | J7: IN | K7: SANMINA TLAJOMULCO | L7: 46265 | M7: 0.20833333 | N7: 0.21180556 | O7: done | P7: 46265 | Q7: 0.26736111 | R7: 0.25574074 | S7: done | T7: 1 | U7: 42 | V7: 27.41 | W7: 28.63 | X7: - | Y7: - | Z7: - | AA7: GARCIA RAMIREZ EZEQUIEL | AB7: 14124002 | AC7: GARCIA RAMIREZ EZEQUIEL | AD7: 14124002 | AE7: SISTEMA | AF7: AUTOMÁTICO | AG7: AUTOMÁTICO | AH7: 36 | AI7: Ok | AJ7: Retrasado,A tiempo | AK7: 0 | AL7: N/A | AM7: Variable por Ruta | AN7: Sin asignar | AO7: AUTOMÁTICO | AP7: 36 | AQ7: 0.0034722222 | AR7: -0.01162037 | AS7: Inicia tarde | AT7: Llega a Tiempo | AU7: Inicia tarde-Llega a Tiempo | AV7: 36 | AW7: No | AX7: San Sebastian 1 Turno 1SANMINA TLAJOMULCO | AY7: CUAUHTEMOC M. | AZ7: Felipe M. | BA7: SANMINA TLAJOMULCOSan Sebastian 1 Turno 1 | BB7: E-SM4-R0108 | BC7: T1 | BD7: San Sebastian 1 Turno 1-R0108-05:00
A8: 176545517 | B8: E-SM4-T1-R0204 | C8: LIPU Guadalajara | D8: San Sebastian 2 | E8: N | F8: 204 | H8: 7915 | I8: 6 | J8: IN | K8: SANMINA TLAJOMULCO | L8: 46265 | M8: 0.20833333 | N8: 0.21458333 | O8: done | P8: 46265 | Q8: 0.26736111 | R8: 0.24138889 | S8: done | T8: 1 | U8: 37 | V8: 32.02 | W8: 28.59 | X8: - | Y8: - | Z8: - | AA8: TORRES SANCHEZ JOSE MARTIN | AB8: 14123894 | AC8: TORRES SANCHEZ JOSE MARTIN | AD8: 14123894 | AE8: SISTEMA | AF8: AUTOMÁTICO | AG8: AUTOMÁTICO | AH8: 36 | AI8: Ok | AJ8: Retrasado,A tiempo | AK8: 0 | AL8: N/A | AM8: Variable por Ruta | AN8: Sin asignar | AO8: AUTOMÁTICO | AP8: - | AQ8: 0.00625 | AR8: -0.025972222 | AS8: Inicia tarde | AT8: Llega a Tiempo | AU8: Inicia tarde-Llega a Tiempo | AV8: 36 | AW8: No | AX8: San Sebastian 2SANMINA TLAJOMULCO | AY8: CUAUHTEMOC M. | AZ8: Felipe M. | BA8: SANMINA TLAJOMULCOSan Sebastian 2 | BB8: E-SM4-R0204 | BC8: T1 | BD8: San Sebastian 2-R0204-05:00
A9: 176551668 | B9: E-BIM-T1-R0009 | C9: LIPU Guadalajara | D9: Oblatos | E9: N | F9: 9 | H9: 4533 | I9: 6 | J9: IN | K9: BIMBO | L9: 46265 | M9: 0.20833333 | N9: 0.21319444 | O9: done | P9: 46265 | Q9: 0.23958333 | R9: 0.23645833 | S9: done | T9: 1 | U9: 21 | V9: 18.63 | W9: 18.69 | X9: - | Y9: - | Z9: - | AA9: REOS GONZALEZ ROBERTO | AB9: 14123572 | AC9: REOS GONZALEZ ROBERTO | AD9: 14123572 | AE9: SISTEMA | AF9: AUTOMÁTICO | AG9: AUTOMÁTICO | AH9: 36 | AI9: Ok | AJ9: Retrasado,A tiempo | AK9: - | AL9: N/A | AM9: Sin asignar | AN9: Sin asignar | AO9: AUTOMÁTICO | AP9: - | AQ9: 0.0048611111 | AR9: -0.003125 | AS9: Inicia tarde | AT9: Llega a Tiempo | AU9: Inicia tarde-Llega a Tiempo | AV9: 36 | AW9: No | AX9: OblatosBIMBO | AY9: DANIEL | AZ9: Leopoldo V. | BA9: BIMBOOblatos | BB9: #N/A | BC9: T1 | BD9: Oblatos-R0009-05:00
A10: 176548304 | B10: E-PIS-T1-R0051 | C10: LIPU Guadalajara | D10: El Refugio | E10: N | F10: 51 | H10: 4431 | I10: 6 | J10: IN | K10: PIS-PISA | L10: 46265 | M10: 0.21041667 | N10: 0.21458333 | O10: done | P10: 46265 | Q10: 0.26736111 | R10: 0.2569213 | S10: done | T10: 1 | U10: 41 | V10: 36.56 | W10: 35.66 | X10: - | Y10: - | Z10: - | AA10: LARIOS SANCHEZ HECTOR ALEXANDE | AB10: 14102875 | AC10: LARIOS SANCHEZ HECTOR ALEXANDE | AD10: 14102875 | AE10: SISTEMA | AF10: AUTOMÁTICO | AG10: AUTOMÁTICO | AH10: 36 | AI10: Ok | AJ10: Retrasado,A tiempo | AK10: 0 | AL10: N/A | AM10: Variable por Ruta | AN10: Sin asignar | AO10: AUTOMÁTICO | AP10: - | AQ10: 0.0041666667 | AR10: -0.010439815 | AS10: Inicia tarde | AT10: Llega a Tiempo | AU10: Inicia tarde-Llega a Tiempo | AV10: 36 | AW10: No | AX10: El RefugioPIS-PISA | AY10: DAVID C. | AZ10: Felipe M. | BA10: PIS-PISAEl Refugio | BB10: E-PIS-R0051 | BC10: T1 | BD10: El Refugio-R0051-05:03
A11: 176540220 | B11: E-CUP-T1-R0012 | C11: LIPU Guadalajara | D11: Huertas | E11: N | F11: 12 | H11: 9700 | I11: 6 | J11: IN | K11: CUPRUM GDL | L11: 46265 | M11: 0.2125 | N11: 0.21597222 | O11: done | P11: 46265 | Q11: 0.24652778 | R11: 0.23888889 | S11: done | T11: 1 | U11: 18 | V11: 13.62 | W11: 14.08 | X11: 26.52 | Y11: 12.08 | Z11: 0.36 | AA11: RAMIREZ GONZALEZ CYNTHIA PATRICIA | AB11: 14123107 | AC11: RAMIREZ GONZALEZ CYNTHIA PATRICIA | AD11: 14123107 | AE11: SISTEMA | AF11: AUTOMÁTICO | AG11: AUTOMÁTICO | AH11: 36 | AI11: Ok | AJ11: Retrasado,A tiempo | AK11: 408.1 | AL11: N/A | AM11: Variable por Ruta | AN11: Sin asignar | AO11: AUTOMÁTICO | AP11: - | AQ11: 0.0034722222 | AR11: -0.0076388889 | AS11: Inicia tarde | AT11: Llega a Tiempo | AU11: Inicia tarde-Llega a Tiempo | AV11: 36 | AW11: No | AX11: HuertasCUPRUM GDL | AY11: DAVID M | AZ11: Ilse M. | BA11: CUPRUM GDLHuertas | BB11: E-CUP-R0012 | BC11: T1 | BD11: Huertas-R0012-05:06
A12: 176538871 | B12: E-SM4-T1-R0119 | C12: LIPU Guadalajara | D12: Tlajomulco 1 | E12: N | F12: 119 | H12: 5771 | I12: 6 | J12: IN | K12: SANMINA TLAJOMULCO | L12: 46265 | M12: 0.21527778 | N12: 0.22083333 | O12: done | P12: 46265 | Q12: 0.26736111 | R12: 0.25721065 | S12: done | T12: 1 | U12: 38 | V12: 35.15 | W12: 33.93 | X12: - | Y12: - | Z12: - | AA12: HERNANDEZ FLORES OSCAR | AB12: 14116853 | AC12: HERNANDEZ FLORES OSCAR | AD12: 14116853 | AE12: SISTEMA | AF12: AUTOMÁTICO | AG12: AUTOMÁTICO | AH12: 36 | AI12: Ok | AJ12: Retrasado,A tiempo | AK12: 0 | AL12: N/A | AM12: Variable por Ruta | AN12: Sin asignar | AO12: AUTOMÁTICO | AP12: - | AQ12: 0.0055555556 | AR12: -0.010150463 | AS12: Inicia tarde | AT12: Llega a Tiempo | AU12: Inicia tarde-Llega a Tiempo | AV12: 36 | AW12: No | AX12: Tlajomulco 1SANMINA TLAJOMULCO | AY12: CUAUHTEMOC M. | AZ12: Felipe M. | BA12: SANMINA TLAJOMULCOTlajomulco 1 | BB12: E-SM4-R0119 | BC12: T1 | BD12: Tlajomulco 1-R0119-05:10
A13: 176551758 | B13: E-BIM-T1-R0012 | C13: LIPU Guadalajara | D13: Adolf Horn | E13: N | F13: 12 | H13: 7345 | I13: 6 | J13: IN | K13: BIMBO | L13: 46265 | M13: 0.21527778 | N13: 0.22430556 | O13: done | P13: 46265 | Q13: 0.23958333 | R13: 0.23768519 | S13: done | T13: 1 | U13: 17 | V13: 14.46 | W13: 14 | X13: - | Y13: - | Z13: - | AA13: PELAYO PELAYO JOSE MARIA | AB13: 14117542 | AC13: PELAYO PELAYO JOSE MARIA | AD13: 14117542 | AE13: SISTEMA | AF13: AUTOMÁTICO | AG13: AUTOMÁTICO | AH13: 36 | AI13: Ok | AJ13: Retrasado,A tiempo | AK13: - | AL13: N/A | AM13: Sin asignar | AN13: Sin asignar | AO13: AUTOMÁTICO | AP13: - | AQ13: 0.0090277778 | AR13: -0.0018981481 | AS13: Inicia tarde | AT13: Llega a Tiempo | AU13: Inicia tarde-Llega a Tiempo | AV13: 36 | AW13: No | AX13: Adolf HornBIMBO | AY13: DANIEL | AZ13: Leopoldo V. | BA13: BIMBOAdolf Horn | BB13: #N/A | BC13: T1 | BD13: Adolf Horn-R0012-05:10
A14: 176538767 | B14: E-SM4-T1-R0080 | C14: LIPU Guadalajara | D14: Villas Santa Cruz | E14: N | F14: 80 | H14: 13375 | I14: 6 | J14: IN | K14: SANMINA TLAJOMULCO | L14: 46265 | M14: 0.21875 | N14: 0.23263889 | O14: done | P14: 46265 | Q14: 0.26736111 | R14: 0.25234954 | S14: done | T14: 1 | U14: 36 | V14: 22.36 | W14: 12.93 | X14: - | Y14: - | Z14: - | AA14: VALLE SANCHEZ RAFAEL | AB14: 14117509 | AC14: VALLE SANCHEZ RAFAEL | AD14: 14117509 | AE14: SISTEMA | AF14: AUTOMÁTICO | AG14: AUTOMÁTICO | AH14: 36 | AI14: Ok | AJ14: Retrasado,A tiempo | AK14: 0 | AL14: N/A | AM14: Variable por Ruta | AN14: Sin asignar | AO14: AUTOMÁTICO | AP14: - | AQ14: 0.013888889 | AR14: -0.015011574 | AS14: Inicia tarde | AT14: Llega a Tiempo | AU14: Inicia tarde-Llega a Tiempo | AV14: 36 | AW14: No | AX14: Villas Santa CruzSANMINA TLAJOMULCO | AY14: CUAUHTEMOC M. | AZ14: Felipe M. | BA14: SANMINA TLAJOMULCOVillas Santa Cruz | BB14: E-SM4-R0080 | BC14: T1 | BD14: Villas Santa Cruz-R0080-05:15
A15: 176538838 | B15: E-SM4-T1-R0105 | C15: LIPU Guadalajara | D15: Prepa 13 T1 | E15: N | F15: 105 | H15: 15993 | I15: 6 | J15: IN | K15: SANMINA TLAJOMULCO | L15: 46265 | M15: 0.21875 | N15: 0.22291667 | O15: done | P15: 46265 | Q15: 0.26736111 | R15: 0.260625 | S15: done | T15: 1 | U15: 38 | V15: 32.09 | W15: 34.45 | X15: - | Y15: - | Z15: - | AA15: CHAVEZ PALOMARES MARIANO | AB15: 14123925 | AC15: CHAVEZ PALOMARES MARIANO | AD15: 14123925 | AE15: SISTEMA | AF15: AUTOMÁTICO | AG15: AUTOMÁTICO | AH15: 36 | AI15: Ok | AJ15: Retrasado,A tiempo | AK15: 0 | AL15: N/A | AM15: Variable por Ruta | AN15: Sin asignar | AO15: AUTOMÁTICO | AP15: - | AQ15: 0.0041666667 | AR15: -0.0067361111 | AS15: Inicia tarde | AT15: Llega a Tiempo | AU15: Inicia tarde-Llega a Tiempo | AV15: 36 | AW15: No | AX15: Prepa 13 T1SANMINA TLAJOMULCO | AY15: CUAUHTEMOC M. | AZ15: Felipe M. | BA15: SANMINA TLAJOMULCOPrepa 13 T1 | BB15: E-SM4-R0105 | BC15: T1 | BD15: Prepa 13 T1-R0105-05:15
A16: 176548507 | B16: E-SM4-T1-R0227 | C16: LIPU Guadalajara | D16: Lomas del Sur | E16: N | F16: 227 | H16: 4980 | I16: 6 | J16: IN | K16: SANMINA TLAJOMULCO | L16: 46265 | M16: 0.21875 | N16: 0.22430556 | O16: done | P16: 46265 | Q16: 0.26736111 | R16: 0.25645833 | S16: done | T16: 1 | U16: 30 | V16: 24.54 | W16: 23.76 | X16: - | Y16: - | Z16: - | AA16: LOPEZ GODINEZ MIGUEL DE JESUS | AB16: 14119154 | AC16: LOPEZ GODINEZ MIGUEL DE JESUS | AD16: 14119154 | AE16: SISTEMA | AF16: AUTOMÁTICO | AG16: AUTOMÁTICO | AH16: 36 | AI16: Ok | AJ16: Retrasado,A tiempo | AK16: 0 | AL16: N/A | AM16: Variable por Ruta | AN16: Sin asignar | AO16: AUTOMÁTICO | AP16: - | AQ16: 0.0055555556 | AR16: -0.010902778 | AS16: Inicia tarde | AT16: Llega a Tiempo | AU16: Inicia tarde-Llega a Tiempo | AV16: 36 | AW16: No | AX16: Lomas del SurSANMINA TLAJOMULCO | AY16: CUAUHTEMOC M. | AZ16: Felipe M. | BA16: SANMINA TLAJOMULCOLomas del Sur | BB16: E-SM4-R0227 | BC16: T1 | BD16: Lomas del Sur-R0227-05:15
A17: 176538621 | B17: E-SK1-T1-R0033 | C17: LIPU Guadalajara | D17: Polanco T1 | E17: N | F17: 33 | H17: 16734 | I17: 6 | J17: IN | K17: SANMINA KAMPUS 16 | L17: 46265 | M17: 0.22222222 | N17: 0.2375 | O17: done | P17: 46265 | Q17: 0.26736111 | R17: 0.27815972 | S17: done | T17: 1 | U17: 26 | V17: 22.25 | W17: 23.85 | X17: - | Y17: - | Z17: - | AA17: VAZQUEZ FLORES FABIAN | AB17: 14107967 | AC17: VAZQUEZ FLORES FABIAN | AD17: 14107967 | AE17: SISTEMA | AF17: AUTOMÁTICO | AG17: AUTOMÁTICO | AH17: 36 | AI17: Ok | AJ17: Retrasado | AK17: 0 | AL17: N/A | AM17: Variable por Ruta | AN17: Sin asignar | AO17: AUTOMÁTICO | AP17: - | AQ17: 0.015277778 | AR17: 0.010798611 | AS17: Inicia tarde | AT17: Llega tarde | AU17: Inicia tarde-Llega tarde | AV17: 36 | AW17: No | AX17: Polanco T1SANMINA KAMPUS 16 | AY17: BRIAN A. | AZ17: Felipe M. | BA17: SANMINA KAMPUS 16Polanco T1 | BB17: E-SK1-R0033 | BC17: T1 | BD17: Polanco T1-R0033-05:20
A18: 176545733 | B18: E-FOX-T1-R0077 | C18: LIPU Guadalajara | D18: Tonala 1 | E18: N | F18: 77 | G18: NORTE | H18: 5527 | I18: 6 | J18: IN | K18: FOXCONN | L18: 46265 | M18: 0.22222222 | N18: 0.22569444 | O18: done | P18: 46265 | Q18: 0.28125 | R18: 0.25989583 | S18: done | T18: 1 | U18: 27 | V18: 23.23 | W18: 22.66 | X18: - | Y18: - | Z18: - | AA18: MONCADA CALDERON FRANCISCO | AB18: 14123254 | AC18: MONCADA CALDERON FRANCISCO | AD18: 14123254 | AE18: SISTEMA | AF18: AUTOMÁTICO | AG18: AUTOMÁTICO | AH18: 36 | AI18: Ok | AJ18: Retrasado,A tiempo | AK18: 0 | AL18: N/A | AM18: Variable por Ruta | AN18: Sin asignar | AO18: AUTOMÁTICO | AP18: - | AQ18: 0.0034722222 | AR18: -0.021354167 | AS18: Inicia tarde | AT18: Llega a Tiempo | AU18: Inicia tarde-Llega a Tiempo | AV18: 36 | AW18: No | AX18: Tonala 1FOXCONN | AY18: CANDELAS | AZ18: Leopoldo V. | BA18: FOXCONNTonala 1 | BB18: E-FOX-R0077 | BC18: T1 | BD18: Tonala 1-R0077-05:20
A19: 176546909 | B19: E-SM3-T1-R0221 | C19: LIPU Guadalajara | D19: El Mirador | E19: N | F19: 221 | H19: 5423 | I19: 6 | J19: IN | K19: SANMINA FORANE | L19: 46265 | M19: 0.22222222 | N19: 0.22708333 | O19: done | P19: 46265 | Q19: 0.26736111 | R19: 0.26046296 | S19: done | T19: 1 | U19: 12 | V19: 17.67 | W19: 17.91 | X19: - | Y19: - | Z19: - | AA19: LUEVANO LOPEZ JUAN EZEQUIEL | AB19: 14123926 | AC19: LUEVANO LOPEZ JUAN EZEQUIEL | AD19: 14123926 | AE19: SISTEMA | AF19: AUTOMÁTICO | AG19: AUTOMÁTICO | AH19: 36 | AI19: Ok | AJ19: Retrasado,A tiempo | AK19: 0 | AL19: N/A | AM19: Variable por Ruta | AN19: Sin asignar | AO19: AUTOMÁTICO | AP19: 49 | AQ19: 0.0048611111 | AR19: -0.0068981481 | AS19: Inicia tarde | AT19: Llega a Tiempo | AU19: Inicia tarde-Llega a Tiempo | AV19: 36 | AW19: No | AX19: El MiradorSANMINA FORANE | AY19: HEROS M. | AZ19: Felipe M. | BA19: SANMINA FORANEEl Mirador | BB19: E-SM3-R0221 | BC19: T1 | BD19: El Mirador-R0221-05:20
A20: 176549079 | B20: E-MAS-T1-R0007 | C20: LIPU Guadalajara | D20: Chulavista | E20: N | F20: 7 | H20: 4984 | I20: 6 | J20: IN | K20: MASECA GDL | L20: 46265 | M20: 0.22222222 | N20: 0.22638889 | O20: done | P20: 46265 | Q20: 0.26041667 | R20: 0.26502315 | S20: done | T20: 1 | U20: 21 | V20: 17.4 | W20: 17.69 | X20: - | Y20: - | Z20: - | AA20: AVILAN RIVERA MIGUEL UBALDO | AB20: 14123652 | AC20: AVILAN RIVERA MIGUEL UBALDO | AD20: 14123652 | AE20: SISTEMA | AF20: AUTOMÁTICO | AG20: AUTOMÁTICO | AH20: 36 | AI20: Ok | AJ20: Retrasado | AK20: 0 | AL20: N/A | AM20: Variable por Ruta | AN20: Sin asignar | AO20: AUTOMÁTICO | AP20: - | AQ20: 0.0041666667 | AR20: 0.0046064815 | AS20: Inicia tarde | AT20: Llega tarde | AU20: Inicia tarde-Llega tarde | AV20: 36 | AW20: No | AX20: ChulavistaMASECA GDL | AY20: DAVID M | AZ20: Ilse M. | BA20: MASECA GDLChulavista | BB20: E-MAS-R0007 | BC20: T1 | BD20: Chulavista-R0007-05:20
A21: 176541791 | B21: E-HER-T1-R0011 | C21: LIPU Guadalajara | D21: El Salto Azucena | E21: N | F21: 11 | H21: 15185 | I21: 6 | J21: IN | K21: HERSHEYS | L21: 46265 | M21: 0.22638889 | N21: 0.23194444 | O21: done | P21: 46265 | Q21: 0.25 | R21: 0.24733796 | S21: done | T21: 1 | U21: 14 | V21: 9.91 | W21: 8.43 | X21: - | Y21: - | Z21: - | AA21: RODRIGUEZ MARTINEZ OMAR ROGELIO | AB21: 14122925 | AC21: RODRIGUEZ MARTINEZ OMAR ROGELIO | AD21: 14122925 | AE21: SISTEMA | AF21: AUTOMÁTICO | AG21: AUTOMÁTICO | AH21: 36 | AI21: Ok | AJ21: Retrasado,A tiempo | AK21: 730 | AL21: N/A | AM21: Variable por Ruta | AN21: Sin asignar | AO21: AUTOMÁTICO | AP21: - | AQ21: 0.0055555556 | AR21: -0.002662037 | AS21: Inicia tarde | AT21: Llega a Tiempo | AU21: Inicia tarde-Llega a Tiempo | AV21: 36 | AW21: No | AX21: El Salto AzucenaHERSHEYS | AY21: CARLOS C. | AZ21: Ilse M. | BA21: HERSHEYSEl Salto Azucena | BB21: E-HER-R0011 | BC21: T1 | BD21: El Salto Azucena-R0011-05:26
A22: 176530495 | B22: E-PEP-T1-R0009 | C22: LIPU Guadalajara | D22: Moctezuma San Agustin | E22: N | F22: 9 | H22: 5923 | I22: 6 | J22: IN | K22: PEPSICO GDL | L22: 46265 | M22: 0.22916667 | N22: 0.23333333 | O22: done | P22: 46265 | Q22: 0.27083333 | R22: 0.26597222 | S22: done | T22: 1 | U22: 22 | V22: 12.46 | W22: 20.08 | X22: 39.91 | Y22: 17.01 | Z22: 2.82 | AA22: HERNANDEZ GALLEGOS HECTOR ABRA | AB22: 14122133 | AC22: HERNANDEZ GALLEGOS HECTOR ABRA | AD22: 14122133 | AE22: SISTEMA | AF22: AUTOMÁTICO | AG22: AUTOMÁTICO | AH22: 36 | AI22: Ok | AJ22: Retrasado,A tiempo | AK22: 544.9 | AL22: N/A | AM22: Variable por Ruta | AN22: Sin asignar | AO22: AUTOMÁTICO | AP22: - | AQ22: 0.0041666667 | AR22: -0.0048611111 | AS22: Inicia tarde | AT22: Llega a Tiempo | AU22: Inicia tarde-Llega a Tiempo | AV22: 36 | AW22: No | AX22: Moctezuma San AgustinPEPSICO GDL | AY22: DANIEL | AZ22: Leopoldo V. | BA22: PEPSICO GDLMoctezuma San Agustin | BB22: E-PEP-R0009 | BC22: T1 | BD22: Moctezuma San Agustin-R0009-05:30
A23: 176543738 | B23: E-FOX-T1-R0050 | C23: LIPU Guadalajara | D23: Villas Terranova | E23: N | F23: 50 | G23: SUR | H23: 12898 | I23: 6 | J23: IN | K23: FOXCONN | L23: 46265 | M23: 0.22916667 | N23: 0.23263889 | O23: done | P23: 46265 | Q23: 0.28125 | R23: 0.26857639 | S23: done | T23: 1 | U23: 25 | V23: 27.27 | W23: 26.78 | X23: - | Y23: - | Z23: - | AA23: DURAN DIAZ MARIO ALBERTO | AB23: 14124143 | AC23: DURAN DIAZ MARIO ALBERTO | AD23: 14124143 | AE23: SISTEMA | AF23: AUTOMÁTICO | AG23: AUTOMÁTICO | AH23: 36 | AI23: Ok | AJ23: Retrasado,A tiempo | AK23: 0 | AL23: N/A | AM23: Variable por Ruta | AN23: Sin asignar | AO23: AUTOMÁTICO | AP23: - | AQ23: 0.0034722222 | AR23: -0.012673611 | AS23: Inicia tarde | AT23: Llega a Tiempo | AU23: Inicia tarde-Llega a Tiempo | AV23: 36 | AW23: No | AX23: Villas TerranovaFOXCONN | AY23: DIEGOVO. | AZ23: Leopoldo V. | BA23: FOXCONNVillas Terranova | BB23: E-FOX-R0050 | BC23: T1 | BD23: Villas Terranova-R0050-05:30
A24: 176547616 | B24: E-FOX-T1-R0098 | C24: LIPU Guadalajara | D24: El Colli | E24: N | F24: 98 | G24: NORTE | H24: 14692 | I24: 6 | J24: IN | K24: FOXCONN | L24: 46265 | M24: 0.22916667 | N24: 0.23611111 | O24: done | P24: 46265 | Q24: 0.28125 | R24: 0.27304398 | S24: done | T24: 1 | U24: 31 | V24: 26.76 | W24: 26.7 | X24: - | Y24: - | Z24: - | AA24: REA PINEDO SALVADOR MANUEL | AB24: 14123725 | AC24: REA PINEDO SALVADOR MANUEL | AD24: 14123725 | AE24: SISTEMA | AF24: AUTOMÁTICO | AG24: AUTOMÁTICO | AH24: 36 | AI24: Ok | AJ24: Retrasado,A tiempo | AK24: 0 | AL24: N/A | AM24: Variable por Ruta | AN24: Sin asignar | AO24: AUTOMÁTICO | AP24: 40 | AQ24: 0.0069444444 | AR24: -0.0082060185 | AS24: Inicia tarde | AT24: Llega a Tiempo | AU24: Inicia tarde-Llega a Tiempo | AV24: 36 | AW24: No | AX24: El ColliFOXCONN | AY24: CANDELAS | AZ24: Leopoldo V. | BA24: FOXCONNEl Colli | BB24: E-FOX-R0098 | BC24: T1 | BD24: El Colli-R0098-05:30
A25: 176549218 | B25: E-SM4-T1-R0237 | C25: LIPU Guadalajara | D25: Apoyo Adolf Horn T1 | E25: N | F25: 237 | H25: 5530 | I25: 6 | J25: IN | K25: SANMINA TLAJOMULCO | L25: 46265 | M25: 0.22916667 | N25: 0.23888889 | O25: done | P25: 46265 | Q25: 0.26736111 | R25: 0.26252315 | S25: done | T25: 1 | U25: 19 | V25: 17.27 | W25: 17.42 | X25: - | Y25: - | Z25: - | AA25: RODRIGUEZ LOPEZ ANGEL ALBERTO | AB25: 14120925 | AC25: RODRIGUEZ LOPEZ ANGEL ALBERTO | AD25: 14120925 | AE25: SISTEMA | AF25: AUTOMÁTICO | AG25: AUTOMÁTICO | AH25: 36 | AI25: Ok | AJ25: Retrasado,A tiempo | AK25: 0 | AL25: N/A | AM25: Variable por Ruta | AN25: Sin asignar | AO25: AUTOMÁTICO | AP25: - | AQ25: 0.0097222222 | AR25: -0.004837963 | AS25: Inicia tarde | AT25: Llega a Tiempo | AU25: Inicia tarde-Llega a Tiempo | AV25: 36 | AW25: No | AX25: Apoyo Adolf Horn T1SANMINA TLAJOMULCO | AY25: CUAUHTEMOC M. | AZ25: Felipe M. | BA25: SANMINA TLAJOMULCOApoyo Adolf Horn T1 | BB25: E-SM4-R0237 | BC25: T1 | BD25: Apoyo Adolf Horn T1-R0237-05:30
A26: 176545723 | B26: E-FOX-T1-R0073 | C26: LIPU Guadalajara | D26: Valle De Tejeda | E26: N | F26: 73 | G26: SUR | H26: 2528 | I26: 6 | J26: IN | K26: FOXCONN | L26: 46265 | M26: 0.23263889 | N26: 0.26111111 | O26: done | P26: 46265 | Q26: 0.28125 | R26: 0.32222222 | S26: done | T26: 1 | U26: 29 | V26: 22.09 | W26: 5.24 | X26: - | Y26: - | Z26: - | AA26: MENDOZA CARDONA JOSE ALEJANDRO | AB26: 14123634 | AC26: MENDOZA CARDONA JOSE ALEJANDRO | AD26: 14123634 | AE26: SISTEMA | AF26: AUTOMÁTICO | AG26: AUTOMÁTICO | AH26: 36 | AI26: Ok | AJ26: Retrasado | AK26: 0 | AL26: N/A | AM26: Variable por Ruta | AN26: Sin asignar | AO26: AUTOMÁTICO | AP26: - | AQ26: 0.028472222 | AR26: 0.040972222 | AS26: Inicia tarde | AT26: Llega tarde | AU26: Inicia tarde-Llega tarde | AV26: 36 | AW26: No | AX26: Valle De TejedaFOXCONN | AY26: CANDELAS | AZ26: Leopoldo V. | BA26: FOXCONNValle De Tejeda | BB26: E-FOX-R0073 | BC26: T1 | BD26: Valle De Tejeda-R0073-05:35
A27: 176538978 | B27: E-DJT-T1-R0001 | C27: LIPU Guadalajara | D27: Puga | E27: N | F27: 1 | H27: 7943 | I27: 6 | J27: IN | K27: DON JULIO TEPIC | L27: 46265 | M27: 0.23611111 | N27: 0.30486111 | O27: done | P27: 46265 | Q27: 0.33333333 | R27: 0.31736111 | S27: done | T27: 1 | U27: 29 | V27: 3.05 | W27: 1.75 | X27: 32.78 | Y27: 18.16 | Z27: 12.87 | AA27: VILLEGAS HUIZAR RAMIRO | AB27: 14122708 | AC27: VILLEGAS HUIZAR RAMIRO | AD27: 14122708 | AE27: SISTEMA | AF27: AUTOMÁTICO | AG27: AUTOMÁTICO | AH27: 36 | AI27: Ok | AJ27: Retrasado,A tiempo | AK27: - | AL27: 0 | AM27: Fijo más Variable por KM | AN27: Sin asignar | AO27: AUTOMÁTICO | AP27: - | AQ27: 0.06875 | AR27: -0.015972222 | AS27: Inicia tarde | AT27: Llega a Tiempo | AU27: Inicia tarde-Llega a Tiempo | AV27: 36 | AW27: No | AX27: PugaDON JULIO TEPIC | AY27: VIRIDIANA G | AZ27: Ilse M. | BA27: DON JULIO TEPIC Puga | BB27: E-DJT-R0001 | BC27: T1 | BD27: Puga-R0001-05:40
A28: 176544211 | B28: E-FOX-T1-R0069 | C28: LIPU Guadalajara | D28: Lomas del Mirador | E28: N | F28: 69 | G28: SUR | H28: 4982 | I28: 6 | J28: IN | K28: FOXCONN | L28: 46265 | M28: 0.23611111 | N28: 0.24097222 | O28: done | P28: 46265 | Q28: 0.28125 | R28: 0.28010417 | S28: done | T28: 1 | U28: 28 | V28: 22.72 | W28: 15.34 | X28: - | Y28: - | Z28: - | AA28: TORRES CAMPOS VICTOR MANUEL | AB28: 14111678 | AC28: TORRES CAMPOS VICTOR MANUEL | AD28: 14111678 | AE28: SISTEMA | AF28: AUTOMÁTICO | AG28: AUTOMÁTICO | AH28: 36 | AI28: Ok | AJ28: Retrasado,A tiempo | AK28: 0 | AL28: N/A | AM28: Variable por Ruta | AN28: Sin asignar | AO28: AUTOMÁTICO | AP28: - | AQ28: 0.0048611111 | AR28: -0.0011458333 | AS28: Inicia tarde | AT28: Llega a Tiempo | AU28: Inicia tarde-Llega a Tiempo | AV28: 36 | AW28: No | AX28: Lomas del MiradorFOXCONN | AY28: DIEGOVO. | AZ28: Leopoldo V. | BA28: FOXCONNLomas del Mirador | BB28: E-FOX-R0069 | BC28: T1 | BD28: Lomas del Mirador-R0069-05:40
A29: 176548851 | B29: E-FOX-T1-R0139 | C29: LIPU Guadalajara | D29: Apoyo Chulavista | E29: N | F29: 139 | G29: SUR | H29: 10359 | I29: 6 | J29: IN | K29: FOXCONN | L29: 46265 | M29: 0.23611111 | N29: 0.24166667 | O29: done | P29: 46265 | Q29: 0.28125 | R29: 0.26740741 | S29: done | T29: 1 | U29: 23 | V29: 23.47 | W29: 26.22 | X29: - | Y29: - | Z29: - | AA29: AGRIPINO ROBLES MARIO ALFONS | AB29: 14112026 | AC29: AGRIPINO ROBLES MARIO ALFONS | AD29: 14112026 | AE29: SISTEMA | AF29: AUTOMÁTICO | AG29: AUTOMÁTICO | AH29: 36 | AI29: Ok | AJ29: Retrasado,A tiempo | AK29: 0 | AL29: N/A | AM29: Variable por Ruta | AN29: Sin asignar | AO29: AUTOMÁTICO | AP29: 25 | AQ29: 0.0055555556 | AR29: -0.013842593 | AS29: Inicia tarde | AT29: Llega a Tiempo | AU29: Inicia tarde-Llega a Tiempo | AV29: 36 | AW29: No | AX29: Apoyo ChulavistaFOXCONN | AY29: DIEGOVO. | AZ29: Leopoldo V. | BA29: FOXCONNApoyo Chulavista | BB29: E-FOX-R0139 | BC29: T1 | BD29: Apoyo Chulavista-R0139-05:40
A30: 176550710 | B30: E-FOX-T1-R0256 | C30: LIPU Guadalajara | D30: Apoyo Valle de la Misericordia | E30: N | F30: 256 | G30: SUR | H30: 5353 | I30: 6 | J30: IN | K30: FOXCONN | L30: 46265 | M30: 0.23611111 | N30: 0.25416667 | O30: done | P30: 46265 | Q30: 0.28125 | R30: 0.28346065 | S30: done | T30: 1 | U30: 16 | V30: 11.79 | W30: 10.79 | X30: - | Y30: - | Z30: - | AA30: ROLDAN RODRIGUEZ LUIS ANGEL | AB30: 14123988 | AC30: ROLDAN RODRIGUEZ LUIS ANGEL | AD30: 14123988 | AE30: SISTEMA | AF30: AUTOMÁTICO | AG30: AUTOMÁTICO | AH30: 36 | AI30: Ok | AJ30: Retrasado | AK30: 0 | AL30: N/A | AM30: Variable por Ruta | AN30: Sin asignar | AO30: AUTOMÁTICO | AP30: - | AQ30: 0.018055556 | AR30: 0.0022106481 | AS30: Inicia tarde | AT30: Llega a Tiempo | AU30: Inicia tarde-Llega a Tiempo | AV30: 36 | AW30: No | AX30: Apoyo Valle de la MisericordiaFOXCONN | AY30: DIEGOVO. | AZ30: Leopoldo V. | BA30: FOXCONNApoyo Valle de la Misericordia | BB30: E-FOX-R0256 | BC30: T1 | BD30: Apoyo Valle de la Misericordia-R0256-05:40
A31: 176552029 | B31: E-FOX-T1-R0269 | C31: LIPU Guadalajara | D31: Hacienda Real | E31: N | F31: 269 | G31: Norte | H31: 6782 | I31: 6 | J31: IN | K31: FOXCONN | L31: 46265 | M31: 0.23611111 | N31: 0.24444444 | O31: done | P31: 46265 | Q31: 0.28125 | R31: 0.28069444 | S31: done | T31: 1 | U31: 18 | V31: 13.57 | W31: 14.28 | X31: - | Y31: - | Z31: - | AA31: REA PINEDO JUAN JOSE | AB31: 14122160 | AC31: REA PINEDO JUAN JOSE | AD31: 14122160 | AE31: SISTEMA | AF31: AUTOMÁTICO | AG31: AUTOMÁTICO | AH31: 36 | AI31: Ok | AJ31: Retrasado,A tiempo | AK31: 0 | AL31: N/A | AM31: Variable por Ruta | AN31: Sin asignar | AO31: AUTOMÁTICO | AP31: - | AQ31: 0.0083333333 | AR31: -0.00055555556 | AS31: Inicia tarde | AT31: Llega a Tiempo | AU31: Inicia tarde-Llega a Tiempo | AV31: 36 | AW31: No | AX31: Hacienda RealFOXCONN | AY31: CANDELAS | AZ31: Leopoldo V. | BA31: FOXCONNHacienda Real | BB31: #N/A | BC31: T1 | BD31: Hacienda Real-R0269-05:40
A32: 176538533 | B32: E-PAQ-T1-R0009 | C32: LIPU Guadalajara | D32: 8 De Julio | E32: N | F32: 9 | H32: 10362 | I32: 6 | J32: IN | K32: PAQUETEXPRESS GDL | L32: 46265 | M32: 0.24305556 | N32: 0.24652778 | O32: done | P32: 46265 | Q32: 0.29166667 | R32: 0.27924769 | S32: done | T32: 1 | U32: 27 | V32: -4308.22 | W32: 24 | X32: - | Y32: - | Z32: - | AA32: MARTINEZ PEREZ OSCAR IVAN | AB32: 14110465 | AC32: MARTINEZ PEREZ OSCAR IVAN | AD32: 14110465 | AE32: SISTEMA | AF32: AUTOMÁTICO | AG32: AUTOMÁTICO | AH32: 36 | AI32: Ok | AJ32: Retrasado,A tiempo | AK32: 1242 | AL32: 0 | AM32: Fijo más Variable por KM | AN32: Mensual | AO32: AUTOMÁTICO | AP32: - | AQ32: 0.0034722222 | AR32: -0.012418981 | AS32: Inicia tarde | AT32: Llega a Tiempo | AU32: Inicia tarde-Llega a Tiempo | AV32: 36 | AW32: No | AX32: 8 De JulioPAQUETEXPRESS GDL | AY32: DAVID D. | AZ32: Leopoldo V. | BA32: PAQUETEXPRESS GDL8 De Julio | BB32: E-PAQ-R0009 | BC32: T1 | BD32: 8 De Julio-R0009-05:50
A33: 176538981 | B33: E-DJT-T1-R0004 | C33: LIPU Guadalajara | D33: Pochotitan Mujeres | E33: N | F33: 4 | H33: 13295 | I33: 7 | J33: IN | K33: DON JULIO TEPIC | L33: 46265 | M33: 0.24305556 | N33: 0.26597222 | O33: done | P33: 46265 | Q33: 0.33333333 | S33: start | T33: 0 | U33: 17 | V33: 1.86 | W33: 16.48 | X33: 33.78 | Y33: 17.3 | Z33: 0 | AA33: ROSALES AVILA MAXIMILIANO | AB33: 14122706 | AC33: ROSALES AVILA MAXIMILIANO | AD33: 14122706 | AE33: SISTEMA | AF33: AUTOMÁTICO | AG33: AUTOMÁTICO | AH33: 36 | AI33: Ok,Cabina | AJ33: Retrasado | AK33: - | AL33: 0 | AM33: Fijo más Variable por KM | AN33: Sin asignar | AO33: AUTOMÁTICO | AP33: - | AQ33: 0.022916667 | AR33: -0.33333333 | AS33: Inicia tarde | AT33: Llega a Tiempo | AU33: Inicia tarde-Llega a Tiempo | AV33: 36 | AW33: No | AX33: Pochotitan MujeresDON JULIO TEPIC | AY33: VIRIDIANA G | AZ33: Ilse M. | BA33: DON JULIO TEPIC Pochotitan Mujeres | BB33: E-DJT-R0004 | BC33: T1 | BD33: Pochotitan Mujeres-R0004-05:50
A34: 176541176 | B34: E-ZFF-T1-R0049 | C34: LIPU Guadalajara | D34: ADM Santa Mago | E34: N | F34: 49 | H34: 6802 | I34: 6 | J34: IN | K34: ZF FORANEO | L34: 46265 | M34: 0.25 | N34: 0.25902778 | O34: done | P34: 46265 | Q34: 0.33333333 | R34: 0.3087037 | S34: done | T34: 1 | U34: 48 | V34: 46.59 | W34: 46.22 | X34: - | Y34: - | Z34: - | AA34: GOMEZ DELGADILLO MARCO ANTONIO | AB34: 14114431 | AC34: GOMEZ DELGADILLO MARCO ANTONIO | AD34: 14114431 | AE34: SISTEMA | AF34: AUTOMÁTICO | AG34: AUTOMÁTICO | AH34: 36 | AI34: Ok | AJ34: Retrasado,A tiempo | AK34: 0 | AL34: N/A | AM34: Variable por Ruta | AN34: Sin asignar | AO34: AUTOMÁTICO | AP34: - | AQ34: 0.0090277778 | AR34: -0.02462963 | AS34: Inicia tarde | AT34: Llega a Tiempo | AU34: Inicia tarde-Llega a Tiempo | AV34: 36 | AW34: No | AX34: ADM Santa MagoZF FORANEO | AY34: AGEO C. | AZ34: Ilse M. | BA34: ZF FORANEOADM Santa Mago | BB34: E-ZFF-R0049 | BC34: T1 | BD34: ADM Santa Mago-R0049-06:00
A35: 176544391 | B35: E-DJT-T1-R0009 | C35: LIPU Guadalajara | D35: San Fernando | E35: N | F35: 9 | H35: 14866 | I35: 5 | J35: IN | K35: DON JULIO TEPIC | L35: 46265 | M35: 0.25 | N35: 0.25486111 | O35: done | P35: 46265 | Q35: 0.33333333 | S35: start | U35: 17 | V35: - | W35: 20.4 | X35: 22.1 | Y35: 1.7 | Z35: 0 | AA35: VILLEGAS HUIZAR FERNANDO | AB35: 14108361 | AC35: VILLEGAS HUIZAR FERNANDO | AD35: 14108361 | AE35: SISTEMA | AF35: AUTOMÁTICO | AG35: AUTOMÁTICO | AH35: 36 | AI35: Ok,Cabina | AJ35: Retrasado | AK35: - | AL35: 0 | AM35: Fijo más Variable por KM | AN35: Sin asignar | AO35: AUTOMÁTICO | AP35: - | AQ35: 0.0048611111 | AR35: -0.33333333 | AS35: Inicia tarde | AT35: Llega a Tiempo | AU35: Inicia tarde-Llega a Tiempo | AV35: 36 | AW35: No | AX35: San FernandoDON JULIO TEPIC | AY35: VIRIDIANA G | AZ35: Ilse M. | BA35: DON JULIO TEPIC San Fernando | BB35: E-DJT-R0009 | BC35: T1 | BD35: San Fernando-R0009-06:00
A36: 176543628 | B36: E-MOL-T1-R0028 | C36: LIPU Guadalajara | D36: ADM Arcos de Zapopan | E36: N | F36: 28 | H36: 15485 | I36: 6 | J36: IN | K36: MOLEX | L36: 46265 | M36: 0.26041667 | N36: 0.26458333 | O36: done | P36: 46265 | Q36: 0.3125 | R36: 0.30070602 | S36: done | T36: 1 | U36: 62 | V36: 58.79 | W36: 58.84 | X36: - | Y36: - | Z36: - | AA36: DIAZ BLANQUET ROSA JANNET | AB36: 14110604 | AC36: DIAZ BLANQUET ROSA JANNET | AD36: 14110604 | AE36: SISTEMA | AF36: AUTOMÁTICO | AG36: AUTOMÁTICO | AH36: 36 | AI36: Ok | AJ36: Retrasado,A tiempo | AK36: 0 | AL36: N/A | AM36: Variable por Ruta | AN36: Sin asignar | AO36: AUTOMÁTICO | AP36: - | AQ36: 0.0041666667 | AR36: -0.011793981 | AS36: Inicia tarde | AT36: Llega a Tiempo | AU36: Inicia tarde-Llega a Tiempo | AV36: 36 | AW36: No | AX36: ADM Arcos de ZapopanMOLEX | AY36: VICTOR C. | AZ36: Leopoldo V. | BA36: MOLEXADM Arcos de Zapopan | BB36: E-MOL-R0028 | BC36: T1 | BD36: ADM Arcos de Zapopan-R0028-06:15
A37: 176538551 | B37: E-SK1-T1-R0001 | C37: LIPU Guadalajara | D37: ADM Calzada | E37: N | F37: 1 | G37: ADM | H37: 16783 | I37: 6 | J37: IN | K37: SANMINA KAMPUS 16 | L37: 46265 | M37: 0.27430556 | N37: 0.27916667 | O37: done | P37: 46265 | Q37: 0.33333333 | R37: 0.31969907 | S37: done | T37: 1 | U37: 28 | V37: 25.16 | W37: 25.31 | X37: - | Y37: - | Z37: - | AA37: SALAMANCA SALAS JOSE VICTORIAN | AB37: 14122067 | AC37: SALAMANCA SALAS JOSE VICTORIAN | AD37: 14122067 | AE37: SISTEMA | AF37: AUTOMÁTICO | AG37: AUTOMÁTICO | AH37: 36 | AI37: Ok | AJ37: Retrasado,A tiempo | AK37: 0 | AL37: N/A | AM37: Variable por Ruta | AN37: Sin asignar | AO37: AUTOMÁTICO | AP37: - | AQ37: 0.0048611111 | AR37: -0.013634259 | AS37: Inicia tarde | AT37: Llega a Tiempo | AU37: Inicia tarde-Llega a Tiempo | AV37: 36 | AW37: No | AX37: ADM CalzadaSANMINA KAMPUS 16 | AY37: BRIAN A. | AZ37: Felipe M. | BA37: SANMINA KAMPUS 16ADM Calzada | BB37: E-SK1-R0001 | BC37: T1 | BD37: ADM Calzada-R0001-06:35
A38: 176545063 | B38: E-SA4-T1-R0099 | C38: LIPU Guadalajara | D38: Ocotlan 2 | E38: N | F38: 99 | G38: ADM HM | H38: 17343 | I38: 6 | J38: IN | K38: SANMINA ADM | L38: 46265 | M38: 0.27638889 | N38: 0.30486111 | O38: done | P38: 46265 | Q38: 0.34722222 | R38: 0.35658565 | S38: done | T38: 1 | U38: 64 | V38: 60.42 | W38: 60.78 | X38: - | Y38: - | Z38: - | AA38: MEDINA SALAZAR CARLOS ERNESTO | AB38: 14115136 | AC38: MEDINA SALAZAR CARLOS ERNESTO | AD38: 14115136 | AE38: SISTEMA | AF38: AUTOMÁTICO | AG38: AUTOMÁTICO | AH38: 36 | AI38: Ok | AJ38: Retrasado | AK38: 0 | AL38: N/A | AM38: Variable por Ruta | AN38: Sin asignar | AO38: AUTOMÁTICO | AP38: - | AQ38: 0.028472222 | AR38: 0.0093634259 | AS38: Inicia tarde | AT38: Llega tarde | AU38: Inicia tarde-Llega tarde | AV38: 36 | AW38: No | AX38: Ocotlan 2SANMINA ADM | AY38: FELIPE G. | AZ38: Felipe M. | BA38: SANMINA ADMOcotlan 2 | BB38: E-SA4-R0099 | BC38: T1 | BD38: Ocotlan 2-R0099-06:38
A39: 176545047 | B39: E-SA4-T1-R0083 | C39: LIPU Guadalajara | D39: Gran Fonda | E39: N | F39: 83 | G39: ADM HM | H39: 6353 | I39: 6 | J39: IN | K39: SANMINA ADM | L39: 46265 | M39: 0.27777778 | N39: 0.30416667 | O39: done | P39: 46265 | Q39: 0.34722222 | R39: 0.34556713 | S39: done | T39: 1 | U39: 35 | V39: 28.43 | W39: 28.67 | X39: - | Y39: - | Z39: - | AA39: MAGDALENO RAMIREZ EDGAR ANTONI | AB39: 14121860 | AC39: MAGDALENO RAMIREZ EDGAR ANTONI | AD39: 14121860 | AE39: SISTEMA | AF39: AUTOMÁTICO | AG39: AUTOMÁTICO | AH39: 36 | AI39: Ok | AJ39: Retrasado,A tiempo | AK39: 0 | AL39: N/A | AM39: Variable por Ruta | AN39: Sin asignar | AO39: AUTOMÁTICO | AP39: - | AQ39: 0.026388889 | AR39: -0.0016550926 | AS39: Inicia tarde | AT39: Llega a Tiempo | AU39: Inicia tarde-Llega a Tiempo | AV39: 36 | AW39: No | AX39: Gran FondaSANMINA ADM | AY39: FELIPE G. | AZ39: Felipe M. | BA39: SANMINA ADMGran Fonda | BB39: E-SA4-R0083 | BC39: T1 | BD39: Gran Fonda-R0083-06:40
A40: 176545069 | B40: E-SA4-T1-R0105 | C40: LIPU Guadalajara | D40: Ocotlan 3 | E40: N | F40: 105 | G40: ADM HM | H40: 17340 | I40: 6 | J40: IN | K40: SANMINA ADM | L40: 46265 | M40: 0.27777778 | N40: 0.30277778 | O40: done | P40: 46265 | Q40: 0.34722222 | R40: 0.34395833 | S40: done | T40: 1 | U40: 47 | V40: 19.35 | W40: 43.42 | X40: - | Y40: - | Z40: - | AA40: LUNA SANDOVAL DAVID | AB40: 14108111 | AC40: LUNA SANDOVAL DAVID | AD40: 14108111 | AE40: SISTEMA | AF40: AUTOMÁTICO | AG40: AUTOMÁTICO | AH40: 36 | AI40: Ok | AJ40: Retrasado,A tiempo | AK40: 0 | AL40: N/A | AM40: Variable por Ruta | AN40: Sin asignar | AO40: AUTOMÁTICO | AP40: - | AQ40: 0.025 | AR40: -0.0032638889 | AS40: Inicia tarde | AT40: Llega a Tiempo | AU40: Inicia tarde-Llega a Tiempo | AV40: 36 | AW40: No | AX40: Ocotlan 3SANMINA ADM | AY40: FELIPE G. | AZ40: Felipe M. | BA40: SANMINA ADMOcotlan 3 | BB40: E-SA4-R0105 | BC40: T1 | BD40: Ocotlan 3-R0105-06:40
A41: 176538553 | B41: E-SK1-T1-R0003 | C41: LIPU Guadalajara | D41: ADM Patria | E41: N | F41: 3 | G41: ADM | H41: 14676 | I41: 6 | J41: IN | K41: SANMINA KAMPUS 16 | L41: 46265 | M41: 0.28125 | N41: 0.29444444 | O41: done | P41: 46265 | Q41: 0.33333333 | R41: 0.34251157 | S41: done | T41: 1 | U41: 27 | V41: 22.93 | W41: 24.75 | X41: - | Y41: - | Z41: - | AA41: VAZQUEZ CORTES MIGUEL ALEJANDR | AB41: 14115917 | AC41: VAZQUEZ CORTES MIGUEL ALEJANDR | AD41: 14115917 | AE41: SISTEMA | AF41: AUTOMÁTICO | AG41: AUTOMÁTICO | AH41: 36 | AI41: Ok | AJ41: Retrasado | AK41: 0 | AL41: N/A | AM41: Variable por Ruta | AN41: Sin asignar | AO41: AUTOMÁTICO | AP41: - | AQ41: 0.013194444 | AR41: 0.0091782407 | AS41: Inicia tarde | AT41: Llega tarde | AU41: Inicia tarde-Llega tarde | AV41: 36 | AW41: No | AX41: ADM PatriaSANMINA KAMPUS 16 | AY41: BRIAN A. | AZ41: Felipe M. | BA41: SANMINA KAMPUS 16ADM Patria | BB41: E-SK1-R0003 | BC41: T1 | BD41: ADM Patria-R0003-06:45
A42: 176545080 | B42: E-SA4-T1-R0116 | C42: LIPU Guadalajara | D42: Tlajomulco | E42: N | F42: 116 | G42: ADM CM | H42: 16768 | I42: 6 | J42: IN | K42: SANMINA ADM | L42: 46265 | M42: 0.28125 | N42: 0.28472222 | O42: done | P42: 46265 | Q42: 0.34722222 | R42: 0.3337037 | S42: done | T42: 1 | U42: 43 | V42: 41.1 | W42: 41.14 | X42: - | Y42: - | Z42: - | AA42: LARIOS ALCARAZ EDUARDO | AB42: 14100729 | AC42: LARIOS ALCARAZ EDUARDO | AD42: 14100729 | AE42: SISTEMA | AF42: AUTOMÁTICO | AG42: AUTOMÁTICO | AH42: 36 | AI42: Ok | AJ42: Retrasado,A tiempo | AK42: 0 | AL42: N/A | AM42: Variable por Ruta | AN42: Sin asignar | AO42: AUTOMÁTICO | AP42: 32 | AQ42: 0.0034722222 | AR42: -0.013518519 | AS42: Inicia tarde | AT42: Llega a Tiempo | AU42: Inicia tarde-Llega a Tiempo | AV42: 36 | AW42: No | AX42: TlajomulcoSANMINA ADM | AY42: FELIPE G. | AZ42: Felipe M. | BA42: SANMINA ADMTlajomulco | BB42: E-SA4-R0116 | BC42: T1 | BD42: Tlajomulco-R0116-06:45
A43: 176545077 | B43: E-SA4-T1-R0113 | C43: LIPU Guadalajara | D43: Sauz | E43: N | F43: 113 | G43: ADM CM | H43: 16736 | I43: 6 | J43: IN | K43: SANMINA ADM | L43: 46265 | M43: 0.28333333 | N43: 0.28958333 | O43: done | P43: 46265 | Q43: 0.34722222 | R43: 0.32273148 | S43: done | T43: 1 | U43: 30 | V43: 25.51 | W43: 27.57 | X43: - | Y43: - | Z43: - | AA43: OLIVARES HERNANDEZ GABRIEL | AB43: 14100740 | AC43: OLIVARES HERNANDEZ GABRIEL | AD43: 14100740 | AE43: SISTEMA | AF43: AUTOMÁTICO | AG43: AUTOMÁTICO | AH43: 36 | AI43: Ok | AJ43: Retrasado,A tiempo | AK43: 0 | AL43: N/A | AM43: Variable por Ruta | AN43: Sin asignar | AO43: AUTOMÁTICO | AP43: - | AQ43: 0.00625 | AR43: -0.024490741 | AS43: Inicia tarde | AT43: Llega a Tiempo | AU43: Inicia tarde-Llega a Tiempo | AV43: 36 | AW43: No | AX43: SauzSANMINA ADM | AY43: FELIPE G. | AZ43: Felipe M. | BA43: SANMINA ADMSauz | BB43: E-SA4-R0113 | BC43: T1 | BD43: Sauz-R0113-06:48
A44: 176544492 | B44: E-MAB-T1-R0022 | C44: LIPU Guadalajara | D44: Sabinos- Santa Rosa | E44: N | F44: 22 | H44: 13447 | I44: 6 | J44: IN | K44: MABE GDL | L44: 46265 | M44: 0.28472222 | N44: 0.29305556 | O44: done | P44: 46265 | Q44: 0.32638889 | R44: 0.32774306 | S44: done | T44: 1 | U44: 35 | V44: 24.28 | W44: 28.09 | X44: - | Y44: - | Z44: - | AA44: SANCHEZ DEL CARMEN HERIBERTO | AB44: 14120091 | AC44: SANCHEZ DEL CARMEN HERIBERTO | AD44: 14120091 | AE44: SISTEMA | AF44: AUTOMÁTICO | AG44: AUTOMÁTICO | AH44: 36 | AI44: Ok | AJ44: Retrasado | AK44: 0 | AL44: N/A | AM44: Variable por Ruta | AN44: Sin asignar | AO44: AUTOMÁTICO | AP44: - | AQ44: 0.0083333333 | AR44: 0.0013541667 | AS44: Inicia tarde | AT44: Llega a Tiempo | AU44: Inicia tarde-Llega a Tiempo | AV44: 36 | AW44: No | AX44: Sabinos- Santa RosaMABE GDL | AY44: OSCAR I | AZ44: Ilse M. | BA44: MABE GDLSabinos- Santa Rosa | BB44: E-MAB-R0022 | BC44: T1 | BD44: Sabinos- Santa Rosa-R0022-06:50
A45: 176545040 | B45: E-SA4-T1-R0076 | C45: LIPU Guadalajara | D45: Ajijic Chapala | E45: N | F45: 76 | G45: ADM HM | H45: 13408 | I45: 6 | J45: IN | K45: SANMINA ADM | L45: 46265 | M45: 0.28472222 | N45: 0.30277778 | O45: done | P45: 46265 | Q45: 0.34722222 | R45: 0.34092593 | S45: done | T45: 1 | U45: 35 | V45: 33.73 | W45: 33.82 | X45: - | Y45: - | Z45: - | AA45: RAMIREZ MIRAMONTES MARTIN ALEJANDRO | AB45: 14123559 | AC45: RAMIREZ MIRAMONTES MARTIN ALEJANDRO | AD45: 14123559 | AE45: SISTEMA | AF45: AUTOMÁTICO | AG45: AUTOMÁTICO | AH45: 36 | AI45: Ok | AJ45: Retrasado,A tiempo | AK45: 0 | AL45: N/A | AM45: Variable por Ruta | AN45: Sin asignar | AO45: AUTOMÁTICO | AP45: - | AQ45: 0.018055556 | AR45: -0.0062962963 | AS45: Inicia tarde | AT45: Llega a Tiempo | AU45: Inicia tarde-Llega a Tiempo | AV45: 36 | AW45: No | AX45: Ajijic ChapalaSANMINA ADM | AY45: FELIPE G. | AZ45: Felipe M. | BA45: SANMINA ADMAjijic Chapala | BB45: E-SA4-R0076 | BC45: T1 | BD45: Ajijic Chapala-R0076-06:50
A46: 176543829 | B46: E-FOX-T1-R0052 | C46: LIPU Guadalajara | D46: ADM Oblatos | E46: N | F46: 52 | H46: 15335 | I46: 6 | J46: IN | K46: FOXCONN | L46: 46265 | M46: 0.29513889 | N46: 0.30208333 | O46: done | P46: 46265 | Q46: 0.34722222 | R46: 0.35167824 | S46: done | T46: 1 | U46: 28 | V46: 23.65 | W46: 23.14 | X46: - | Y46: - | Z46: - | AA46: VAZQUEZ FLORES DANIEL | AB46: 14123273 | AC46: VAZQUEZ FLORES DANIEL | AD46: 14123273 | AE46: SISTEMA | AF46: AUTOMÁTICO | AG46: AUTOMÁTICO | AH46: 36 | AI46: Ok | AJ46: Retrasado | AK46: 0 | AL46: N/A | AM46: Variable por Ruta | AN46: Sin asignar | AO46: AUTOMÁTICO | AP46: - | AQ46: 0.0069444444 | AR46: 0.0044560185 | AS46: Inicia tarde | AT46: Llega tarde | AU46: Inicia tarde-Llega tarde | AV46: 36 | AW46: No | AX46: ADM OblatosFOXCONN | AY46: CANDELAS | AZ46: Leopoldo V. | BA46: FOXCONNADM Oblatos | BB46: E-FOX-R0052 | BC46: T1 | BD46: ADM Oblatos-R0052-07:05
A47: 176545073 | B47: E-SA4-T1-R0109 | C47: LIPU Guadalajara | D47: Santa fe Combinado | E47: N | F47: 109 | G47: ADM CM | H47: 15995 | I47: 6 | J47: IN | K47: SANMINA ADM | L47: 46265 | M47: 0.29513889 | N47: 0.30763889 | O47: done | P47: 46265 | Q47: 0.34722222 | R47: 0.34206019 | S47: done | T47: 1 | U47: 22 | V47: 18.81 | W47: 19.27 | X47: - | Y47: - | Z47: - | AA47: RAMIREZ RAMIREZ ADRIAN | AB47: 14121015 | AC47: RAMIREZ RAMIREZ ADRIAN | AD47: 14121015 | AE47: SISTEMA | AF47: AUTOMÁTICO | AG47: AUTOMÁTICO | AH47: 36 | AI47: Ok | AJ47: Retrasado,A tiempo | AK47: 0 | AL47: N/A | AM47: Variable por Ruta | AN47: Sin asignar | AO47: AUTOMÁTICO | AP47: - | AQ47: 0.0125 | AR47: -0.005162037 | AS47: Inicia tarde | AT47: Llega a Tiempo | AU47: Inicia tarde-Llega a Tiempo | AV47: 36 | AW47: No | AX47: Santa fe CombinadoSANMINA ADM | AY47: FELIPE G. | AZ47: Felipe M. | BA47: SANMINA ADMSanta fe Combinado | BB47: E-SA4-R0109 | BC47: T1 | BD47: Santa fe Combinado-R0109-07:05
A48: 176545043 | B48: E-SA4-T1-R0079 | C48: LIPU Guadalajara | D48: El Salto 2 | E48: N | F48: 79 | G48: ADM HM | H48: 17342 | I48: 6 | J48: IN | K48: SANMINA ADM | L48: 46265 | M48: 0.29791667 | N48: 0.31875 | O48: done | P48: 46265 | Q48: 0.34722222 | R48: 0.34524306 | S48: done | T48: 1 | U48: 17 | V48: 13.74 | W48: 13.42 | X48: - | Y48: - | Z48: - | AA48: ORTIZ GARCIA LUIS ALBERTO | AB48: 14100724 | AC48: ORTIZ GARCIA LUIS ALBERTO | AD48: 14100724 | AE48: SISTEMA | AF48: AUTOMÁTICO | AG48: AUTOMÁTICO | AH48: 36 | AI48: Ok | AJ48: Retrasado,A tiempo | AK48: 0 | AL48: N/A | AM48: Variable por Ruta | AN48: Sin asignar | AO48: AUTOMÁTICO | AP48: - | AQ48: 0.020833333 | AR48: -0.0019791667 | AS48: Inicia tarde | AT48: Llega a Tiempo | AU48: Inicia tarde-Llega a Tiempo | AV48: 36 | AW48: No | AX48: El Salto 2SANMINA ADM | AY48: FELIPE G. | AZ48: Felipe M. | BA48: SANMINA ADMEl Salto 2 | BB48: E-SA4-R0079 | BC48: T1 | BD48: El Salto 2-R0079-07:09
A49: 176549443 | B49: E-FOX-T1-R0203 | C49: LIPU Guadalajara | D49: ADM Mariano Otero | E49: N | F49: 203 | G49: NORTE | H49: 13502 | I49: 6 | J49: IN | K49: FOXCONN | L49: 46265 | M49: 0.3 | N49: 0.30763889 | O49: done | P49: 46265 | Q49: 0.34722222 | R49: 0.33234954 | S49: done | T49: 1 | U49: 24 | V49: 19.28 | W49: 18.98 | X49: - | Y49: - | Z49: - | AA49: GARCIA GAYTAN ALDO LEONARDO | AB49: 14123591 | AC49: GARCIA GAYTAN ALDO LEONARDO | AD49: 14123591 | AE49: SISTEMA | AF49: AUTOMÁTICO | AG49: AUTOMÁTICO | AH49: 36 | AI49: Ok | AJ49: Retrasado,A tiempo | AK49: 0 | AL49: N/A | AM49: Variable por Ruta | AN49: Sin asignar | AO49: AUTOMÁTICO | AP49: - | AQ49: 0.0076388889 | AR49: -0.014872685 | AS49: Inicia tarde | AT49: Llega a Tiempo | AU49: Inicia tarde-Llega a Tiempo | AV49: 36 | AW49: No | AX49: ADM Mariano OteroFOXCONN | AY49: CANDELAS | AZ49: Leopoldo V. | BA49: FOXCONNADM Mariano Otero | BB49: E-FOX-R0203 | BC49: T1 | BD49: ADM Mariano Otero-R0203-07:12
A50: 176535582 | B50: E-CAB-T1-R0005 | C50: LIPU Guadalajara | D50: Periférico | E50: N | F50: 5 | H50: 4978 | I50: 6 | J50: IN | K50: CABRERA LLAMAS GDL | L50: 46265 | M50: 0.32291667 | N50: 0.32638889 | O50: done | P50: 46265 | Q50: 0.37361111 | R50: 0.36890046 | S50: done | T50: 1 | U50: 30 | V50: 28.3 | W50: 28.41 | X50: - | Y50: - | Z50: - | AA50: PADILLA MORENO RENE | AB50: 14122291 | AC50: PADILLA MORENO RENE | AD50: 14122291 | AE50: SISTEMA | AF50: AUTOMÁTICO | AG50: AUTOMÁTICO | AH50: 36 | AI50: Ok | AJ50: Retrasado,A tiempo | AK50: 0 | AL50: N/A | AM50: Variable por Ruta | AN50: Sin asignar | AO50: AUTOMÁTICO | AP50: - | AQ50: 0.0034722222 | AR50: -0.0047106481 | AS50: Inicia tarde | AT50: Llega a Tiempo | AU50: Inicia tarde-Llega a Tiempo | AV50: 36 | AW50: No | AX50: PeriféricoCABRERA LLAMAS GDL | AY50: DAVID M | AZ50: Ilse M. | BA50: CABRERA LLAMAS GDLPeriférico | BB50: E-CAB-R0005 | BC50: T1 | BD50: Periférico-R0005-07:45
A51: 176530482 | B51: E-PEP-T2-R0007 | C51: LIPU Guadalajara | D51: Moctezuma San Sebastian | E51: N | F51: 7 | H51: 6063 | I51: 6 | J51: IN | K51: PEPSICO GDL | L51: 46265 | M51: 0.51388889 | N51: 0.53541667 | O51: done | P51: 46265 | Q51: 0.60416667 | R51: 0.60069444 | S51: done | T51: 1 | U51: 38 | V51: 31.5 | W51: 24.75 | X51: - | Y51: - | Z51: - | AA51: GARDUÑO LOPEZ MANUEL | AB51: 14123336 | AC51: GARDUÑO LOPEZ MANUEL | AD51: 14123336 | AE51: SISTEMA | AF51: AUTOMÁTICO | AG51: AUTOMÁTICO | AH51: 36 | AI51: Ok | AJ51: Retrasado,A tiempo | AK51: 612.41 | AL51: N/A | AM51: Variable por Ruta | AN51: Sin asignar | AO51: AUTOMÁTICO | AP51: - | AQ51: 0.021527778 | AR51: -0.0034722222 | AS51: Inicia tarde | AT51: Llega a Tiempo | AU51: Inicia tarde-Llega a Tiempo | AV51: 36 | AW51: No | AX51: Moctezuma San SebastianPEPSICO GDL | AY51: DANIEL | AZ51: Leopoldo V. | BA51: PEPSICO GDLMoctezuma San Sebastian | BB51: E-PEP-R0007 | BC51: T2 | BD51: Moctezuma San Sebastian-R0007-12:20
A52: 176531487 | B52: E-CUP-T2-R0001 | C52: LIPU Guadalajara | D52: Chulavista | E52: N | F52: 1 | H52: 5351 | I52: 6 | J52: IN | K52: CUPRUM GDL | L52: 46265 | M52: 0.51388889 | N52: 0.51736111 | O52: done | P52: 46265 | Q52: 0.57986111 | R52: 0.57274306 | S52: done | T52: 1 | U52: 26 | V52: 21.32 | W52: 20.67 | X52: - | Y52: - | Z52: - | AA52: ESTRADA ALVAREZ FERNANDO | AB52: 14102730 | AC52: ESTRADA ALVAREZ FERNANDO | AD52: 14102730 | AE52: SISTEMA | AF52: AUTOMÁTICO | AG52: AUTOMÁTICO | AH52: 36 | AI52: Ok | AJ52: Retrasado,A tiempo | AK52: 522.74 | AL52: N/A | AM52: Variable por Ruta | AN52: Sin asignar | AO52: AUTOMÁTICO | AP52: 12 | AQ52: 0.0034722222 | AR52: -0.0071180556 | AS52: Inicia tarde | AT52: Llega a Tiempo | AU52: Inicia tarde-Llega a Tiempo | AV52: 36 | AW52: No | AX52: ChulavistaCUPRUM GDL | AY52: DAVID M | AZ52: Ilse M. | BA52: CUPRUM GDLChulavista | BB52: E-CUP-R0001 | BC52: T2 | BD52: Chulavista-R0001-12:20
A53: 176540491 | B53: E-SOR-T2-R0033 | C53: LIPU Guadalajara | D53: El Vado | E53: N | F53: 33 | H53: 11387 | I53: 6 | J53: IN | K53: SORIANA GDL | L53: 46265 | M53: 0.52083333 | N53: 0.53194444 | O53: done | P53: 46265 | Q53: 0.57291667 | R53: 0.5815162 | S53: done | T53: 1 | U53: 32 | V53: 27.89 | W53: 28.12 | X53: - | Y53: - | Z53: - | AC53: OPERADOR NO REGISTRADO | AE53: SISTEMA | AF53: AUTOMÁTICO | AG53: AUTOMÁTICO | AH53: 36 | AI53: Ok | AJ53: Retrasado | AK53: 0 | AL53: N/A | AM53: Variable por Ruta | AN53: Sin asignar | AO53: AUTOMÁTICO | AP53: - | AQ53: 0.011111111 | AR53: 0.008599537 | AS53: Inicia tarde | AT53: Llega tarde | AU53: Inicia tarde-Llega tarde | AV53: 36 | AW53: No | AX53: El VadoSORIANA GDL | AY53: OSCAR I | AZ53: Ilse M. | BA53: SORIANA GDLEl Vado | BB53: E-SOR-R0033 | BC53: T2 | BD53: El Vado-R0033-12:30
A54: 176541810 | B54: E-HER-T2-R0017 | C54: LIPU Guadalajara | D54: Arenales | E54: N | F54: 17 | H54: 15192 | I54: 6 | J54: IN | K54: HERSHEYS | L54: 46265 | M54: 0.52083333 | N54: 0.53402778 | O54: done | P54: 46265 | Q54: 0.60416667 | R54: 0.58951389 | S54: done | T54: 1 | U54: 37 | V54: 33.03 | W54: 37.52 | X54: - | Y54: - | Z54: - | AA54: ZUÑIGA CARRILLO CHRISTIAN ALEJ | AB54: 14122103 | AC54: ZUÑIGA CARRILLO CHRISTIAN ALEJ | AD54: 14122103 | AE54: SISTEMA | AF54: AUTOMÁTICO | AG54: AUTOMÁTICO | AH54: 36 | AI54: Ok | AJ54: Retrasado,A tiempo | AK54: 815 | AL54: N/A | AM54: Variable por Ruta | AN54: Sin asignar | AO54: AUTOMÁTICO | AP54: - | AQ54: 0.013194444 | AR54: -0.014652778 | AS54: Inicia tarde | AT54: Llega a Tiempo | AU54: Inicia tarde-Llega a Tiempo | AV54: 36 | AW54: No | AX54: ArenalesHERSHEYS | AY54: CARLOS C. | AZ54: Ilse M. | BA54: HERSHEYSArenales | BB54: E-HER-R0017 | BC54: T2 | BD54: Arenales-R0017-12:30
A55: 176550818 | B55: E-ONT-T2-R0003 | C55: LIPU Guadalajara | D55: Jamay | E55: N | F55: 3 | H55: 11852 | I55: 6 | J55: IN | K55: ONEST | L55: 46265 | M55: 0.52569444 | N55: 0.54513889 | O55: done | P55: 46265 | Q55: 0.57291667 | R55: 0.56603009 | S55: done | T55: 1 | U55: 64 | V55: 52.13 | W55: 30.48 | X55: - | Y55: - | Z55: - | AA55: CASTAÑEDA VALENZUELA JUAN DANIEL | AB55: 14123193 | AC55: CASTAÑEDA VALENZUELA JUAN DANIEL | AD55: 14123193 | AE55: SISTEMA | AF55: AUTOMÁTICO | AG55: AUTOMÁTICO | AH55: 36 | AI55: Ok | AJ55: Retrasado,A tiempo | AK55: 0 | AL55: N/A | AM55: Variable por Ruta | AN55: Sin asignar | AO55: AUTOMÁTICO | AP55: - | AQ55: 0.019444444 | AR55: -0.0068865741 | AS55: Inicia tarde | AT55: Llega a Tiempo | AU55: Inicia tarde-Llega a Tiempo | AV55: 36 | AW55: No | AX55: JamayONEST | AY55: VIRIDIANA G | AZ55: Ilse M. | BA55: ONESTJamay | BB55: E-ONT-R0003 | BC55: T2 | BD55: Jamay-R0003-12:37
A56: 176538828 | B56: E-SM4-T2-R0101 | C56: LIPU Guadalajara | D56: Lomas de San Agustin | E56: N | F56: 101 | H56: 10747 | I56: 6 | J56: IN | K56: SANMINA TLAJOMULCO | L56: 46265 | M56: 0.52777778 | N56: 0.53194444 | O56: done | P56: 46265 | Q56: 0.60069444 | R56: 0.57461806 | S56: done | T56: 1 | U56: 43 | V56: 36.2 | W56: 37.23 | X56: - | Y56: - | Z56: - | AA56: BRISEÑO TOVAR ORLANDO FABIAN | AB56: 14123488 | AC56: BRISEÑO TOVAR ORLANDO FABIAN | AD56: 14123488 | AE56: SISTEMA | AF56: AUTOMÁTICO | AG56: AUTOMÁTICO | AH56: 36 | AI56: Ok | AJ56: Retrasado,A tiempo | AK56: 0 | AL56: N/A | AM56: Variable por Ruta | AN56: Sin asignar | AO56: AUTOMÁTICO | AP56: - | AQ56: 0.0041666667 | AR56: -0.026076389 | AS56: Inicia tarde | AT56: Llega a Tiempo | AU56: Inicia tarde-Llega a Tiempo | AV56: 36 | AW56: No | AX56: Lomas de San AgustinSANMINA TLAJOMULCO | AY56: CUAUHTEMOC M. | AZ56: Felipe M. | BA56: SANMINA TLAJOMULCOLomas de San Agustin | BB56: E-SM4-R0101 | BC56: T2 | BD56: Lomas de San Agustin-R0101-12:40
A57: 176548513 | B57: E-SAN-T2-R0497 | C57: LIPU Guadalajara | D57: Zapopan T2 y T3 | E57: N | F57: 497 | H57: 5719 | I57: 6 | J57: IN | K57: SANMINA GDL | L57: 46265 | M57: 0.52777778 | N57: 0.54166667 | O57: done | P57: 46265 | Q57: 0.60069444 | R57: 0.60445602 | S57: done | T57: 1 | U57: 43 | V57: 35.04 | W57: 39.74 | X57: - | Y57: - | Z57: - | AA57: VILLAGRAN PEREZ ARMANDO | AB57: 14115536 | AC57: VILLAGRAN PEREZ ARMANDO | AD57: 14115536 | AE57: SISTEMA | AF57: AUTOMÁTICO | AG57: AUTOMÁTICO | AH57: 36 | AI57: Ok | AJ57: Retrasado | AK57: 0 | AL57: N/A | AM57: Variable por Ruta | AN57: Sin asignar | AO57: AUTOMÁTICO | AP57: - | AQ57: 0.013888889 | AR57: 0.0037615741 | AS57: Inicia tarde | AT57: Llega tarde | AU57: Inicia tarde-Llega tarde | AV57: 36 | AW57: No | AX57: Zapopan T2 y T3SANMINA GDL | AY57: PABLO F. | AZ57: Felipe M. | BA57: SANMINA GDLZapopan T2 y T3 | BB57: E-SAN-R0497 | BC57: T2 | BD57: Zapopan T2 y T3-R0497-12:40
A58: 176531118 | B58: E-SAN-T2-R0061 | C58: LIPU Guadalajara | D58: Bethel | E58: N | F58: 61 | H58: 16744 | I58: 6 | J58: IN | K58: SANMINA GDL | L58: 46265 | M58: 0.53472222 | N58: 0.53819444 | O58: done | P58: 46265 | Q58: 0.60069444 | R58: 0.58511574 | S58: done | T58: 1 | U58: 46 | V58: 42.96 | W58: 45.56 | X58: - | Y58: - | Z58: - | AA58: CASTAÑEDA AGUILAR LUIS ANTONIO | AB58: 14119956 | AC58: CASTAÑEDA AGUILAR LUIS ANTONIO | AD58: 14119956 | AE58: SISTEMA | AF58: AUTOMÁTICO | AG58: AUTOMÁTICO | AH58: 36 | AI58: Ok | AJ58: Retrasado,A tiempo | AK58: 530.63 | AL58: N/A | AM58: Variable por Ruta | AN58: Sin asignar | AO58: AUTOMÁTICO | AP58: - | AQ58: 0.0034722222 | AR58: -0.015578704 | AS58: Inicia tarde | AT58: Llega a Tiempo | AU58: Inicia tarde-Llega a Tiempo | AV58: 36 | AW58: No | AX58: BethelSANMINA GDL | AY58: PABLO F. | AZ58: Felipe M. | BA58: SANMINA GDLBethel | BB58: E-SAN-R0061 | BC58: T2 | BD58: Bethel-R0061-12:50
A59: 176531133 | B59: E-SAN-T2-R0068 | C59: LIPU Guadalajara | D59: Panteon | E59: N | F59: 68 | H59: 16363 | I59: 6 | J59: IN | K59: SANMINA GDL | L59: 46265 | M59: 0.53472222 | N59: 0.54375 | O59: done | P59: 46265 | Q59: 0.60069444 | R59: 0.58827546 | S59: done | T59: 1 | U59: 33 | V59: 28.2 | W59: 29.01 | X59: - | Y59: - | Z59: - | AA59: CARRILLO DUEÑAS ANDRES DE JESUS | AB59: 14124189 | AC59: CARRILLO DUEÑAS ANDRES DE JESUS | AD59: 14124189 | AE59: SISTEMA | AF59: AUTOMÁTICO | AG59: AUTOMÁTICO | AH59: 36 | AI59: Ok | AJ59: Retrasado,A tiempo | AK59: 530.63 | AL59: N/A | AM59: Variable por Ruta | AN59: Sin asignar | AO59: AUTOMÁTICO | AP59: - | AQ59: 0.0090277778 | AR59: -0.012418981 | AS59: Inicia tarde | AT59: Llega a Tiempo | AU59: Inicia tarde-Llega a Tiempo | AV59: 36 | AW59: No | AX59: PanteonSANMINA GDL | AY59: PABLO F. | AZ59: Felipe M. | BA59: SANMINA GDLPanteon | BB59: E-SAN-R0068 | BC59: T2 | BD59: Panteon-R0068-12:50
A60: 176544710 | B60: E-SM4-T2-R0142 | C60: LIPU Guadalajara | D60: Prepa 13 T2 y T3 | E60: N | F60: 142 | H60: 15993 | I60: 6 | J60: IN | K60: SANMINA TLAJOMULCO | L60: 46265 | M60: 0.53472222 | N60: 0.53819444 | O60: done | P60: 46265 | Q60: 0.60069444 | R60: 0.59663194 | S60: done | T60: 1 | U60: 38 | V60: 30.23 | W60: 33.53 | X60: - | Y60: - | Z60: - | AA60: CHAVEZ PALOMARES MARIANO | AB60: 14123925 | AC60: CHAVEZ PALOMARES MARIANO | AD60: 14123925 | AE60: SISTEMA | AF60: AUTOMÁTICO | AG60: AUTOMÁTICO | AH60: 36 | AI60: Ok | AJ60: Retrasado,A tiempo | AK60: 0 | AL60: N/A | AM60: Variable por Ruta | AN60: Sin asignar | AO60: AUTOMÁTICO | AP60: - | AQ60: 0.0034722222 | AR60: -0.0040625 | AS60: Inicia tarde | AT60: Llega a Tiempo | AU60: Inicia tarde-Llega a Tiempo | AV60: 36 | AW60: No | AX60: Prepa 13 T2 y T3SANMINA TLAJOMULCO | AY60: CUAUHTEMOC M. | AZ60: Felipe M. | BA60: SANMINA TLAJOMULCOPrepa 13 T2 y T3 | BB60: E-SM4-R0142 | BC60: T2 | BD60: Prepa 13 T2 y T3-R0142-12:50
A61: 176530496 | B61: E-PEP-T2-R0009 | C61: LIPU Guadalajara | D61: Moctezuma San Agustin | E61: N | F61: 9 | H61: 5923 | I61: 6 | J61: IN | K61: PEPSICO GDL | L61: 46265 | M61: 0.53819444 | N61: 0.54305556 | O61: done | P61: 46265 | Q61: 0.60416667 | R61: 0.575 | S61: done | T61: 1 | U61: 22 | V61: 12.46 | W61: 17.14 | X61: 34.42 | Y61: 14.74 | Z61: 2.54 | AA61: HERNANDEZ GALLEGOS HECTOR ABRA | AB61: 14122133 | AC61: HERNANDEZ GALLEGOS HECTOR ABRA | AD61: 14122133 | AE61: SISTEMA | AF61: AUTOMÁTICO | AG61: AUTOMÁTICO | AH61: 36 | AI61: Ok | AJ61: Retrasado,A tiempo | AK61: 544.9 | AL61: N/A | AM61: Variable por Ruta | AN61: Sin asignar | AO61: AUTOMÁTICO | AP61: - | AQ61: 0.0048611111 | AR61: -0.029166667 | AS61: Inicia tarde | AT61: Llega a Tiempo | AU61: Inicia tarde-Llega a Tiempo | AV61: 36 | AW61: No | AX61: Moctezuma San AgustinPEPSICO GDL | AY61: DANIEL | AZ61: Leopoldo V. | BA61: PEPSICO GDLMoctezuma San Agustin | BB61: E-PEP-R0009 | BC61: T2 | BD61: Moctezuma San Agustin-R0009-12:55
A62: 176538846 | B62: E-SM4-T2-R0109 | C62: LIPU Guadalajara | D62: San Sebastian 1 T2 y T3 | E62: N | F62: 109 | H62: 5672 | I62: 6 | J62: IN | K62: SANMINA TLAJOMULCO | L62: 46265 | M62: 0.53819444 | N62: 0.54236111 | O62: done | P62: 46265 | Q62: 0.60069444 | R62: 0.58070602 | S62: done | T62: 1 | U62: 42 | V62: 25.13 | W62: 27.15 | X62: - | Y62: - | Z62: - | AA62: GARCIA RAMIREZ EZEQUIEL | AB62: 14124002 | AC62: GARCIA RAMIREZ EZEQUIEL | AD62: 14124002 | AE62: SISTEMA | AF62: AUTOMÁTICO | AG62: AUTOMÁTICO | AH62: 36 | AI62: Ok | AJ62: Retrasado,A tiempo | AK62: 0 | AL62: N/A | AM62: Variable por Ruta | AN62: Sin asignar | AO62: AUTOMÁTICO | AP62: 43 | AQ62: 0.0041666667 | AR62: -0.019988426 | AS62: Inicia tarde | AT62: Llega a Tiempo | AU62: Inicia tarde-Llega a Tiempo | AV62: 36 | AW62: No | AX62: San Sebastian 1 T2 y T3SANMINA TLAJOMULCO | AY62: CUAUHTEMOC M. | AZ62: Felipe M. | BA62: SANMINA TLAJOMULCOSan Sebastian 1 T2 y T3 | BB62: E-SM4-R0109 | BC62: T2 | BD62: San Sebastian 1 T2 y T3-R0109-12:55
A63: 176541780 | B63: E-HER-T2-R0007 | C63: LIPU Guadalajara | D63: Tonala | E63: N | F63: 7 | H63: 15765 | I63: 6 | J63: IN | K63: HERSHEYS | L63: 46265 | M63: 0.53819444 | N63: 0.54166667 | O63: done | P63: 46265 | Q63: 0.60416667 | R63: 0.58681713 | S63: done | T63: 1 | U63: 34 | V63: 28.41 | W63: 29.5 | X63: - | Y63: - | Z63: - | AA63: OLMEDO LORETO SERGIO MOISES AN | AB63: 14113198 | AC63: OLMEDO LORETO SERGIO MOISES AN | AD63: 14113198 | AE63: SISTEMA | AF63: AUTOMÁTICO | AG63: AUTOMÁTICO | AH63: 36 | AI63: Ok | AJ63: Retrasado,A tiempo | AK63: 842 | AL63: N/A | AM63: Variable por Ruta | AN63: Sin asignar | AO63: AUTOMÁTICO | AP63: - | AQ63: 0.0034722222 | AR63: -0.017349537 | AS63: Inicia tarde | AT63: Llega a Tiempo | AU63: Inicia tarde-Llega a Tiempo | AV63: 36 | AW63: No | AX63: TonalaHERSHEYS | AY63: CARLOS C. | AZ63: Ilse M. | BA63: HERSHEYSTonala | BB63: E-HER-R0007 | BC63: T2 | BD63: Tonala-R0007-12:55
A64: 176541783 | B64: E-HER-T2-R0008 | C64: LIPU Guadalajara | D64: Parque Morelos | E64: N | F64: 8 | H64: 11827 | I64: 6 | J64: IN | K64: HERSHEYS | L64: 46265 | M64: 0.53819444 | N64: 0.55625 | O64: done | P64: 46265 | Q64: 0.60416667 | R64: 0.59642361 | S64: done | T64: 1 | U64: 31 | V64: 26.23 | W64: 31.28 | X64: - | Y64: - | Z64: - | AC64: OPERADOR NO REGISTRADO | AE64: SISTEMA | AF64: AUTOMÁTICO | AG64: AUTOMÁTICO | AH64: 36 | AI64: Ok | AJ64: Retrasado,A tiempo | AK64: 782 | AL64: N/A | AM64: Variable por Ruta | AN64: Sin asignar | AO64: AUTOMÁTICO | AP64: - | AQ64: 0.018055556 | AR64: -0.0077430556 | AS64: Inicia tarde | AT64: Llega a Tiempo | AU64: Inicia tarde-Llega a Tiempo | AV64: 36 | AW64: No | AX64: Parque MorelosHERSHEYS | AY64: CARLOS C. | AZ64: Ilse M. | BA64: HERSHEYSParque Morelos | BB64: E-HER-R0008 | BC64: T2 | BD64: Parque Morelos-R0008-12:55
A65: 176547787 | B65: E-SK1-T2-R0084 | C65: LIPU Guadalajara | D65: Chulavista 2 T2 | E65: N | F65: 84 | H65: 13844 | I65: 6 | J65: IN | K65: SANMINA KAMPUS 16 | L65: 46265 | M65: 0.53819444 | N65: 0.54444444 | O65: done | P65: 46265 | Q65: 0.60069444 | R65: 0.58680556 | S65: done | T65: 1 | U65: 23 | V65: 20.92 | W65: 19.77 | X65: - | Y65: - | Z65: - | AA65: AMPARO RAMOS JOSE MANUEL | AB65: 14122329 | AC65: AMPARO RAMOS JOSE MANUEL | AD65: 14122329 | AE65: SISTEMA | AF65: AUTOMÁTICO | AG65: AUTOMÁTICO | AH65: 36 | AI65: Ok | AJ65: Retrasado,A tiempo | AK65: 0 | AL65: N/A | AM65: Variable por Ruta | AN65: Sin asignar | AO65: AUTOMÁTICO | AP65: - | AQ65: 0.00625 | AR65: -0.013888889 | AS65: Inicia tarde | AT65: Llega a Tiempo | AU65: Inicia tarde-Llega a Tiempo | AV65: 36 | AW65: No | AX65: Chulavista 2 T2SANMINA KAMPUS 16 | AY65: BRIAN A. | AZ65: Felipe M. | BA65: SANMINA KAMPUS 16Chulavista 2 T2 | BB65: E-SK1-R0084 | BC65: T2 | BD65: Chulavista 2 T2-R0084-12:55
A66: 176538890 | B66: E-SM4-T2-R0125 | C66: LIPU Guadalajara | D66: Vergel Rosas Pintas | E66: N | F66: 125 | H66: 15994 | I66: 6 | J66: IN | K66: SANMINA TLAJOMULCO | L66: 46265 | M66: 0.54166667 | N66: 0.55277778 | O66: done | P66: 46265 | Q66: 0.60069444 | R66: 0.58770833 | S66: done | T66: 1 | U66: 21 | V66: 20.71 | W66: 21.38 | X66: - | Y66: - | Z66: - | AA66: SOLIS GOMEZ JUAN ENRIQUE | AB66: 14121104 | AC66: SOLIS GOMEZ JUAN ENRIQUE | AD66: 14121104 | AE66: SISTEMA | AF66: AUTOMÁTICO | AG66: AUTOMÁTICO | AH66: 36 | AI66: Ok | AJ66: Retrasado,A tiempo | AK66: 0 | AL66: N/A | AM66: Variable por Ruta | AN66: Sin asignar | AO66: AUTOMÁTICO | AP66: - | AQ66: 0.011111111 | AR66: -0.012986111 | AS66: Inicia tarde | AT66: Llega a Tiempo | AU66: Inicia tarde-Llega a Tiempo | AV66: 36 | AW66: No | AX66: Vergel Rosas PintasSANMINA TLAJOMULCO | AY66: CUAUHTEMOC M. | AZ66: Felipe M. | BA66: SANMINA TLAJOMULCOVergel Rosas Pintas | BB66: E-SM4-R0125 | BC66: T2 | BD66: Vergel Rosas Pintas-R0125-13:00
A67: 176548508 | B67: E-SM4-T2-R0227 | C67: LIPU Guadalajara | D67: Lomas del Sur | E67: N | F67: 227 | H67: 4980 | I67: 6 | J67: IN | K67: SANMINA TLAJOMULCO | L67: 46265 | M67: 0.54166667 | N67: 0.54583333 | O67: done | P67: 46265 | Q67: 0.60069444 | R67: 0.57791667 | S67: done | T67: 1 | U67: 30 | V67: 24.54 | W67: 24.87 | X67: - | Y67: - | Z67: - | AA67: LOPEZ GODINEZ MIGUEL DE JESUS | AB67: 14119154 | AC67: LOPEZ GODINEZ MIGUEL DE JESUS | AD67: 14119154 | AE67: SISTEMA | AF67: AUTOMÁTICO | AG67: AUTOMÁTICO | AH67: 36 | AI67: Ok | AJ67: Retrasado,A tiempo | AK67: 0 | AL67: N/A | AM67: Variable por Ruta | AN67: Sin asignar | AO67: AUTOMÁTICO | AP67: - | AQ67: 0.0041666667 | AR67: -0.022777778 | AS67: Inicia tarde | AT67: Llega a Tiempo | AU67: Inicia tarde-Llega a Tiempo | AV67: 36 | AW67: No | AX67: Lomas del SurSANMINA TLAJOMULCO | AY67: CUAUHTEMOC M. | AZ67: Felipe M. | BA67: SANMINA TLAJOMULCOLomas del Sur | BB67: E-SM4-R0227 | BC67: T2 | BD67: Lomas del Sur-R0227-13:00
A68: 176549853 | B68: E-CUP-T2-R0020 | C68: LIPU Guadalajara | D68: 1 de Mayo | E68: N | F68: 20 | H68: 5425 | I68: 6 | J68: IN | K68: CUPRUM GDL | L68: 46265 | M68: 0.54166667 | N68: 0.54513889 | O68: done | P68: 46265 | Q68: 0.57986111 | R68: 0.57440972 | S68: done | T68: 1 | U68: 11 | V68: 8.09 | W68: 8 | X68: - | Y68: - | Z68: - | AA68: RODRIGUEZ RENTERIA BRAYAN IVAN | AB68: 14123536 | AC68: RODRIGUEZ RENTERIA BRAYAN IVAN | AD68: 14123536 | AE68: SISTEMA | AF68: AUTOMÁTICO | AG68: AUTOMÁTICO | AH68: 36 | AI68: Ok | AJ68: Retrasado,A tiempo | AK68: 0 | AL68: N/A | AM68: Variable por Ruta | AN68: Sin asignar | AO68: AUTOMÁTICO | AP68: - | AQ68: 0.0034722222 | AR68: -0.0054513889 | AS68: Inicia tarde | AT68: Llega a Tiempo | AU68: Inicia tarde-Llega a Tiempo | AV68: 36 | AW68: No | AX68: 1 de MayoCUPRUM GDL | AY68: DAVID M | AZ68: Ilse M. | BA68: CUPRUM GDL1 de Mayo | BB68: E-CUP-R0020 | BC68: T2 | BD68: 1 de Mayo-R0020-13:00
A69: 176538768 | B69: E-SM4-T2-R0080 | C69: LIPU Guadalajara | D69: Villas Santa Cruz | E69: N | F69: 80 | H69: 13375 | I69: 6 | J69: IN | K69: SANMINA TLAJOMULCO | L69: 46265 | M69: 0.54513889 | N69: 0.55416667 | O69: done | P69: 46265 | Q69: 0.60069444 | R69: 0.60313657 | S69: done | T69: 1 | U69: 36 | V69: 22.36 | W69: 32.61 | X69: - | Y69: - | Z69: - | AA69: VALLE SANCHEZ RAFAEL | AB69: 14117509 | AC69: VALLE SANCHEZ RAFAEL | AD69: 14117509 | AE69: SISTEMA | AF69: AUTOMÁTICO | AG69: AUTOMÁTICO | AH69: 36 | AI69: Ok | AJ69: Retrasado | AK69: 0 | AL69: N/A | AM69: Variable por Ruta | AN69: Sin asignar | AO69: AUTOMÁTICO | AP69: - | AQ69: 0.0090277778 | AR69: 0.0024421296 | AS69: Inicia tarde | AT69: Llega a Tiempo | AU69: Inicia tarde-Llega a Tiempo | AV69: 36 | AW69: No | AX69: Villas Santa CruzSANMINA TLAJOMULCO | AY69: CUAUHTEMOC M. | AZ69: Felipe M. | BA69: SANMINA TLAJOMULCOVillas Santa Cruz | BB69: E-SM4-R0080 | BC69: T2 | BD69: Villas Santa Cruz-R0080-13:05
A70: 176548184 | B70: E-SK1-T2-R0087 | C70: LIPU Guadalajara | D70: San Martin | E70: N | F70: 87 | H70: 14676 | I70: 6 | J70: IN | K70: SANMINA KAMPUS 16 | L70: 46265 | M70: 0.54861111 | N70: 0.57291667 | O70: done | P70: 46265 | Q70: 0.60069444 | R70: 0.58888889 | S70: done | T70: 1 | U70: 17 | V70: 13.2 | W70: 9.48 | X70: 26.81 | Y70: 14.91 | Z70: 2.42 | AA70: MARES ARREDONDO MIGUEL ANGEL | AB70: 14118811 | AC70: MARES ARREDONDO MIGUEL ANGEL | AD70: 14118811 | AE70: SISTEMA | AF70: AUTOMÁTICO | AG70: AUTOMÁTICO | AH70: 36 | AI70: Ok | AJ70: Retrasado,A tiempo | AK70: 0 | AL70: N/A | AM70: Variable por Ruta | AN70: Sin asignar | AO70: AUTOMÁTICO | AP70: - | AQ70: 0.024305556 | AR70: -0.011805556 | AS70: Inicia tarde | AT70: Llega a Tiempo | AU70: Inicia tarde-Llega a Tiempo | AV70: 36 | AW70: No | AX70: San MartinSANMINA KAMPUS 16 | AY70: BRIAN A. | AZ70: Felipe M. | BA70: SANMINA KAMPUS 16San Martin | BB70: E-SK1-R0087 | BC70: T2 | BD70: San Martin-R0087-13:10
A71: 176548877 | B71: E-FOX-T2-R0149 | C71: LIPU Guadalajara | D71: Apoyo Santa Fe 1 | E71: N | F71: 149 | G71: SUR | H71: 13754 | I71: 8 | J71: IN | K71: FOXCONN | L71: 46265 | M71: 0.55 | N71: 0.55347222 | O71: done | P71: 46265 | Q71: 0.61458333 | R71: 0.58912037 | S71: done | T71: 0 | U71: 20 | V71: 19.84 | W71: 22.72 | X71: - | Y71: - | Z71: - | AA71: ROLDAN CASTILLO HECTOR MISAEL | AB71: 14118889 | AC71: ROLDAN CASTILLO HECTOR MISAEL | AD71: 14118889 | AE71: SISTEMA | AF71: AUTOMÁTICO | AG71: AUTOMÁTICO | AH71: 36 | AI71: Ok | AJ71: Retrasado,A tiempo | AK71: 0 | AL71: N/A | AM71: Variable por Ruta | AN71: Sin asignar | AO71: AUTOMÁTICO | AP71: - | AQ71: 0.0034722222 | AR71: -0.025462963 | AS71: Inicia tarde | AT71: Llega a Tiempo | AU71: Inicia tarde-Llega a Tiempo | AV71: 36 | AW71: No | AX71: Apoyo Santa Fe 1FOXCONN | AY71: DIEGOVO. | AZ71: Leopoldo V. | BA71: FOXCONNApoyo Santa Fe 1 | BB71: E-FOX-R0149 | BC71: T2 | BD71: Apoyo Santa Fe 1-R0149-13:12
A72: 176547617 | B72: E-FOX-T2-R0098 | C72: LIPU Guadalajara | D72: El Colli | E72: N | F72: 98 | G72: NORTE | H72: 14692 | I72: 6 | J72: IN | K72: FOXCONN | L72: 46265 | M72: 0.55208333 | N72: 0.55555556 | O72: done | P72: 46265 | Q72: 0.61458333 | R72: 0.60396991 | S72: done | T72: 1 | U72: 31 | V72: 26.76 | W72: 26.72 | X72: - | Y72: - | Z72: - | AA72: REA PINEDO SALVADOR MANUEL | AB72: 14123725 | AC72: REA PINEDO SALVADOR MANUEL | AD72: 14123725 | AE72: SISTEMA | AF72: AUTOMÁTICO | AG72: AUTOMÁTICO | AH72: 36 | AI72: Ok | AJ72: Retrasado,A tiempo | AK72: 0 | AL72: N/A | AM72: Variable por Ruta | AN72: Sin asignar | AO72: AUTOMÁTICO | AP72: 37 | AQ72: 0.0034722222 | AR72: -0.010613426 | AS72: Inicia tarde | AT72: Llega a Tiempo | AU72: Inicia tarde-Llega a Tiempo | AV72: 36 | AW72: No | AX72: El ColliFOXCONN | AY72: CANDELAS | AZ72: Leopoldo V. | BA72: FOXCONNEl Colli | BB72: E-FOX-R0098 | BC72: T2 | BD72: El Colli-R0098-13:15
A73: 176532578 | B73: E-PEP-T2-R0018 | C73: LIPU Guadalajara | D73: Moctezuma Miramar 2 | E73: N | F73: 18 | H73: 5429 | I73: 6 | J73: IN | K73: PEPSICO GDL | L73: 46265 | M73: 0.55555556 | N73: 0.56805556 | O73: done | P73: 46265 | Q73: 0.60416667 | R73: 0.59998843 | S73: done | T73: 1 | U73: 16 | V73: 9.87 | W73: 9.75 | X73: - | Y73: - | Z73: - | AA73: RUVALCABA ESTRADA GUSTAVO | AB73: 14122709 | AC73: RUVALCABA ESTRADA GUSTAVO | AD73: 14122709 | AE73: SISTEMA | AF73: AUTOMÁTICO | AG73: AUTOMÁTICO | AH73: 36 | AI73: Ok | AJ73: Retrasado,A tiempo | AK73: 584.1 | AL73: N/A | AM73: Variable por Ruta | AN73: Sin asignar | AO73: AUTOMÁTICO | AP73: - | AQ73: 0.0125 | AR73: -0.0041782407 | AS73: Inicia tarde | AT73: Llega a Tiempo | AU73: Inicia tarde-Llega a Tiempo | AV73: 36 | AW73: No | AX73: Moctezuma Miramar 2PEPSICO GDL | AY73: DANIEL | AZ73: Leopoldo V. | BA73: PEPSICO GDLMoctezuma Miramar 2 | BB73: E-PEP-R0018 | BC73: T2 | BD73: Moctezuma Miramar 2-R0018-13:20
A74: 176546910 | B74: E-SM3-T2-R0221 | C74: LIPU Guadalajara | D74: El Mirador | E74: N | F74: 221 | H74: 5423 | I74: 6 | J74: IN | K74: SANMINA FORANE | L74: 46265 | M74: 0.55555556 | N74: 0.56388889 | O74: done | P74: 46265 | Q74: 0.60069444 | R74: 0.59929398 | S74: done | T74: 1 | U74: 12 | V74: 17.67 | W74: 17.94 | X74: - | Y74: - | Z74: - | AA74: LUEVANO LOPEZ JUAN EZEQUIEL | AB74: 14123926 | AC74: LUEVANO LOPEZ JUAN EZEQUIEL | AD74: 14123926 | AE74: SISTEMA | AF74: AUTOMÁTICO | AG74: AUTOMÁTICO | AH74: 36 | AI74: Ok | AJ74: Retrasado,A tiempo | AK74: 0 | AL74: N/A | AM74: Variable por Ruta | AN74: Sin asignar | AO74: AUTOMÁTICO | AP74: - | AQ74: 0.0083333333 | AR74: -0.001400463 | AS74: Inicia tarde | AT74: Llega a Tiempo | AU74: Inicia tarde-Llega a Tiempo | AV74: 36 | AW74: No | AX74: El MiradorSANMINA FORANE | AY74: HEROS M. | AZ74: Felipe M. | BA74: SANMINA FORANEEl Mirador | BB74: E-SM3-R0221 | BC74: T2 | BD74: El Mirador-R0221-13:20
A75: 176548643 | B75: E-SM4-T2-R0229 | C75: LIPU Guadalajara | D75: Apoyo Adolf Horn T2 y T3 | E75: N | F75: 229 | H75: 5530 | I75: 6 | J75: IN | K75: SANMINA TLAJOMULCO | L75: 46265 | M75: 0.55555556 | N75: 0.55972222 | O75: done | P75: 46265 | Q75: 0.60069444 | R75: 0.58402778 | S75: done | T75: 1 | U75: 19 | V75: 15.4 | W75: 10.12 | X75: 30.49 | Y75: 15.27 | Z75: 5.1 | AA75: RODRIGUEZ LOPEZ ANGEL ALBERTO | AB75: 14120925 | AC75: RODRIGUEZ LOPEZ ANGEL ALBERTO | AD75: 14120925 | AE75: SISTEMA | AF75: AUTOMÁTICO | AG75: AUTOMÁTICO | AH75: 36 | AI75: Ok | AJ75: Retrasado,A tiempo | AK75: 0 | AL75: N/A | AM75: Variable por Ruta | AN75: Sin asignar | AO75: AUTOMÁTICO | AP75: - | AQ75: 0.0041666667 | AR75: -0.016666667 | AS75: Inicia tarde | AT75: Llega a Tiempo | AU75: Inicia tarde-Llega a Tiempo | AV75: 36 | AW75: No | AX75: Apoyo Adolf Horn T2 y T3SANMINA TLAJOMULCO | AY75: CUAUHTEMOC M. | AZ75: Felipe M. | BA75: SANMINA TLAJOMULCOApoyo Adolf Horn T2 y T3 | BB75: E-SM4-R0229 | BC75: T2 | BD75: Apoyo Adolf Horn T2 y T3-R0229-13:20
A76: 176538916 | B76: E-SM3-T2-R0104 | C76: LIPU Guadalajara | D76: San Martin 2 Turno 2 y 3 | E76: N | F76: 104 | H76: 5474 | I76: 6 | J76: IN | K76: SANMINA FORANE | L76: 46265 | M76: 0.55902778 | N76: 0.56944444 | O76: done | P76: 46265 | Q76: 0.60069444 | R76: 0.59306713 | S76: done | T76: 1 | U76: 26 | V76: 20.02 | W76: 17.44 | X76: - | Y76: - | Z76: - | AA76: P.SOTO RAMOS FRANCISCO FERNANDO | AC76: P.SOTO RAMOS FRANCISCO FERNANDO | AE76: SISTEMA | AF76: AUTOMÁTICO | AG76: AUTOMÁTICO | AH76: 36 | AI76: Ok | AJ76: Retrasado,A tiempo | AK76: 0 | AL76: N/A | AM76: Variable por Ruta | AN76: Sin asignar | AO76: AUTOMÁTICO | AP76: - | AQ76: 0.010416667 | AR76: -0.0076273148 | AS76: Inicia tarde | AT76: Llega a Tiempo | AU76: Inicia tarde-Llega a Tiempo | AV76: 36 | AW76: No | AX76: San Martin 2 Turno 2 y 3SANMINA FORANE | AY76: HEROS M. | AZ76: Felipe M. | BA76: SANMINA FORANESan Martin 2 Turno 2 y 3 | BB76: E-SM3-R0104 | BC76: T2 | BD76: San Martin 2 Turno 2 y 3-R0104-13:25
A77: 176544041 | B77: E-FOX-T2-R0063 | C77: LIPU Guadalajara | D77: Valle Dorado | E77: N | F77: 63 | G77: SUR | H77: 2528 | I77: 6 | J77: IN | K77: FOXCONN | L77: 46265 | M77: 0.5625 | N77: 0.57083333 | O77: done | P77: 46265 | Q77: 0.61458333 | R77: 0.62954861 | S77: done | T77: 1 | U77: 28 | V77: 19.54 | W77: 5.77 | X77: - | Y77: - | Z77: - | AA77: MENDOZA CARDONA JOSE ALEJANDRO | AB77: 14123634 | AC77: MENDOZA CARDONA JOSE ALEJANDRO | AD77: 14123634 | AE77: SISTEMA | AF77: AUTOMÁTICO | AG77: AUTOMÁTICO | AH77: 36 | AI77: Ok | AJ77: Retrasado | AK77: 0 | AL77: N/A | AM77: Variable por Ruta | AN77: Sin asignar | AO77: AUTOMÁTICO | AP77: - | AQ77: 0.0083333333 | AR77: 0.014965278 | AS77: Inicia tarde | AT77: Llega tarde | AU77: Inicia tarde-Llega tarde | AV77: 36 | AW77: No | AX77: Valle DoradoFOXCONN | AY77: DIEGOVO. | AZ77: Leopoldo V. | BA77: FOXCONNValle Dorado | BB77: E-FOX-R0063 | BC77: T2 | BD77: Valle Dorado-R0063-13:30
A78: 176548413 | B78: E-FOX-T2-R0114 | C78: LIPU Guadalajara | D78: Tonala 2 | E78: N | F78: 114 | G78: NORTE | H78: 13500 | I78: 6 | J78: IN | K78: FOXCONN | L78: 46265 | M78: 0.56805556 | N78: 0.58333333 | O78: done | P78: 46265 | Q78: 0.61458333 | R78: 0.61752315 | S78: done | T78: 1 | U78: 26 | V78: 20.91 | W78: 20.72 | X78: - | Y78: - | Z78: - | AA78: GUERRERO MEDRANO DANIEL | AB78: 14123083 | AC78: GUERRERO MEDRANO DANIEL | AD78: 14123083 | AE78: SISTEMA | AF78: AUTOMÁTICO | AG78: AUTOMÁTICO | AH78: 36 | AI78: Ok | AJ78: Retrasado | AK78: 0 | AL78: N/A | AM78: Variable por Ruta | AN78: Sin asignar | AO78: AUTOMÁTICO | AP78: - | AQ78: 0.015277778 | AR78: 0.0029398148 | AS78: Inicia tarde | AT78: Llega a Tiempo | AU78: Inicia tarde-Llega a Tiempo | AV78: 36 | AW78: No | AX78: Tonala 2FOXCONN | AY78: CANDELAS | AZ78: Leopoldo V. | BA78: FOXCONNTonala 2 | BB78: E-FOX-R0114 | BC78: T2 | BD78: Tonala 2-R0114-13:38
A79: 176538878 | B79: E-SM4-T2-R0121 | C79: LIPU Guadalajara | D79: Tlajomulco 2 | E79: N | F79: 121 | H79: 16768 | I79: 6 | J79: IN | K79: SANMINA TLAJOMULCO | L79: 46265 | M79: 0.56944444 | N79: 0.57361111 | O79: done | P79: 46265 | Q79: 0.60069444 | R79: 0.59765046 | S79: done | T79: 1 | U79: 19 | V79: 18.34 | W79: 18.75 | X79: - | Y79: - | Z79: - | AC79: OPERADOR NO REGISTRADO | AE79: SISTEMA | AF79: AUTOMÁTICO | AG79: AUTOMÁTICO | AH79: 36 | AI79: Ok | AJ79: Retrasado,A tiempo | AK79: 0 | AL79: N/A | AM79: Variable por Ruta | AN79: Sin asignar | AO79: AUTOMÁTICO | AP79: 49 | AQ79: 0.0041666667 | AR79: -0.0030439815 | AS79: Inicia tarde | AT79: Llega a Tiempo | AU79: Inicia tarde-Llega a Tiempo | AV79: 36 | AW79: No | AX79: Tlajomulco 2SANMINA TLAJOMULCO | AY79: CUAUHTEMOC M. | AZ79: Felipe M. | BA79: SANMINA TLAJOMULCOTlajomulco 2 | BB79: E-SM4-R0121 | BC79: T2 | BD79: Tlajomulco 2-R0121-13:40
A80: 176548423 | B80: E-FOX-T2-R0118 | C80: LIPU Guadalajara | D80: Jardines-Alameda | E80: N | F80: 118 | G80: NORTE | H80: 4200 | I80: 6 | J80: IN | K80: FOXCONN | L80: 46265 | M80: 0.56944444 | N80: 0.57847222 | O80: done | P80: 46265 | Q80: 0.61458333 | R80: 0.61984954 | S80: done | T80: 1 | U80: 20 | V80: 14.57 | W80: 6.1 | X80: - | Y80: - | Z80: - | AA80: VAZQUEZ MORALES MILTON | AB80: 14117160 | AC80: VAZQUEZ MORALES MILTON | AD80: 14117160 | AE80: SISTEMA | AF80: AUTOMÁTICO | AG80: AUTOMÁTICO | AH80: 36 | AI80: Ok | AJ80: Retrasado | AK80: 0 | AL80: N/A | AM80: Variable por Ruta | AN80: Sin asignar | AO80: AUTOMÁTICO | AP80: - | AQ80: 0.0090277778 | AR80: 0.0052662037 | AS80: Inicia tarde | AT80: Llega tarde | AU80: Inicia tarde-Llega tarde | AV80: 36 | AW80: No | AX80: Jardines-AlamedaFOXCONN | AY80: CANDELAS | AZ80: Leopoldo V. | BA80: FOXCONNJardines-Alameda | BB80: E-FOX-R0118 | BC80: T2 | BD80: Jardines-Alameda-R0118-13:40
A81: 176541792 | B81: E-HER-T2-R0011 | C81: LIPU Guadalajara | D81: El Salto Azucena | E81: N | F81: 11 | H81: 15185 | I81: 6 | J81: IN | K81: HERSHEYS | L81: 46265 | M81: 0.57361111 | N81: 0.57916667 | O81: done | P81: 46265 | Q81: 0.60416667 | R81: 0.59236111 | S81: done | T81: 1 | U81: 14 | V81: 9.91 | W81: 8.39 | X81: - | Y81: - | Z81: - | AA81: RODRIGUEZ MARTINEZ OMAR ROGELIO | AB81: 14122925 | AC81: RODRIGUEZ MARTINEZ OMAR ROGELIO | AD81: 14122925 | AE81: SISTEMA | AF81: AUTOMÁTICO | AG81: AUTOMÁTICO | AH81: 36 | AI81: Ok | AJ81: Retrasado,A tiempo | AK81: 730 | AL81: N/A | AM81: Variable por Ruta | AN81: Sin asignar | AO81: AUTOMÁTICO | AP81: - | AQ81: 0.0055555556 | AR81: -0.011805556 | AS81: Inicia tarde | AT81: Llega a Tiempo | AU81: Inicia tarde-Llega a Tiempo | AV81: 36 | AW81: No | AX81: El Salto AzucenaHERSHEYS | AY81: CARLOS C. | AZ81: Ilse M. | BA81: HERSHEYSEl Salto Azucena | BB81: E-HER-R0011 | BC81: T2 | BD81: El Salto Azucena-R0011-13:46
A82: 176543883 | B82: E-FOX-T2-R0056 | C82: LIPU Guadalajara | D82: Lomas Del Salto | E82: N | F82: 56 | G82: NORTE | H82: 15316 | I82: 6 | J82: IN | K82: FOXCONN | L82: 46265 | M82: 0.57708333 | N82: 0.61388889 | O82: done | P82: 46265 | Q82: 0.61458333 | R82: 0.64106481 | S82: done | T82: 1 | U82: 29 | V82: 20.52 | W82: 8.72 | X82: - | Y82: - | Z82: - | AA82: FLORES CERVANTES JOSE CHRISTIA | AB82: 14118505 | AC82: FLORES CERVANTES JOSE CHRISTIA | AD82: 14118505 | AE82: SISTEMA | AF82: AUTOMÁTICO | AG82: AUTOMÁTICO | AH82: 36 | AI82: Ok | AJ82: Retrasado | AK82: 0 | AL82: N/A | AM82: Variable por Ruta | AN82: Sin asignar | AO82: AUTOMÁTICO | AP82: - | AQ82: 0.036805556 | AR82: 0.026481481 | AS82: Inicia tarde | AT82: Llega tarde | AU82: Inicia tarde-Llega tarde | AV82: 36 | AW82: No | AX82: Lomas Del SaltoFOXCONN | AY82: CANDELAS | AZ82: Leopoldo V. | BA82: FOXCONNLomas Del Salto | BB82: E-FOX-R0056 | BC82: T2 | BD82: Lomas Del Salto-R0056-13:51
A83: 176548408 | B83: E-FOX-T2-R0112 | C83: LIPU Guadalajara | D83: Cima Serena | E83: N | F83: 112 | G83: SUR | H83: 4983 | I83: 6 | J83: IN | K83: FOXCONN | L83: 46265 | M83: 0.57986111 | N83: 0.59236111 | O83: done | P83: 46265 | Q83: 0.61458333 | R83: 0.61534722 | S83: done | T83: 1 | U83: 17 | V83: 11.83 | W83: 18.35 | X83: - | Y83: - | Z83: - | AA83: ZUNO DAUTO JORGE DANIEL | AB83: 14122621 | AC83: ZUNO DAUTO JORGE DANIEL | AD83: 14122621 | AE83: SISTEMA | AF83: AUTOMÁTICO | AG83: AUTOMÁTICO | AH83: 36 | AI83: Ok | AJ83: Retrasado | AK83: 0 | AL83: N/A | AM83: Variable por Ruta | AN83: Sin asignar | AO83: AUTOMÁTICO | AP83: - | AQ83: 0.0125 | AR83: 0.00076388889 | AS83: Inicia tarde | AT83: Llega a Tiempo | AU83: Inicia tarde-Llega a Tiempo | AV83: 36 | AW83: No | AX83: Cima SerenaFOXCONN | AY83: DIEGOVO. | AZ83: Leopoldo V. | BA83: FOXCONNCima Serena | BB83: E-FOX-R0112 | BC83: T2 | BD83: Cima Serena-R0112-13:55
A84: 176531492 | B84: E-CUP-T1-R0002 | C84: LIPU Guadalajara | D84: Polanco | E84: N | F84: 2 | G84: Polanco 12x12 | H84: 6384 | I84: 6 | J84: IN | K84: CUPRUM GDL | L84: 46265 | M84: 0.67708333 | N84: 0.68194444 | O84: done | P84: 46265 | Q84: 0.74305556 | R84: 0.75028935 | S84: done | T84: 1 | U84: 32 | V84: 122.42 | W84: 28.05 | X84: - | Y84: - | Z84: - | AA84: OROZCO GUERRERO GERARDO DANIEL | AB84: 14122871 | AC84: OROZCO GUERRERO GERARDO DANIEL | AD84: 14122871 | AE84: SISTEMA | AF84: AUTOMÁTICO | AG84: AUTOMÁTICO | AH84: 36 | AI84: Ok | AJ84: Retrasado | AK84: 447.41 | AL84: N/A | AM84: Variable por Ruta | AN84: Sin asignar | AO84: AUTOMÁTICO | AP84: - | AQ84: 0.0048611111 | AR84: 0.0072337963 | AS84: Inicia tarde | AT84: Llega tarde | AU84: Inicia tarde-Llega tarde | AV84: 36 | AW84: No | AX84: PolancoCUPRUM GDL | AY84: DAVID M | AZ84: Ilse M. | BA84: CUPRUM GDLPolanco | BB84: E-CUP-R0002 | BC84: T1 | BD84: Polanco-R0002-16:15
A85: 176531493 | B85: E-CUP-T1-R0003 | C85: LIPU Guadalajara | D85: Chulavista 12X12 | E85: N | F85: 3 | H85: 5351 | I85: 6 | J85: IN | K85: CUPRUM GDL | L85: 46265 | M85: 0.69097222 | N85: 0.69583333 | O85: done | P85: 46265 | Q85: 0.74305556 | R85: 0.73819444 | S85: done | T85: 1 | U85: 24 | V85: 21.51 | W85: 21.15 | X85: 24.63 | Y85: 3.47 | Z85: 0.01 | AA85: ESTRADA ALVAREZ FERNANDO | AB85: 14102730 | AC85: ESTRADA ALVAREZ FERNANDO | AD85: 14102730 | AE85: SISTEMA | AF85: AUTOMÁTICO | AG85: AUTOMÁTICO | AH85: 36 | AI85: Ok | AJ85: Retrasado,A tiempo | AK85: 522.74 | AL85: N/A | AM85: Variable por Ruta | AN85: Sin asignar | AO85: AUTOMÁTICO | AP85: 29 | AQ85: 0.0048611111 | AR85: -0.0048611111 | AS85: Inicia tarde | AT85: Llega a Tiempo | AU85: Inicia tarde-Llega a Tiempo | AV85: 36 | AW85: No | AX85: Chulavista 12X12CUPRUM GDL | AY85: DAVID M | AZ85: Ilse M. | BA85: CUPRUM GDLChulavista 12X12 | BB85: E-CUP-R0003 | BC85: T1 | BD85: Chulavista 12X12-R0003-16:35
A86: 176543615 | B86: E-MOL-T2-R0018 | C86: LIPU Guadalajara | D86: Zacoalco L - J | E86: N | F86: 18 | H86: 11943 | I86: 6 | J86: IN | K86: MOLEX | L86: 46265 | M86: 0.70486111 | N86: 0.72152778 | O86: done | P86: 46265 | Q86: 0.76041667 | R86: 0.74877315 | S86: done | T86: 1 | U86: 35 | V86: 18.48 | W86: 17.8 | X86: - | Y86: - | Z86: - | AA86: DIAZ VICENTE LUIS | AB86: 14116262 | AC86: DIAZ VICENTE LUIS | AD86: 14116262 | AE86: SISTEMA | AF86: AUTOMÁTICO | AG86: AUTOMÁTICO | AH86: 36 | AI86: Ok | AJ86: Retrasado,A tiempo | AK86: 0 | AL86: N/A | AM86: Variable por Ruta | AN86: Sin asignar | AO86: AUTOMÁTICO | AP86: - | AQ86: 0.016666667 | AR86: -0.011643519 | AS86: Inicia tarde | AT86: Llega a Tiempo | AU86: Inicia tarde-Llega a Tiempo | AV86: 36 | AW86: No | AX86: Zacoalco L - JMOLEX | AY86: VICTOR C. | AZ86: Leopoldo V. | BA86: MOLEXZacoalco L - J | BB86: E-MOL-R0018 | BC86: T2 | BD86: Zacoalco L - J-R0018-16:55
A87: 176548265 | B87: E-PIS-T2-R0031 | C87: LIPU Guadalajara | D87: Los Girasoles | E87: N | F87: 31 | G87: Vias | H87: 4444 | I87: 6 | J87: IN | K87: PIS-PISA | L87: 46265 | M87: 0.71875 | N87: 0.72569444 | O87: done | P87: 46265 | Q87: 0.76736111 | R87: 0.76340278 | S87: done | T87: 1 | U87: 24 | V87: 19.63 | W87: 21.94 | X87: - | Y87: - | Z87: - | AA87: HERNANDEZ CONTRERAS EDUARDO | AB87: 14114324 | AC87: HERNANDEZ CONTRERAS EDUARDO | AD87: 14114324 | AE87: SISTEMA | AF87: AUTOMÁTICO | AG87: AUTOMÁTICO | AH87: 36 | AI87: Ok | AJ87: Retrasado,A tiempo | AK87: 0 | AL87: N/A | AM87: Variable por Ruta | AN87: Sin asignar | AO87: AUTOMÁTICO | AP87: - | AQ87: 0.0069444444 | AR87: -0.0039583333 | AS87: Inicia tarde | AT87: Llega a Tiempo | AU87: Inicia tarde-Llega a Tiempo | AV87: 36 | AW87: No | AX87: Los GirasolesPIS-PISA | AY87: DAVID C. | AZ87: Felipe M. | BA87: PIS-PISALos Girasoles | BB87: E-PIS-R0031 | BC87: T2 | BD87: Los Girasoles-R0031-17:15
A88: 176539212 | B88: E-PEM-T3-R0004 | C88: LIPU Guadalajara | D88: Mixing Demostenes | E88: N | F88: 4 | H88: 5922 | I88: 6 | J88: IN | K88: PEPSICO MIXING | L88: 46265 | M88: 0.83194444 | N88: 0.93402778 | O88: done | P88: 46265 | Q88: 0.89583333 | S88: start | T88: 1 | U88: 34 | V88: 31.31 | W88: - | X88: - | Y88: - | Z88: - | AA88: MENDEZ RUIZ BENJAMIN FRANCISCO | AB88: 14107167 | AC88: MENDEZ RUIZ BENJAMIN FRANCISCO | AD88: 14107167 | AE88: SISTEMA | AF88: AUTOMÁTICO | AG88: AUTOMÁTICO | AH88: 36 | AI88: Ok,Cabina | AJ88: Retrasado | AK88: 647.36 | AL88: N/A | AM88: Variable por Ruta | AN88: Sin asignar | AO88: AUTOMÁTICO | AP88: - | AQ88: 0.10208333 | AR88: -0.89583333 | AS88: Inicia tarde | AT88: Llega a Tiempo | AU88: Inicia tarde-Llega a Tiempo | AV88: 36 | AW88: No | AX88: Mixing DemostenesPEPSICO MIXING | AY88: DANIEL | AZ88: Leopoldo V. | BA88: PEPSICO MIXINGMixing Demostenes | BB88: E-PEM-R0004 | BC88: T3 | BD88: Mixing Demostenes-R0004-19:58
A89: 176544969 | B89: E-HLL-T3-R0039 | C89: LIPU Guadalajara | D89: Mezcala | E89: N | F89: 39 | H89: 13444 | I89: 6 | J89: IN | K89: HELLA GDL | L89: 46265 | M89: 0.84027778 | N89: 0.84722222 | O89: done | P89: 46265 | Q89: 0.90625 | R89: 0.90138889 | S89: almost | T89: 1 | U89: 58 | V89: 50.96 | W89: 56.98 | X89: - | Y89: - | Z89: - | AA89: VELAZQUEZ MENDEZ CESAR ARMANDO | AB89: 14122928 | AC89: VELAZQUEZ MENDEZ CESAR ARMANDO | AD89: 14122928 | AE89: SISTEMA | AF89: AUTOMÁTICO | AG89: AUTOMÁTICO | AH89: 36 | AI89: Ok,Calibrar / Operador | AJ89: Retrasado,A tiempo | AK89: 0 | AL89: N/A | AM89: Variable por Ruta | AN89: Sin asignar | AO89: AUTOMÁTICO | AP89: - | AQ89: 0.0069444444 | AR89: -0.0048611111 | AS89: Inicia tarde | AT89: Llega a Tiempo | AU89: Inicia tarde-Llega a Tiempo | AV89: 36 | AW89: No | AX89: MezcalaHELLA GDL | AY89: SIMON / EUGI | AZ89: Ilse M. | BA89: HELLA GDLMezcala | BB89: E-HLL-R0039 | BC89: T3 | BD89: Mezcala-R0039-20:10
A90: 176535043 | B90: E-PEP-T3-R0038 | C90: LIPU Guadalajara | D90: Moctezuma Zalate | E90: N | F90: 38 | H90: 5877 | I90: 6 | J90: IN | K90: PEPSICO GDL | L90: 46265 | M90: 0.84722222 | N90: 0.85069444 | O90: done | P90: 46265 | Q90: 0.90277778 | R90: 0.90069444 | S90: done | T90: 1 | U90: 26 | V90: 23.05 | W90: 22.81 | X90: - | Y90: - | Z90: - | AA90: MORALES ESPINOSA JUAN IGNACIO | AB90: 14120489 | AC90: MORALES ESPINOSA JUAN IGNACIO | AD90: 14120489 | AE90: SISTEMA | AF90: AUTOMÁTICO | AG90: AUTOMÁTICO | AH90: 36 | AI90: Ok | AJ90: Retrasado,A tiempo | AK90: 483.41 | AL90: N/A | AM90: Variable por Ruta | AN90: Sin asignar | AO90: AUTOMÁTICO | AP90: - | AQ90: 0.0034722222 | AR90: -0.0020833333 | AS90: Inicia tarde | AT90: Llega a Tiempo | AU90: Inicia tarde-Llega a Tiempo | AV90: 36 | AW90: No | AX90: Moctezuma ZalatePEPSICO GDL | AY90: DANIEL | AZ90: Leopoldo V. | BA90: PEPSICO GDLMoctezuma Zalate | BB90: E-PEP-R0038 | BC90: T3 | BD90: Moctezuma Zalate-R0038-20:20
A91: 176541811 | B91: E-HER-T3-R0017 | C91: LIPU Guadalajara | D91: Arenales | E91: N | F91: 17 | H91: 15192 | I91: 6 | J91: IN | K91: HERSHEYS | L91: 46265 | M91: 0.85416667 | N91: 0.85972222 | O91: done | P91: 46265 | Q91: 0.91666667 | R91: 0.91527778 | S91: done | T91: 1 | U91: 37 | V91: 33.03 | W91: 34.3 | X91: - | Y91: - | Z91: - | AA91: ZUÑIGA CARRILLO CHRISTIAN ALEJ | AB91: 14122103 | AC91: ZUÑIGA CARRILLO CHRISTIAN ALEJ | AD91: 14122103 | AE91: SISTEMA | AF91: AUTOMÁTICO | AG91: AUTOMÁTICO | AH91: 36 | AI91: Ok | AJ91: Retrasado,A tiempo | AK91: 815 | AL91: N/A | AM91: Variable por Ruta | AN91: Sin asignar | AO91: AUTOMÁTICO | AP91: - | AQ91: 0.0055555556 | AR91: -0.0013888889 | AS91: Inicia tarde | AT91: Llega a Tiempo | AU91: Inicia tarde-Llega a Tiempo | AV91: 36 | AW91: No | AX91: ArenalesHERSHEYS | AY91: CARLOS C. | AZ91: Ilse M. | BA91: HERSHEYSArenales | BB91: E-HER-R0017 | BC91: T3 | BD91: Arenales-R0017-20:30
A92: 176530497 | B92: E-PEP-T3-R0009 | C92: LIPU Guadalajara | D92: Moctezuma San Agustin | E92: N | F92: 9 | H92: 6900 | I92: 6 | J92: IN | K92: PEPSICO GDL | L92: 46265 | M92: 0.85763889 | N92: 0.88888889 | O92: done | P92: 46265 | Q92: 0.90277778 | R92: 0.9125 | S92: done | T92: 1 | U92: 22 | V92: 12.46 | W92: 16.12 | X92: - | Y92: - | Z92: - | AA92: BARBOSA HERNANDEZ LUIS EDUARDO | AB92: 14118440 | AC92: BARBOSA HERNANDEZ LUIS EDUARDO | AD92: 14118440 | AE92: SISTEMA | AF92: AUTOMÁTICO | AG92: AUTOMÁTICO | AH92: 36 | AI92: Ok | AJ92: Retrasado | AK92: 544.9 | AL92: N/A | AM92: Variable por Ruta | AN92: Sin asignar | AO92: AUTOMÁTICO | AP92: - | AQ92: 0.03125 | AR92: 0.0097222222 | AS92: Inicia tarde | AT92: Llega tarde | AU92: Inicia tarde-Llega tarde | AV92: 36 | AW92: No | AX92: Moctezuma San AgustinPEPSICO GDL | AY92: DANIEL | AZ92: Leopoldo V. | BA92: PEPSICO GDLMoctezuma San Agustin | BB92: E-PEP-R0009 | BC92: T3 | BD92: Moctezuma San Agustin-R0009-20:35
A93: 176548503 | B93: E-SAN-T3-R0490 | C93: LIPU Guadalajara | D93: Tabachines T2 y T3 | E93: N | F93: 490 | H93: 6979 | I93: 6 | J93: IN | K93: SANMINA GDL | L93: 46265 | M93: 0.86805556 | N93: 0.87291667 | O93: done | P93: 46265 | Q93: 0.93402778 | R93: 0.92430556 | S93: done | T93: 1 | U93: 42 | V93: -3532.76 | W93: 37.12 | X93: - | Y93: - | Z93: - | AA93: MEJIA IBARRA IVAN ALEJANDRO | AB93: 14122685 | AC93: MEJIA IBARRA IVAN ALEJANDRO | AD93: 14122685 | AE93: SISTEMA | AF93: AUTOMÁTICO | AG93: AUTOMÁTICO | AH93: 36 | AI93: Ok | AJ93: Retrasado,A tiempo | AK93: 0 | AL93: N/A | AM93: Variable por Ruta | AN93: Sin asignar | AO93: AUTOMÁTICO | AP93: - | AQ93: 0.0048611111 | AR93: -0.0097222222 | AS93: Inicia tarde | AT93: Llega a Tiempo | AU93: Inicia tarde-Llega a Tiempo | AV93: 36 | AW93: No | AX93: Tabachines T2 y T3SANMINA GDL | AY93: PABLO F. | AZ93: Felipe M. | BA93: SANMINA GDLTabachines T2 y T3 | BB93: E-SAN-R0490 | BC93: T3 | BD93: Tabachines T2 y T3-R0490-20:50
A94: 176548546 | B94: E-FOX-T3-R0125 | C94: LIPU Guadalajara | D94: La Noria | E94: N | F94: 125 | G94: SUR | H94: 17090 | I94: 6 | J94: IN | K94: FOXCONN | L94: 46265 | M94: 0.86944444 | N94: 0.87291667 | O94: done | P94: 46265 | Q94: 0.92708333 | R94: 0.91388889 | S94: done | T94: 1 | U94: 34 | V94: 28.89 | W94: 28.8 | X94: - | Y94: - | Z94: - | AA94: ALCANTAR ORTIZ MIGUEL ANGEL | AB94: 14124261 | AC94: ALCANTAR ORTIZ MIGUEL ANGEL | AD94: 14124261 | AE94: SISTEMA | AF94: AUTOMÁTICO | AG94: AUTOMÁTICO | AH94: 36 | AI94: Ok | AJ94: Retrasado,A tiempo | AK94: 0 | AL94: N/A | AM94: Variable por Ruta | AN94: Sin asignar | AO94: AUTOMÁTICO | AP94: - | AQ94: 0.0034722222 | AR94: -0.013194444 | AS94: Inicia tarde | AT94: Llega a Tiempo | AU94: Inicia tarde-Llega a Tiempo | AV94: 36 | AW94: No | AX94: La NoriaFOXCONN | AY94: DIEGOVO. | AZ94: Leopoldo V. | BA94: FOXCONNLa Noria | BB94: E-FOX-R0125 | BC94: T3 | BD94: La Noria-R0125-20:52
A95: 176549454 | B95: E-FOX-T3-R0213 | C95: LIPU Guadalajara | D95: 3A Villas Andalucia | E95: N | F95: 213 | G95: SUR | H95: 5001 | I95: 6 | J95: IN | K95: FOXCONN | L95: 46265 | M95: 0.87361111 | N95: 0.87708333 | O95: done | P95: 46265 | Q95: 0.92708333 | R95: 0.91527778 | S95: done | T95: 1 | U95: 33 | V95: 29.57 | W95: 30.03 | X95: - | Y95: - | Z95: - | AA95: LUNA CASTRO ARTURO | AB95: 14121328 | AC95: LUNA CASTRO ARTURO | AD95: 14121328 | AE95: SISTEMA | AF95: AUTOMÁTICO | AG95: AUTOMÁTICO | AH95: 36 | AI95: Ok | AJ95: Retrasado,A tiempo | AK95: 0 | AL95: N/A | AM95: Variable por Ruta | AN95: Sin asignar | AO95: AUTOMÁTICO | AP95: - | AQ95: 0.0034722222 | AR95: -0.011805556 | AS95: Inicia tarde | AT95: Llega a Tiempo | AU95: Inicia tarde-Llega a Tiempo | AV95: 36 | AW95: No | AX95: 3A Villas AndaluciaFOXCONN | AY95: WENDY H. | AZ95: Leopoldo V. | BA95: FOXCONN3A Villas Andalucia | BB95: E-FOX-R0213 | BC95: T3 | BD95: 3A Villas Andalucia-R0213-20:58
A96: 176531119 | B96: E-SAN-T3-R0061 | C96: LIPU Guadalajara | D96: Bethel | E96: N | F96: 61 | H96: 16744 | I96: 6 | J96: IN | K96: SANMINA GDL | L96: 46265 | M96: 0.875 | N96: 0.87986111 | O96: done | P96: 46265 | Q96: 0.93402778 | R96: 0.95625 | S96: done | T96: 1 | U96: 46 | V96: 42.96 | W96: 45.7 | X96: - | Y96: - | Z96: - | AA96: CASTAÑEDA AGUILAR LUIS ANTONIO | AB96: 14119956 | AC96: CASTAÑEDA AGUILAR LUIS ANTONIO | AD96: 14119956 | AE96: SISTEMA | AF96: AUTOMÁTICO | AG96: AUTOMÁTICO | AH96: 36 | AI96: Ok | AJ96: Retrasado | AK96: 530.63 | AL96: N/A | AM96: Variable por Ruta | AN96: Sin asignar | AO96: AUTOMÁTICO | AP96: - | AQ96: 0.0048611111 | AR96: 0.022222222 | AS96: Inicia tarde | AT96: Llega tarde | AU96: Inicia tarde-Llega tarde | AV96: 36 | AW96: No | AX96: BethelSANMINA GDL | AY96: PABLO F. | AZ96: Felipe M. | BA96: SANMINA GDLBethel | BB96: E-SAN-R0061 | BC96: T3 | BD96: Bethel-R0061-21:00
A97: 176542693 | B97: E-FOX-T3-R0022 | C97: LIPU Guadalajara | D97: Arcos Zapopan | E97: N | F97: 22 | G97: NORTE | H97: 15320 | I97: 6 | J97: IN | K97: FOXCONN | L97: 46265 | M97: 0.875 | N97: 0.8875 | O97: done | P97: 46265 | Q97: 0.92708333 | R97: 0.92291667 | S97: done | T97: 1 | U97: 36 | V97: 26.97 | W97: 26.96 | X97: - | Y97: - | Z97: - | AA97: MENDOZA OSEGUERA CHRISTOPHER | AB97: 14122618 | AC97: MENDOZA OSEGUERA CHRISTOPHER | AD97: 14122618 | AE97: SISTEMA | AF97: AUTOMÁTICO | AG97: AUTOMÁTICO | AH97: 36 | AI97: Ok | AJ97: Retrasado,A tiempo | AK97: 0 | AL97: N/A | AM97: Variable por Ruta | AN97: Sin asignar | AO97: AUTOMÁTICO | AP97: 8 | AQ97: 0.0125 | AR97: -0.0041666667 | AS97: Inicia tarde | AT97: Llega a Tiempo | AU97: Inicia tarde-Llega a Tiempo | AV97: 36 | AW97: No | AX97: Arcos ZapopanFOXCONN | AY97: CANDELAS | AZ97: Leopoldo V. | BA97: FOXCONNArcos Zapopan | BB97: E-FOX-R0022 | BC97: T3 | BD97: Arcos Zapopan-R0022-21:00
A98: 176546836 | B98: E-SK1-T3-R0070 | C98: LIPU Guadalajara | D98: Periferico T3 | E98: N | F98: 70 | H98: 15991 | I98: 6 | J98: IN | K98: SANMINA KAMPUS 16 | L98: 46265 | M98: 0.875 | N98: 0.88125 | O98: done | P98: 46265 | Q98: 0.93402778 | R98: 0.93263889 | S98: done | T98: 1 | U98: 42 | V98: 40.16 | W98: 57.29 | X98: - | Y98: - | Z98: - | AA98: LARIOS MANZANO ALBERTO ALJANDRO | AB98: 14124159 | AC98: LARIOS MANZANO ALBERTO ALJANDRO | AD98: 14124159 | AE98: SISTEMA | AF98: AUTOMÁTICO | AG98: AUTOMÁTICO | AH98: 36 | AI98: Ok | AJ98: Retrasado,A tiempo | AK98: 0 | AL98: N/A | AM98: Variable por Ruta | AN98: Sin asignar | AO98: AUTOMÁTICO | AP98: - | AQ98: 0.00625 | AR98: -0.0013888889 | AS98: Inicia tarde | AT98: Llega a Tiempo | AU98: Inicia tarde-Llega a Tiempo | AV98: 36 | AW98: No | AX98: Periferico T3SANMINA KAMPUS 16 | AY98: BRIAN A. | AZ98: Felipe M. | BA98: SANMINA KAMPUS 16Periferico T3 | BB98: E-SK1-R0070 | BC98: T3 | BD98: Periferico T3-R0070-21:00
A99: 176548863 | B99: E-FOX-T3-R0143 | C99: LIPU Guadalajara | D99: Apoyo Valle Dorado | E99: N | F99: 143 | G99: SUR | H99: 14708 | I99: 6 | J99: IN | K99: FOXCONN | L99: 46265 | M99: 0.87638889 | N99: 0.89027778 | O99: done | P99: 46265 | Q99: 0.92708333 | R99: 0.91736111 | S99: done | T99: 1 | U99: 21 | V99: 20.72 | W99: 20.78 | X99: - | Y99: - | Z99: - | AA99: HARO CISNEROS EDGAR OMAR | AB99: 14122072 | AC99: HARO CISNEROS EDGAR OMAR | AD99: 14122072 | AE99: SISTEMA | AF99: AUTOMÁTICO | AG99: AUTOMÁTICO | AH99: 36 | AI99: Ok | AJ99: Retrasado,A tiempo | AK99: 0 | AL99: N/A | AM99: Variable por Ruta | AN99: Sin asignar | AO99: AUTOMÁTICO | AP99: 0 | AQ99: 0.013888889 | AR99: -0.0097222222 | AS99: Inicia tarde | AT99: Llega a Tiempo | AU99: Inicia tarde-Llega a Tiempo | AV99: 36 | AW99: No | AX99: Apoyo Valle DoradoFOXCONN | AY99: DIEGOVO. | AZ99: Leopoldo V. | BA99: FOXCONNApoyo Valle Dorado | BB99: E-FOX-R0143 | BC99: T3 | BD99: Apoyo Valle Dorado-R0143-21:02
A100: 176550707 | B100: E-FOX-T3-R0254 | C100: LIPU Guadalajara | D100: Casa Blanca | E100: N | F100: 254 | G100: SUR | H100: 13850 | I100: 6 | J100: IN | K100: FOXCONN | L100: 46265 | M100: 0.88125 | N100: 0.88472222 | O100: done | P100: 46265 | Q100: 0.92708333 | R100: 0.91319444 | S100: done | T100: 1 | U100: 47 | V100: 42 | W100: 41.69 | X100: - | Y100: - | Z100: - | AA100: GIL LOPEZ IGNACIO | AB100: 14123649 | AC100: GIL LOPEZ IGNACIO | AD100: 14123649 | AE100: SISTEMA | AF100: AUTOMÁTICO | AG100: AUTOMÁTICO | AH100: 36 | AI100: Ok | AJ100: Retrasado,A tiempo | AK100: 0 | AL100: N/A | AM100: Variable por Ruta | AN100: Sin asignar | AO100: AUTOMÁTICO | AP100: - | AQ100: 0.0034722222 | AR100: -0.013888889 | AS100: Inicia tarde | AT100: Llega a Tiempo | AU100: Inicia tarde-Llega a Tiempo | AV100: 36 | AW100: No | AX100: Casa BlancaFOXCONN | AY100: DIEGOVO. | AZ100: Leopoldo V. | BA100: FOXCONNCasa Blanca | BB100: E-FOX-R0254 | BC100: T3 | BD100: Casa Blanca-R0254-21:09
...

Sheet ACUMULADO
A1: agrupador | B1: concepto | C1: clave | D1: nombre_completo | E1: periodo | F1: importe
A2: PERCEPCIONES | B2: AYUDA ESCOLAR | C2: 16124304 | D2: SERNA ALANIS EMMANUEL OQUITZI | E2: S38 | F2: 1950
A3: PERCEPCIONES | B3: AYUDA ESCOLAR | C3: 16123865 | D3: RUBIO REYES ROBERTO | E3: S38 | F3: 2350
A4: PERCEPCIONES | B4: BONO DESEMPEÑO | C4: 14124376 | D4: ORTIZ ROBLES LUIS RAMON | E4: S38 | F4: 268.36
A5: PERCEPCIONES | B5: BONO DESEMPEÑO | C5: 14124352 | D5: ROJAS LOZANO LUIS BENJAMIN | E5: S38 | F5: 268.36
A6: PERCEPCIONES | B6: BONO DESEMPEÑO | C6: 14124334 | D6: FRIAS TERRONES GILBERTO | E6: S38 | F6: 645.8
A7: PERCEPCIONES | B7: BONO DESEMPEÑO | C7: 14124320 | D7: JIMENEZ VALDES ERNESTO | E7: S38 | F7: 468.36
A8: PERCEPCIONES | B8: BONO DESEMPEÑO | C8: 14124303 | D8: DE LEON TORRES RAMON | E8: S38 | F8: 645.8
A9: PERCEPCIONES | B9: BONO DESEMPEÑO | C9: 14124286 | D9: SANCHEZ GOMEZ JUAN CARLOS | E9: S38 | F9: 645.8
A10: PERCEPCIONES | B10: BONO DESEMPEÑO | C10: 14124263 | D10: SOTO RAMOS FRANCISCO FERNANDO | E10: S38 | F10: 268.36
A11: PERCEPCIONES | B11: BONO DESEMPEÑO | C11: 14124260 | D11: MENDEZ MANZO JOSE MANUEL | E11: S38 | F11: 645.8
A12: PERCEPCIONES | B12: BONO DESEMPEÑO | C12: 14124254 | D12: RAMOS TENE JUAN CARLOS | E12: S38 | F12: 645.8
A13: PERCEPCIONES | B13: BONO DESEMPEÑO | C13: 14124244 | D13: OCEGUEDA GONZALEZ DAVID SALVADOR | E13: S38 | F13: 511.62
... A3326: PERCEPCIONES | B3326: SUELDO | C3326: 14100913 | D3326: SANCHEZ PICHARDO JUAN | E3326: S38 | F3326: 3052.84

Sheet DMAS
A1: driver_name | B1: 46285 | C1: 46284 | D1: 46283 | E1: 46282 | F1: 46281 | G1: 46280 | H1: 46279 | I1: 46278 | J1: 46277 | K1: 46276 | L1: 46275 | M1: 46274 | N1: 46273 | O1: 46272 | P1: 46271 | Q1: 46270 | R1: 46269 | S1: 46268 | T1: 46267 | U1: 46266 | V1: 46265 | W1: Nomina | X1: CEROS | Y1: LOGUEO
A2: GARCIA SALCEDO FRANCISCO JAVIE | B2: 3.93 | C2: 5.58 | D2: 5.98 | E2: 6.19 | F2: 1.25 | G2: 6.2699 | H2: 7 | I2: 3.88 | J2: 5.85 | K2: 6.98 | L2: 6.2699 | M2: 6.8399 | N2: 7.06 | O2: 1.47 | P2: 5.21 | Q2: 6.82 | R2: 6.82 | S2: 6.7699 | T2: 6.66 | U2: 7.93 | V2: 6.55 | W2: 14109436 | X2: =COUNTIF(P2:V2,0) -> 0 | Y2: =IF(X2>1,"NO LOGUEO","LOGUEO") -> LOGUEO
A3: GALLEGOS PEREZ BERNARDO CRUZ | B3: 0 | C3: 3.43 | D3: 3.35 | E3: 3.8 | F3: 0 | G3: 2.61 | H3: 3.62 | I3: 4.4799 | J3: 3.59 | K3: 3.56 | L3: 4.29 | M3: 3.29 | N3: 3.68 | O3: 3.65 | P3: 0 | Q3: 3.56 | R3: 3.55 | S3: 3.75 | T3: 3.47 | U3: 3.3 | V3: 3.58 | W3: 14117986 | X3: =COUNTIF(P3:V3,0) -> 1 | Y3: =IF(X3>1,"NO LOGUEO","LOGUEO") -> LOGUEO
A4: P.NUNO SUAREZ AMADO | B4: 0 | C4: 0 | D4: 0 | E4: 0 | F4: 0 | G4: 0 | H4: 0 | I4: 0 | J4: 0 | K4: 0 | L4: 1.93 | M4: 1.94 | N4: 0 | O4: 0 | P4: 0 | Q4: 0 | R4: 0 | S4: 0 | T4: 0 | U4: 0 | V4: 0 | X4: =COUNTIF(P4:V4,0) -> 7 | Y4: =IF(X4>1,"NO LOGUEO","LOGUEO") -> NO LOGUEO
A5: P.SANCHEZ CASTELLANOS ANTONIO DE JESUS | B5: 4.23 | C5: 0 | D5: 0.85 | E5: 0 | F5: 0 | G5: 6.67 | H5: 2.2799 | I5: 0 | J5: 0 | K5: 7.14 | L5: 1.97 | M5: 0 | N5: 0 | O5: 0 | P5: 0 | Q5: 0 | R5: 0 | S5: 0 | T5: 0 | U5: 0 | V5: 0 | X5: =COUNTIF(P5:V5,0) -> 7 | Y5: =IF(X5>1,"NO LOGUEO","LOGUEO") -> NO LOGUEO
A6: P.RAMIREZ RAMIREZ LINO | B6: 0 | C6: 0 | D6: 0 | E6: 0 | F6: 0 | G6: 0 | H6: 4.35 | I6: 0 | J6: 0 | K6: 0 | L6: 0 | M6: 0.63 | N6: 0 | O6: 0 | P6: 0 | Q6: 0 | R6: 0 | S6: 0 | T6: 0 | U6: 0 | V6: 0 | X6: =COUNTIF(P6:V6,0) -> 7 | Y6: =IF(X6>1,"NO LOGUEO","LOGUEO") -> NO LOGUEO
A7: SANCHEZ PONCE JOSE ALBERTO | B7: 0 | C7: 6.34 | D7: 7.42 | E7: 12.11 | F7: 8.65 | G7: 2.67 | H7: 0 | I7: 0 | J7: 4.22 | K7: 5.79 | L7: 9.7099 | M7: 7.31 | N7: 8.39 | O7: 2.47 | P7: 0 | Q7: 5.21 | R7: 11.28 | S7: 6.85 | T7: 9.49 | U7: 0 | V7: 0 | W7: 14100902 | X7: =COUNTIF(P7:V7,0) -> 3 | Y7: =IF(X7>1,"NO LOGUEO","LOGUEO") -> NO LOGUEO
A8: P.PARRA MAGANA JOSE ANDRES | B8: 0 | C8: 0 | D8: 0.73 | E8: 0 | F8: 0 | G8: 2.43 | H8: 0 | I8: 0 | J8: 2.48 | K8: 3.77 | L8: 0 | M8: 0.92 | N8: 0 | O8: 0 | P8: 0 | Q8: 0 | R8: 0 | S8: 0 | T8: 0 | U8: 0 | V8: 0 | X8: =COUNTIF(P8:V8,0) -> 7 | Y8: =IF(X8>1,"NO LOGUEO","LOGUEO") -> NO LOGUEO
A9: MARTINEZ LOPEZ PEDRO ALBERTO | B9: 0 | C9: 0 | D9: 10.15 | E9: 0 | F9: 4.38 | G9: 0 | H9: 6.75 | I9: 1.58 | J9: 10 | K9: 0 | L9: 12.02 | M9: 0 | N9: 11.4199 | O9: 1.35 | P9: 0 | Q9: 0 | R9: 10.93 | S9: 0 | T9: 0 | U9: 0 | V9: 1.53 | X9: =COUNTIF(P9:V9,0) -> 5 | Y9: =IF(X9>1,"NO LOGUEO","LOGUEO") -> NO LOGUEO
A10: P.MARTINEZ LOPEZ PEDRO ALBERTO | B10: 0 | C10: 0 | D10: 0 | E10: 0 | F10: 0 | G10: 0 | H10: 0 | I10: 0 | J10: 0 | K10: 0 | L10: 0 | M10: 0 | N10: 0 | O10: 0 | P10: 0 | Q10: 0 | R10: 0 | S10: 0 | T10: 0 | U10: 0 | V10: 0 | X10: =COUNTIF(P10:V10,0) -> 7 | Y10: =IF(X10>1,"NO LOGUEO","LOGUEO") -> NO LOGUEO
A11: P.CAMPOS RIOS JUAN CARLOS | B11: 5.13 | C11: 0 | D11: 0 | E11: 6.19 | F11: 0 | G11: 5.4 | H11: 3.67 | I11: 0 | J11: 0 | K11: 0 | L11: 5.55 | M11: 0 | N11: 0 | O11: 0 | P11: 0 | Q11: 0 | R11: 0 | S11: 0 | T11: 0 | U11: 0 | V11: 0 | X11: =COUNTIF(P11:V11,0) -> 7 | Y11: =IF(X11>1,"NO LOGUEO","LOGUEO") -> NO LOGUEO
A12: ESPARZA OCHOA ARMANDO | B12: 6.67 | C12: 4.2699 | D12: 5.38 | E12: 4.92 | F12: 1.92 | G12: 4.63 | H12: 5.5 | I12: 4.47 | J12: 4.35 | K12: 4.5299 | L12: 5.67 | M12: 3.68 | N12: 0 | O12: 3.89 | P12: 4.5599 | Q12: 7.51 | R12: 6.3 | S12: 4.72 | T12: 6.49 | U12: 4.87 | V12: 5.1 | W12: 14121543 | X12: =COUNTIF(P12:V12,0) -> 0 | Y12: =IF(X12>1,"NO LOGUEO","LOGUEO") -> LOGUEO
A13: GARCIA GARCIA RUBEN | B13: 0 | C13: 3.52 | D13: 3.34 | E13: 3.36 | F13: 2.85 | G13: 3.98 | H13: 3.88 | I13: 2.41 | J13: 2.83 | K13: 3.78 | L13: 3.67 | M13: 4.43 | N13: 5.3 | O13: 3.7 | P13: 0 | Q13: 4.63 | R13: 3.24 | S13: 3.67 | T13: 1.78 | U13: 5.1099 | V13: 3.7299 | W13: 14114709 | X13: =COUNTIF(P13:V13,0) -> 1 | Y13: =IF(X13>1,"NO LOGUEO","LOGUEO") -> LOGUEO
A14: TAVERA MORALES SATURNINO | B14: 0 | C14: 11.06 | D14: 10.86 | E14: 8.32 | F14: 0 | G14: 0 | H14: 3.08 | I14: 4.2 | J14: 4.75 | K14: 4.73 | L14: 8.11 | M14: 4.32 | N14: 10.1299 | O14: 3.33 | P14: 5.16 | Q14: 7.2899 | R14: 8.41 | S14: 4.04 | T14: 7.43 | U14: 4.2 | V14: 10.87 | X14: =COUNTIF(P14:V14,0) -> 0 | Y14: =IF(X14>1,"NO LOGUEO","LOGUEO") -> LOGUEO
A15: CHAVEZ RUIZ ARMANDO | B15: 0 | C15: 5.87 | D15: 7.49 | E15: 5.53 | F15: 2.59 | G15: 6.54 | H15: 6.15 | I15: 1.47 | J15: 6.1299 | K15: 6.02 | L15: 6.13 | M15: 6.38 | N15: 5.46 | O15: 5.2499 | P15: 0 | Q15: 5.66 | R15: 6.0199 | S15: 7.1699 | T15: 7.44 | U15: 6.91 | V15: 5.34 | W15: 14121784 | X15: =COUNTIF(P15:V15,0) -> 1 | Y15: =IF(X15>1,"NO LOGUEO","LOGUEO") -> LOGUEO
A16: GARCIA RAZO VICTOR MANUEL | B16: 1.9 | C16: 3.37 | D16: 2.4699 | E16: 6.16 | F16: 1.37 | G16: 5.59 | H16: 3.62 | I16: 1.2 | J16: 2.88 | K16: 4.3 | L16: 8.27 | M16: 6.47 | N16: 8.52 | O16: 6.34 | P16: 1.57 | Q16: 7.88 | R16: 4.99 | S16: 5.51 | T16: 6.3 | U16: 5.16 | V16: 2.75 | W16: 14121809 | X16: =COUNTIF(P16:V16,0) -> 0 | Y16: =IF(X16>1,"NO LOGUEO","LOGUEO") -> LOGUEO
A17: AGUINAGA GUERRERO JOSE DAMIA | B17: 1.98 | C17: 7.4 | D17: 0.62 | E17: 11.78 | F17: 0 | G17: 18.73 | H17: 6.4799 | I17: 32.03 | J17: 10.4299 | K17: 29.42 | L17: 7.63 | M17: 9.23 | N17: 5.2699 | O17: 9.8799 | P17: 2.0099 | Q17: 10.7299 | R17: 10.3599 | S17: 16.79 | T17: 6.21 | U17: 10.7 | V17: 5.51 | X17: =COUNTIF(P17:V17,0) -> 0 | Y17: =IF(X17>1,"NO LOGUEO","LOGUEO") -> LOGUEO
A18: DE LA ROSA PORTUGAL ALBERTO | B18: 5.44 | C18: 2.86 | D18: 6.81 | E18: 2.29 | F18: 4.8999 | G18: 5.3199 | H18: 2.25 | I18: 5.1499 | J18: 4.76 | K18: 3.67 | L18: 0 | M18: 4.72 | N18: 5.6 | O18: 6.17 | P18: 5.33 | Q18: 5.0699 | R18: 4.85 | S18: 4.9599 | T18: 4.47 | U18: 5.2399 | V18: 5.69 | W18: 14121672 | X18: =COUNTIF(P18:V18,0) -> 0 | Y18: =IF(X18>1,"NO LOGUEO","LOGUEO") -> LOGUEO
A19: DE LA CRUZ PLASCENCIA ARMANDO | B19: 9.18 | C19: 5.0299 | D19: 3.41 | E19: 4.7899 | F19: 1.23 | G19: 4.8999 | H19: 3.67 | I19: 5.27 | J19: 0 | K19: 1.99 | L19: 3.76 | M19: 3.34 | N19: 2.87 | O19: 5.11 | P19: 10.85 | Q19: 4.94 | R19: 3.07 | S19: 2.7199 | T19: 3.1399 | U19: 3.96 | V19: 2.96 | W19: 14121733 | X19: =COUNTIF(P19:V19,0) -> 0 | Y19: =IF(X19>1,"NO LOGUEO","LOGUEO") -> LOGUEO
A20: CAMPOS LOPEZ JOEL SALVADOR | B20: 0 | C20: 8.03 | D20: 7 | E20: 7.9 | F20: 1.35 | G20: 7.62 | H20: 7.2 | I20: 5.32 | J20: 8.55 | K20: 7.1599 | L20: 2.99 | M20: 8.09 | N20: 6.95 | O20: 8.3699 | P20: 6.15 | Q20: 8.1299 | R20: 9.6599 | S20: 10.81 | T20: 6.53 | U20: 9.7099 | V20: 7.09 | X20: =COUNTIF(P20:V20,0) -> 0 | Y20: =IF(X20>1,"NO LOGUEO","LOGUEO") -> LOGUEO
A21: P.CAMPOS LOPEZ JOEL SALVADOR | B21: 0 | C21: 0 | D21: 0 | E21: 0 | F21: 0 | G21: 0 | H21: 0 | I21: 0 | J21: 0 | K21: 0 | L21: 0 | M21: 0 | N21: 0 | O21: 0 | P21: 0 | Q21: 0 | R21: 0 | S21: 0 | T21: 0 | U21: 0 | V21: 0 | X21: =COUNTIF(P21:V21,0) -> 7 | Y21: =IF(X21>1,"NO LOGUEO","LOGUEO") -> NO LOGUEO
A22: A.HERNANDEZ BEDOLLA MIGUEL ANGEL | B22: 0 | C22: 0 | D22: 0 | E22: 0.22 | F22: 0 | G22: 0 | H22: 0.77 | I22: 0 | J22: 0 | K22: 0 | L22: 0 | M22: 0.8 | N22: 0 | O22: 0 | P22: 0 | Q22: 0 | R22: 1.18 | S22: 0 | T22: 0 | U22: 0.4 | V22: 0.33 | X22: =COUNTIF(P22:V22,0) -> 4 | Y22: =IF(X22>1,"NO LOGUEO","LOGUEO") -> NO LOGUEO
A23: P.VAZQUEZ LUCAS LUIS FERNANDO | B23: 0 | C23: 0 | D23: 0 | E23: 0 | F23: 0 | G23: 0 | H23: 0 | I23: 0 | J23: 0 | K23: 0 | L23: 0 | M23: 0 | N23: 0 | O23: 0 | P23: 0 | Q23: 0 | R23: 0 | S23: 0 | T23: 0 | U23: 0 | V23: 0 | X23: =COUNTIF(P23:V23,0) -> 7 | Y23: =IF(X23>1,"NO LOGUEO","LOGUEO") -> NO LOGUEO
A24: P.MENDEZ CAMPOS RUBEN | B24: 0 | C24: 0 | D24: 0 | E24: 0 | F24: 0 | G24: 0 | H24: 0 | I24: 0 | J24: 0 | K24: 0 | L24: 0 | M24: 0 | N24: 0 | O24: 0 | P24: 0 | Q24: 0 | R24: 0 | S24: 0 | T24: 0 | U24: 0 | V24: 0 | X24: =COUNTIF(P24:V24,0) -> 7 | Y24: =IF(X24>1,"NO LOGUEO","LOGUEO") -> NO LOGUEO
A25: DURAN DIAZ MARIO ALBERTO | B25: 0 | C25: 0 | D25: 12.52 | E25: 4.4 | F25: 0 | G25: 0 | H25: 0 | I25: 0 | J25: 0 | K25: 0 | L25: 0 | M25: 0 | N25: 0 | O25: 0 | P25: 0 | Q25: 4.82 | R25: 3.84 | S25: 0 | T25: 0 | U25: 0 | V25: 1.88 | X25: =COUNTIF(P25:V25,0) -> 4 | Y25: =IF(X25>1,"NO LOGUEO","LOGUEO") -> NO LOGUEO
A26: P.DURAN DIAZ MARIO ALBERTO | B26: 0 | C26: 0 | D26: 0 | E26: 0 | F26: 0 | G26: 0 | H26: 0 | I26: 0 | J26: 0 | K26: 0 | L26: 0 | M26: 0 | N26: 0 | O26: 0 | P26: 0 | Q26: 0 | R26: 0 | S26: 0 | T26: 0 | U26: 0 | V26: 0 | X26: =COUNTIF(P26:V26,0) -> 7 | Y26: =IF(X26>1,"NO LOGUEO","LOGUEO") -> NO LOGUEO
A27: P.VAZQUEZ HERNANDEZ RODOLFO | B27: 0 | C27: 0 | D27: 0 | E27: 0 | F27: 0 | G27: 0 | H27: 0 | I27: 0 | J27: 0 | K27: 0 | L27: 0 | M27: 0 | N27: 0 | O27: 0 | P27: 0 | Q27: 0 | R27: 0 | S27: 0 | T27: 0 | U27: 0 | V27: 0 | X27: =COUNTIF(P27:V27,0) -> 7 | Y27: =IF(X27>1,"NO LOGUEO","LOGUEO") -> NO LOGUEO
A28: SERRANO MACHUCA MARTIN DE JESU | B28: 2.8 | C28: 4.1 | D28: 4.68 | E28: 7.46 | F28: 0.32 | G28: 3.52 | H28: 6.15 | I28: 1.08 | J28: 3.78 | K28: 5.95 | L28: 8.07 | M28: 8.17 | N28: 2.4 | O28: 6.28 | P28: 1.7599 | Q28: 1.56 | R28: 3.2199 | S28: 0 | T28: 0 | U28: 0 | V28: 0 | W28: 14104315 | X28: =COUNTIF(P28:V28,0) -> 4 | Y28: =IF(X28>1,"NO LOGUEO","LOGUEO") -> NO LOGUEO
A29: MEZA RAMIREZ FEDERICO | B29: 2.27 | C29: 5.39 | D29: 4.93 | E29: 2.67 | F29: 3.17 | G29: 8.5899 | H29: 2.97 | I29: 2.4 | J29: 11 | K29: 4.95 | L29: 10.26 | M29: 5.1 | N29: 5.48 | O29: 6.64 | P29: 0 | Q29: 9.84 | R29: 7.77 | S29: 8.8899 | T29: 5.24 | U29: 8.47 | V29: 0 | X29: =COUNTIF(P29:V29,0) -> 2 | Y29: =IF(X29>1,"NO LOGUEO","LOGUEO") -> NO LOGUEO
A30: P.MEZA RAMIREZ FEDERICO | B30: 0 | C30: 0 | D30: 0 | E30: 0 | F30: 0 | G30: 0 | H30: 0 | I30: 0 | J30: 0 | K30: 0 | L30: 0 | M30: 0 | N30: 0 | O30: 0 | P30: 0 | Q30: 0 | R30: 0 | S30: 0 | T30: 0 | U30: 0 | V30: 0 | X30: =COUNTIF(P30:V30,0) -> 7 | Y30: =IF(X30>1,"NO LOGUEO","LOGUEO") -> NO LOGUEO
A31: P.CAMPOS CRUZ LUIS ALBERTO | B31: 0 | C31: 0 | D31: 0 | E31: 0 | F31: 0 | G31: 0 | H31: 0 | I31: 0 | J31: 0 | K31: 0 | L31: 0 | M31: 0 | N31: 0 | O31: 0 | P31: 0 | Q31: 0 | R31: 0 | S31: 0 | T31: 0 | U31: 0 | V31: 0 | X31: =COUNTIF(P31:V31,0) -> 7 | Y31: =IF(X31>1,"NO LOGUEO","LOGUEO") -> NO LOGUEO
A32: MARTINEZ MORENO JAVAN EMILIANO | B32: 7.12 | C32: 6.6 | D32: 7.75 | E32: 6.73 | F32: 7.69 | G32: 8.3199 | H32: 6.72 | I32: 0 | J32: 6.25 | K32: 7.18 | L32: 7.43 | M32: 6.8 | N32: 6.9 | O32: 7.35 | P32: 6.58 | Q32: 8.7899 | R32: 7.27 | S32: 7.17 | T32: 7.4 | U32: 0 | V32: 6.6 | X32: =COUNTIF(P32:V32,0) -> 1 | Y32: =IF(X32>1,"NO LOGUEO","LOGUEO") -> LOGUEO
A33: P.MARTINEZ MORENO JAVAN EMILIANO | B33: 0 | C33: 0 | D33: 0 | E33: 0 | F33: 0 | G33: 0 | H33: 0 | I33: 0 | J33: 0 | K33: 0 | L33: 0 | M33: 0 | N33: 0 | O33: 0 | P33: 0 | Q33: 0 | R33: 0 | S33: 0 | T33: 0 | U33: 0 | V33: 0 | X33: =COUNTIF(P33:V33,0) -> 7 | Y33: =IF(X33>1,"NO LOGUEO","LOGUEO") -> NO LOGUEO
A34: PROCOPIO MENDOZA JUAN FERNANDO | B34: 0.42 | C34: 10.12 | D34: 9.73 | E34: 12.6499 | F34: 8.8699 | G34: 13.82 | H34: 9.96 | I34: 0 | J34: 7.11 | K34: 13.18 | L34: 10.2899 | M34: 14.05 | N34: 9.95 | O34: 13.91 | P34: 0.4 | Q34: 10.51 | R34: 10.1599 | S34: 12.97 | T34: 10.23 | U34: 13.99 | V34: 10.06 | W34: 14121522 | X34: =COUNTIF(P34:V34,0) -> 0 | Y34: =IF(X34>1,"NO LOGUEO","LOGUEO") -> LOGUEO
A35: BARAJAS TOVAR JAVIER IGNACIO | B35: 0 | C35: 0 | D35: 0 | E35: 0 | F35: 0 | G35: 0 | H35: 0 | I35: 0 | J35: 0 | K35: 5.03 | L35: 9.1399 | M35: 0 | N35: 9.58 | O35: 7.03 | P35: 3.8 | Q35: 8.52 | R35: 9.5 | S35: 8.35 | T35: 7.73 | U35: 11.5399 | V35: 9.77 | X35: =COUNTIF(P35:V35,0) -> 0 | Y35: =IF(X35>1,"NO LOGUEO","LOGUEO") -> LOGUEO
A36: P.BARAJAS TOVAR JAVIER IGNACIO | B36: 0 | C36: 0 | D36: 0 | E36: 0 | F36: 0 | G36: 0 | H36: 0 | I36: 0 | J36: 0 | K36: 0 | L36: 0 | M36: 0 | N36: 0 | O36: 0 | P36: 0 | Q36: 0 | R36: 0 | S36: 0 | T36: 0 | U36: 0 | V36: 0 | X36: =COUNTIF(P36:V36,0) -> 7 | Y36: =IF(X36>1,"NO LOGUEO","LOGUEO") -> NO LOGUEO
A37: GONZALEZ GERARDO URIEL | B37: 0 | C37: 0 | D37: 2.3499 | E37: 5.19 | F37: 1.91 | G37: 7.17 | H37: 6.43 | I37: 0 | J37: 6.51 | K37: 6.74 | L37: 6.2 | M37: 5 | N37: 0 | O37: 4.19 | P37: 4.07 | Q37: 1.5 | R37: 2.87 | S37: 7.04 | T37: 6.5899 | U37: 6.5 | V37: 5.55 | W37: 14121398 | X37: =COUNTIF(P37:V37,0) -> 0 | Y37: =IF(X37>1,"NO LOGUEO","LOGUEO") -> LOGUEO
A38: GUTIERREZ SEGURA JUAN ARMANDO | B38: 0 | C38: 0 | D38: 4.1 | E38: 3.74 | F38: 2.2199 | G38: 8.05 | H38: 7.19 | I38: 8.22 | J38: 7.07 | K38: 7.98 | L38: 4.5599 | M38: 0 | N38: 0 | O38: 0 | P38: 0 | Q38: 0 | R38: 0 | S38: 0 | T38: 0 | U38: 0 | V38: 0 | W38: 14112962 | X38: =COUNTIF(P38:V38,0) -> 7 | Y38: =IF(X38>1,"NO LOGUEO","LOGUEO") -> NO LOGUEO
A39: PINEDA VELAZQUEZ PASCUAL | B39: 5.17 | C39: 6.22 | D39: 7.32 | E39: 5.57 | F39: 5.88 | G39: 7.02 | H39: 6.0199 | I39: 0 | J39: 5.93 | K39: 6.08 | L39: 5.95 | M39: 0 | N39: 7.1 | O39: 5.73 | P39: 7.6199 | Q39: 6.02 | R39: 5.92 | S39: 7.3 | T39: 6.68 | U39: 5.6499 | V39: 6.56 | W39: 14118892 | X39: =COUNTIF(P39:V39,0) -> 0 | Y39: =IF(X39>1,"NO LOGUEO","LOGUEO") -> LOGUEO
A40: GUILLEN VEGA GUILLERMO | B40: 0 | C40: 11.1199 | D40: 10.08 | E40: 4.45 | F40: 8.0399 | G40: 4.47 | H40: 10.7099 | I40: 0 | J40: 9.1199 | K40: 4.74 | L40: 10.2199 | M40: 6.81 | N40: 5.21 | O40: 13.67 | P40: 0 | Q40: 5.72 | R40: 7.12 | S40: 1.92 | T40: 9.48 | U40: 4.58 | V40: 9.85 | W40: 14121545 | X40: =COUNTIF(P40:V40,0) -> 1 | Y40: =IF(X40>1,"NO LOGUEO","LOGUEO") -> LOGUEO
A41: LOPEZ RAYMUNDO ROBERTO | B41: 4.21 | C41: 2.77 | D41: 4.01 | E41: 6.62 | F41: 3.93 | G41: 5.57 | H41: 1.47 | I41: 0 | J41: 7.35 | K41: 6.5 | L41: 4.67 | M41: 5.1 | N41: 11.11 | O41: 4.66 | P41: 5.5199 | Q41: 8.08 | R41: 5.37 | S41: 7.8 | T41: 7.26 | U41: 1.6 | V41: 6.4799 | W41: 14100843 | X41: =COUNTIF(P41:V41,0) -> 0 | Y41: =IF(X41>1,"NO LOGUEO","LOGUEO") -> LOGUEO
A42: DIAZ BLANQUET ROSA JANNET | B42: 0 | C42: 8.75 | D42: 2.2599 | E42: 1.22 | F42: 0 | G42: 4.63 | H42: 1.1299 | I42: 0 | J42: 0 | K42: 0 | L42: 0 | M42: 0.18 | N42: 0 | O42: 0 | P42: 0 | Q42: 2.3 | R42: 0 | S42: 3.33 | T42: 0 | U42: 5.04 | V42: 1.29 | W42: 14110604 | X42: =COUNTIF(P42:V42,0) -> 3 | Y42: =IF(X42>1,"NO LOGUEO","LOGUEO") -> NO LOGUEO
A43: P.TORRES JARAS CHRISTIAN OMAR | B43: 0 | C43: 0 | D43: 0 | E43: 0 | F43: 0 | G43: 0 | H43: 0 | I43: 0 | J43: 0 | K43: 0 | L43: 0 | M43: 0 | N43: 0 | O43: 0 | P43: 0 | Q43: 0 | R43: 0 | S43: 0 | T43: 0 | U43: 0 | V43: 0 | X43: =COUNTIF(P43:V43,0) -> 7 | Y43: =IF(X43>1,"NO LOGUEO","LOGUEO") -> NO LOGUEO
A44: P.MARTINEZ SALAS CARLOS | B44: 0 | C44: 0 | D44: 0 | E44: 0 | F44: 0 | G44: 0 | H44: 0 | I44: 0 | J44: 0 | K44: 0 | L44: 0 | M44: 0 | N44: 0 | O44: 0 | P44: 0 | Q44: 0 | R44: 0 | S44: 0 | T44: 0 | U44: 0 | V44: 0 | X44: =COUNTIF(P44:V44,0) -> 7 | Y44: =IF(X44>1,"NO LOGUEO","LOGUEO") -> NO LOGUEO
A45: SANTOS GOMEZ ARTURO | B45: 5.19 | C45: 6.88 | D45: 9.45 | E45: 2.25 | F45: 2.51 | G45: 3.9 | H45: 0.5699 | I45: 1.92 | J45: 9.12 | K45: 1.52 | L45: 8.03 | M45: 4.25 | N45: 8.71 | O45: 1.45 | P45: 0.6 | Q45: 1.96 | R45: 5.35 | S45: 4.38 | T45: 11.44 | U45: 0.4 | V45: 5.91 | W45: 14112124 | X45: =COUNTIF(P45:V45,0) -> 0 | Y45: =IF(X45>1,"NO LOGUEO","LOGUEO") -> LOGUEO
A46: ALMARAZ AVALOS FRANCISCO JAVIER | B46: 6.96 | C46: 10.5699 | D46: 7.83 | E46: 1.3799 | F46: 7.7199 | G46: 9.75 | H46: 12.52 | I46: 6.71 | J46: 10.0399 | K46: 9.6299 | L46: 12.99 | M46: 0.62 | N46: 6.78 | O46: 11.45 | P46: 6.13 | Q46: 4.11 | R46: 2.35 | S46: 10.64 | T46: 11.75 | U46: 9.84 | V46: 11.39 | X46: =COUNTIF(P46:V46,0) -> 0 | Y46: =IF(X46>1,"NO LOGUEO","LOGUEO") -> LOGUEO
A47: P.ALMARAZ AVALOS FRANCISCO JAVIER | B47: 0 | C47: 0 | D47: 0 | E47: 0 | F47: 0 | G47: 0 | H47: 0 | I47: 0 | J47: 0 | K47: 0 | L47: 0 | M47: 0 | N47: 0 | O47: 0 | P47: 0 | Q47: 0 | R47: 0 | S47: 0 | T47: 0 | U47: 0 | V47: 0 | X47: =COUNTIF(P47:V47,0) -> 7 | Y47: =IF(X47>1,"NO LOGUEO","LOGUEO") -> NO LOGUEO
A48: CHAVEZ MORA CESAR ADRIAN | B48: 0 | C48: 2 | D48: 10.1 | E48: 7.76 | F48: 2.73 | G48: 11.11 | H48: 10.24 | I48: 4.57 | J48: 4.04 | K48: 0 | L48: 4.2 | M48: 8.68 | N48: 10.0099 | O48: 9.9699 | P48: 2.72 | Q48: 11.09 | R48: 7.98 | S48: 10.25 | T48: 7.38 | U48: 6.82 | V48: 7.8 | W48: 14121523 | X48: =COUNTIF(P48:V48,0) -> 0 | Y48: =IF(X48>1,"NO LOGUEO","LOGUEO") -> LOGUEO
A49: P.RODRIGUEZ ASCENCIO CESAR | B49: 0 | C49: 0 | D49: 0 | E49: 0 | F49: 0 | G49: 0 | H49: 0 | I49: 0 | J49: 0 | K49: 0 | L49: 0 | M49: 0 | N49: 0 | O49: 0 | P49: 0 | Q49: 0 | R49: 0 | S49: 0 | T49: 0 | U49: 0 | V49: 0 | X49: =COUNTIF(P49:V49,0) -> 7 | Y49: =IF(X49>1,"NO LOGUEO","LOGUEO") -> NO LOGUEO
A50: P.CEDENO GALLO BRANDON ALEJANDRO | B50: 0 | C50: 0 | D50: 0 | E50: 0 | F50: 0 | G50: 0 | H50: 0 | I50: 0 | J50: 0 | K50: 0 | L50: 0 | M50: 0 | N50: 0 | O50: 0 | P50: 0 | Q50: 0 | R50: 0 | S50: 0 | T50: 0 | U50: 0 | V50: 0 | X50: =COUNTIF(P50:V50,0) -> 7 | Y50: =IF(X50>1,"NO LOGUEO","LOGUEO") -> NO LOGUEO
A51: AVILES BRITO JORGE | B51: 8.27 | C51: 0 | D51: 6.97 | E51: 8.52 | F51: 8.2199 | G51: 7.72 | H51: 7.92 | I51: 9.2 | J51: 0 | K51: 7.8 | L51: 7.34 | M51: 9.7499 | N51: 8.07 | O51: 8.09 | P51: 9.43 | Q51: 0 | R51: 9.35 | S51: 9.22 | T51: 8.1199 | U51: 9.65 | V51: 7.3699 | X51: =COUNTIF(P51:V51,0) -> 1 | Y51: =IF(X51>1,"NO LOGUEO","LOGUEO") -> LOGUEO
A52: CRUZ GUTIERREZ ALFREDO | B52: 0 | C52: 0 | D52: 0 | E52: 0 | F52: 0 | G52: 0 | H52: 0 | I52: 0 | J52: 0 | K52: 0 | L52: 0 | M52: 0 | N52: 0 | O52: 0 | P52: 0 | Q52: 0 | R52: 2.97 | S52: 7.1 | T52: 8.3199 | U52: 6.92 | V52: 4.93 | W52: 14100897 | X52: =COUNTIF(P52:V52,0) -> 2 | Y52: =IF(X52>1,"NO LOGUEO","LOGUEO") -> NO LOGUEO
A53: JIMENEZ QUIROZ JAVIER DE JESUS | B53: 1.27 | C53: 4.01 | D53: 3.28 | E53: 0 | F53: 0 | G53: 0 | H53: 0 | I53: 1.7 | J53: 5.29 | K53: 6.91 | L53: 5.29 | M53: 5.5299 | N53: 3.25 | O53: 3.67 | P53: 2.14 | Q53: 4.04 | R53: 5.5 | S53: 5.08 | T53: 6.04 | U53: 5.33 | V53: 3.75 | W53: 14119517 | X53: =COUNTIF(P53:V53,0) -> 0 | Y53: =IF(X53>1,"NO LOGUEO","LOGUEO") -> LOGUEO
A54: CASTILLO FUENTES MIGUEL | B54: 5.26 | C54: 7.2 | D54: 7.06 | E54: 7.53 | F54: 1.7199 | G54: 7.28 | H54: 7.02 | I54: 5.07 | J54: 6.72 | K54: 7.08 | L54: 7.46 | M54: 6.81 | N54: 6.64 | O54: 7.41 | P54: 0 | Q54: 7.63 | R54: 6.36 | S54: 7.86 | T54: 7.9 | U54: 7.21 | V54: 6.43 | W54: 14112730 | X54: =COUNTIF(P54:V54,0) -> 1 | Y54: =IF(X54>1,"NO LOGUEO","LOGUEO") -> LOGUEO
A55: CARRILLO DUENAS ANDRES DE JESUS | B55: 0 | C55: 13.3299 | D55: 12.59 | E55: 14.31 | F55: 11.6399 | G55: 6.3 | H55: 6.86 | I55: 8.31 | J55: 11.51 | K55: 7.65 | L55: 13.72 | M55: 15.22 | N55: 13.6899 | O55: 8.3099 | P55: 0 | Q55: 1.75 | R55: 11.8899 | S55: 12.17 | T55: 13.89 | U55: 13.81 | V55: 11.58 | X55: =COUNTIF(P55:V55,0) -> 1 | Y55: =IF(X55>1,"NO LOGUEO","LOGUEO") -> LOGUEO
A56: P.CARRILLO DUENAS ANDRES DE JESUS | B56: 0 | C56: 0 | D56: 0 | E56: 0 | F56: 0 | G56: 0 | H56: 0 | I56: 0 | J56: 0 | K56: 0 | L56: 0 | M56: 0 | N56: 0 | O56: 0 | P56: 0 | Q56: 0 | R56: 0 | S56: 0 | T56: 0 | U56: 0 | V56: 0 | X56: =COUNTIF(P56:V56,0) -> 7 | Y56: =IF(X56>1,"NO LOGUEO","LOGUEO") -> NO LOGUEO
A57: RODRIGUEZ ORTIZ JOSE MANUEL | B57: 8.56 | C57: 3.84 | D57: 4.2 | E57: 5.2 | F57: 1.79 | G57: 4.07 | H57: 3.85 | I57: 0 | J57: 2 | K57: 3.74 | L57: 3.17 | M57: 4.07 | N57: 4.03 | O57: 4.58 | P57: 7.27 | Q57: 3.96 | R57: 4.3 | S57: 5.31 | T57: 4.18 | U57: 4 | V57: 3.89 | W57: 14104957 | X57: =COUNTIF(P57:V57,0) -> 0 | Y57: =IF(X57>1,"NO LOGUEO","LOGUEO") -> LOGUEO
A58: RODRIGUEZ LOPEZ ANGEL ALBERTO | B58: 4.9 | C58: 6.65 | D58: 9.82 | E58: 5.9099 | F58: 5.4199 | G58: 1.35 | H58: 3.81 | I58: 6.86 | J58: 5.48 | K58: 11.2 | L58: 7.31 | M58: 10.4399 | N58: 1 | O58: 5.84 | P58: 8.4799 | Q58: 7.35 | R58: 11.27 | S58: 9.21 | T58: 7.2 | U58: 1.4 | V58: 4.08 | W58: 14120925 | X58: =COUNTIF(P58:V58,0) -> 0 | Y58: =IF(X58>1,"NO LOGUEO","LOGUEO") -> LOGUEO
A59: P.RICO ALFEREZ ALBERTO | B59: 0 | C59: 0 | D59: 0 | E59: 0 | F59: 0 | G59: 0 | H59: 0 | I59: 0 | J59: 0 | K59: 0 | L59: 0 | M59: 0 | N59: 0 | O59: 0 | P59: 0 | Q59: 0 | R59: 0 | S59: 0 | T59: 0 | U59: 0 | V59: 0 | X59: =COUNTIF(P59:V59,0) -> 7 | Y59: =IF(X59>1,"NO LOGUEO","LOGUEO") -> NO LOGUEO
A60: DIAZ RAMIREZ JUAN JOSE | B60: 4.17 | C60: 5.4 | D60: 5.94 | E60: 2.7199 | F60: 0 | G60: 2.75 | H60: 8.48 | I60: 4.98 | J60: 3.99 | K60: 4.4499 | L60: 4.13 | M60: 4.48 | N60: 5.94 | O60: 8.78 | P60: 4.03 | Q60: 0 | R60: 4.05 | S60: 5.29 | T60: 6.11 | U60: 3.85 | V60: 5.25 | W60: 14121235 | X60: =COUNTIF(P60:V60,0) -> 1 | Y60: =IF(X60>1,"NO LOGUEO","LOGUEO") -> LOGUEO
A61: P.BRISENO HERNANDEZ ENRIQUE | B61: 0 | C61: 0 | D61: 0 | E61: 0 | F61: 0 | G61: 0 | H61: 0 | I61: 0 | J61: 0 | K61: 0 | L61: 0 | M61: 0 | N61: 0 | O61: 0 | P61: 0 | Q61: 0 | R61: 0 | S61: 0 | T61: 0 | U61: 0 | V61: 0 | X61: =COUNTIF(P61:V61,0) -> 7 | Y61: =IF(X61>1,"NO LOGUEO","LOGUEO") -> NO LOGUEO
A62: P.TORRES LEONER OSCAR ALAN | B62: 0 | C62: 0 | D62: 0 | E62: 0 | F62: 0 | G62: 0 | H62: 0 | I62: 0 | J62: 0 | K62: 0 | L62: 0 | M62: 0 | N62: 0 | O62: 0 | P62: 0 | Q62: 0 | R62: 0 | S62: 0 | T62: 0 | U62: 0 | V62: 0 | X62: =COUNTIF(P62:V62,0) -> 7 | Y62: =IF(X62>1,"NO LOGUEO","LOGUEO") -> NO LOGUEO
A63: GARIBAY GARCIA REYES MARTIN | B63: 1.47 | C63: 4.07 | D63: 6.74 | E63: 1.83 | F63: 1.52 | G63: 7.2899 | H63: 2.0299 | I63: 0.63 | J63: 3.52 | K63: 9.9899 | L63: 6.4099 | M63: 5.98 | N63: 5.93 | O63: 3.73 | P63: 2.07 | Q63: 9.34 | R63: 2.77 | S63: 7.47 | T63: 2.5099 | U63: 5.0699 | V63: 1.6 | W63: 14121193 | X63: =COUNTIF(P63:V63,0) -> 0 | Y63: =IF(X63>1,"NO LOGUEO","LOGUEO") -> LOGUEO
A64: CLARO ROSALES JOSE MARIA | B64: 6.69 | C64: 3.57 | D64: 7.45 | E64: 3.4 | F64: 6.34 | G64: 3.11 | H64: 6.57 | I64: 3.2 | J64: 6.55 | K64: 6.21 | L64: 6.62 | M64: 1.3799 | N64: 4.6 | O64: 3.37 | P64: 7.02 | Q64: 0 | R64: 7.39 | S64: 3.62 | T64: 7.08 | U64: 3.95 | V64: 6.88 | W64: 14120850 | X64: =COUNTIF(P64:V64,0) -> 1 | Y64: =IF(X64>1,"NO LOGUEO","LOGUEO") -> LOGUEO
A65: REYES MARTINEZ MIGUEL ANGEL | B65: 3.85 | C65: 7.49 | D65: 11.2999 | E65: 7.05 | F65: 2.12 | G65: 3.9799 | H65: 2.7 | I65: 5.13 | J65: 8.26 | K65: 8.53 | L65: 8.43 | M65: 8.8 | N65: 8.02 | O65: 7.25 | P65: 5.76 | Q65: 7.86 | R65: 8.05 | S65: 9.5399 | T65: 7.23 | U65: 0 | V65: 2.22 | W65: 14118184 | X65: =COUNTIF(P65:V65,0) -> 1 | Y65: =IF(X65>1,"NO LOGUEO","LOGUEO") -> LOGUEO
A66: HUERTA ARREOLA JUAN MIGUEL | B66: 0 | C66: 3.41 | D66: 3.63 | E66: 5.41 | F66: 3.08 | G66: 3.75 | H66: 5.75 | I66: 0 | J66: 3.37 | K66: 5.91 | L66: 4.75 | M66: 8.05 | N66: 4.57 | O66: 6.27 | P66: 0 | Q66: 7.61 | R66: 7.05 | S66: 6.88 | T66: 5.26 | U66: 4.03 | V66: 8.06 | W66: 14118887 | X66: =COUNTIF(P66:V66,0) -> 1 | Y66: =IF(X66>1,"NO LOGUEO","LOGUEO") -> LOGUEO
A67: MORENO ROJAS CAMILO | B67: 8.39 | C67: 8.4 | D67: 6.78 | E67: 8.0399 | F67: 0.73 | G67: 6.35 | H67: 10.7099 | I67: 0 | J67: 9.61 | K67: 10.91 | L67: 12.1499 | M67: 11.8099 | N67: 11.01 | O67: 11.5499 | P67: 0 | Q67: 11.67 | R67: 11.25 | S67: 11.65 | T67: 12.52 | U67: 10.63 | V67: 11.67 | W67: 14119539 | X67: =COUNTIF(P67:V67,0) -> 1 | Y67: =IF(X67>1,"NO LOGUEO","LOGUEO") -> LOGUEO
A68: MORALES FELICIANO JUAN PABLO | B68: 0 | C68: 0 | D68: 0 | E68: 0 | F68: 0 | G68: 0 | H68: 0 | I68: 0 | J68: 0 | K68: 0 | L68: 0 | M68: 0 | N68: 0 | O68: 0 | P68: 0 | Q68: 0 | R68: 0 | S68: 0 | T68: 0 | U68: 0 | V68: 0 | W68: 14119483 | X68: =COUNTIF(P68:V68,0) -> 7 | Y68: =IF(X68>1,"NO LOGUEO","LOGUEO") -> NO LOGUEO
A69: GARCIA RAMIREZ EZEQUIEL | B69: 0 | C69: 10.92 | D69: 9 | E69: 11.8799 | F69: 9.55 | G69: 10.8799 | H69: 12.26 | I69: 0 | J69: 11.75 | K69: 12.24 | L69: 11.2199 | M69: 12.8299 | N69: 11.3 | O69: 11.86 | P69: 0 | Q69: 10.67 | R69: 11.5 | S69: 12.03 | T69: 10.8299 | U69: 8.44 | V69: 10.0399 | X69: =COUNTIF(P69:V69,0) -> 1 | Y69: =IF(X69>1,"NO LOGUEO","LOGUEO") -> LOGUEO
A70: P.GARCIA RAMIREZ EZEQUIEL | B70: 0 | C70: 0 | D70: 0 | E70: 0 | F70: 0 | G70: 0 | H70: 0 | I70: 0 | J70: 0 | K70: 0 | L70: 0 | M70: 0 | N70: 0 | O70: 0 | P70: 0 | Q70: 0 | R70: 0 | S70: 0 | T70: 0 | U70: 0 | V70: 0 | X70: =COUNTIF(P70:V70,0) -> 7 | Y70: =IF(X70>1,"NO LOGUEO","LOGUEO") -> NO LOGUEO
A71: P.AMARAL AGREDANO SAUL | B71: 0 | C71: 0 | D71: 0 | E71: 0 | F71: 0 | G71: 0 | H71: 0 | I71: 0 | J71: 0 | K71: 0 | L71: 0 | M71: 0 | N71: 0 | O71: 0 | P71: 0 | Q71: 0 | R71: 0 | S71: 0 | T71: 0 | U71: 0 | V71: 0 | X71: =COUNTIF(P71:V71,0) -> 7 | Y71: =IF(X71>1,"NO LOGUEO","LOGUEO") -> NO LOGUEO
A72: LUNA CASTRO ARTURO | B72: 2.66 | C72: 10.05 | D72: 9.59 | E72: 7.15 | F72: 2.61 | G72: 7.01 | H72: 5.7799 | I72: 2.77 | J72: 5.62 | K72: 7.32 | L72: 8.94 | M72: 5.74 | N72: 8.28 | O72: 3.92 | P72: 2.12 | Q72: 7.58 | R72: 7.76 | S72: 6.42 | T72: 7.7299 | U72: 9.7299 | V72: 5.81 | W72: 14121328 | X72: =COUNTIF(P72:V72,0) -> 0 | Y72: =IF(X72>1,"NO LOGUEO","LOGUEO") -> LOGUEO
A73: VILLEGAS HERNANDEZ JORGE ANGEL | B73: 6.1 | C73: 10.23 | D73: 5.4 | E73: 7.03 | F73: 0 | G73: 5.1999 | H73: 7.2 | I73: 0 | J73: 12.3299 | K73: 4.57 | L73: 8.25 | M73: 4.7 | N73: 6.64 | O73: 8.14 | P73: 5.92 | Q73: 11.93 | R73: 7.35 | S73: 7.28 | T73: 3.59 | U73: 0 | V73: 1.47 | W73: 14120789 | X73: =COUNTIF(P73:V73,0) -> 1 | Y73: =IF(X73>1,"NO LOGUEO","LOGUEO") -> LOGUEO
A74: A.GODINEZ GARCIA MARIO RICARDO | B74: 0 | C74: 1.1299 | D74: 0 | E74: 0 | F74: 0 | G74: 0 | H74: 0 | I74: 0 | J74: 0 | K74: 0 | L74: 0 | M74: 0 | N74: 0 | O74: 0.98 | P74: 0 | Q74: 0 | R74: 0 | S74: 0 | T74: 0 | U74: 0.65 | V74: 1.75 | W74: 14109772 | X74: =COUNTIF(P74:V74,0) -> 5 | Y74: =IF(X74>1,"NO LOGUEO","LOGUEO") -> NO LOGUEO
A75: LOPEZ GODINEZ MIGUEL DE JESUS | B75: 7.37 | C75: 11.4 | D75: 4.92 | E75: 0 | F75: 7.19 | G75: 8.95 | H75: 9.3799 | I75: 5.2 | J75: 2.82 | K75: 5.55 | L75: 11.32 | M75: 12.3 | N75: 11.37 | O75: 7.53 | P75: 0 | Q75: 8.53 | R75: 5.0599 | S75: 1.1299 | T75: 2.6 | U75: 4.12 | V75: 11.08 | W75: 14119154 | X75: =COUNTIF(P75:V75,0) -> 1 | Y75: =IF(X75>1,"NO LOGUEO","LOGUEO") -> LOGUEO
A76: LOPEZ ACEVES FERNANDO | B76: 8.11 | C76: 12.56 | D76: 5.75 | E76: 0 | F76: 9.8699 | G76: 5.88 | H76: 6.29 | I76: 4.65 | J76: 7.23 | K76: 5.35 | L76: 6.78 | M76: 3.11 | N76: 6.69 | O76: 6.0199 | P76: 4.26 | Q76: 13.45 | R76: 5.41 | S76: 7.29 | T76: 5.1499 | U76: 7.61 | V76: 5.2699 | X76: =COUNTIF(P76:V76,0) -> 0 | Y76: =IF(X76>1,"NO LOGUEO","LOGUEO") -> LOGUEO
A77: P.LOPEZ ACEVES FERNANDO | B77: 0 | C77: 0 | D77: 0 | E77: 0 | F77: 0 | G77: 0 | H77: 0 | I77: 0 | J77: 0 | K77: 0 | L77: 0 | M77: 0 | N77: 0 | O77: 0 | P77: 0 | Q77: 0 | R77: 0 | S77: 0 | T77: 0 | U77: 0 | V77: 0 | X77: =COUNTIF(P77:V77,0) -> 7 | Y77: =IF(X77>1,"NO LOGUEO","LOGUEO") -> NO LOGUEO
A78: HERNANDEZ AGUILAR LUIS ENRIQUE | B78: 9.24 | C78: 7.72 | D78: 8.73 | E78: 1.33 | F78: 4.45 | G78: 4.47 | H78: 6.87 | I78: 0 | J78: 7.22 | K78: 7.3899 | L78: 1.9 | M78: 6.49 | N78: 2.91 | O78: 8.4 | P78: 3.78 | Q78: 5.72 | R78: 1.75 | S78: 6.12 | T78: 1.67 | U78: 6.5199 | V78: 0 | W78: 14119153 | X78: =COUNTIF(P78:V78,0) -> 1 | Y78: =IF(X78>1,"NO LOGUEO","LOGUEO") -> LOGUEO
A79: P.VALENCIA FIGUEROA JESUS ALBERTO | B79: 0 | C79: 0 | D79: 0 | E79: 0 | F79: 0 | G79: 0 | H79: 0 | I79: 0 | J79: 0 | K79: 0 | L79: 0 | M79: 0 | N79: 0 | O79: 0 | P79: 0 | Q79: 0 | R79: 0 | S79: 0 | T79: 0 | U79: 0 | V79: 0 | X79: =COUNTIF(P79:V79,0) -> 7 | Y79: =IF(X79>1,"NO LOGUEO","LOGUEO") -> NO LOGUEO
A80: VALENCIA FIGUEROA JESUS ALBERTO | B80: 0 | C80: 9.22 | D80: 7.2 | E80: 6.53 | F80: 1.4 | G80: 6.35 | H80: 6.78 | I80: 6.97 | J80: 9.69 | K80: 8.01 | L80: 6.82 | M80: 7.06 | N80: 7.3899 | O80: 8.04 | P80: 0 | Q80: 9.78 | R80: 9.71 | S80: 6.97 | T80: 7.19 | U80: 9.77 | V80: 8.45 | X80: =COUNTIF(P80:V80,0) -> 1 | Y80: =IF(X80>1,"NO LOGUEO","LOGUEO") -> LOGUEO
A81: MURILLO GOMEZ MARIO ROBERTO | B81: 3.85 | C81: 6.97 | D81: 7.23 | E81: 6.86 | F81: 2.63 | G81: 7.11 | H81: 7.4 | I81: 2.17 | J81: 6.55 | K81: 8.78 | L81: 7.53 | M81: 6.96 | N81: 8.19 | O81: 7.98 | P81: 5.93 | Q81: 8.95 | R81: 8 | S81: 5.4 | T81: 8.45 | U81: 7.8 | V81: 7.41 | X81: =COUNTIF(P81:V81,0) -> 0 | Y81: =IF(X81>1,"NO LOGUEO","LOGUEO") -> LOGUEO
A82: P.MURILLO GOMEZ MARIO ROBERTO | B82: 0 | C82: 0 | D82: 0 | E82: 0 | F82: 0 | G82: 0 | H82: 0 | I82: 0 | J82: 0 | K82: 0 | L82: 0 | M82: 0 | N82: 0 | O82: 0 | P82: 0 | Q82: 0 | R82: 0 | S82: 0 | T82: 0 | U82: 0 | V82: 0 | X82: =COUNTIF(P82:V82,0) -> 7 | Y82: =IF(X82>1,"NO LOGUEO","LOGUEO") -> NO LOGUEO
A83: VALENCIA IBARRA ESLI JAVIER | B83: 0 | C83: 5.92 | D83: 5.1099 | E83: 5.7699 | F83: 1.24 | G83: 6.13 | H83: 5.49 | I83: 1.32 | J83: 5.3099 | K83: 5.58 | L83: 5.51 | M83: 5.56 | N83: 5.08 | O83: 5.63 | P83: 3.47 | Q83: 5.55 | R83: 5.47 | S83: 4.52 | T83: 5.21 | U83: 0 | V83: 0 | W83: 14119155 | X83: =COUNTIF(P83:V83,0) -> 2 | Y83: =IF(X83>1,"NO LOGUEO","LOGUEO") -> NO LOGUEO
A84: REYES JIMENEZ MIGUEL ANGEL | B84: 7.16 | C84: 3.69 | D84: 7.19 | E84: 4.06 | F84: 7.03 | G84: 4.69 | H84: 4.44 | I84: 3.13 | J84: 7.91 | K84: 2.08 | L84: 5.8 | M84: 4.65 | N84: 7.63 | O84: 4.86 | P84: 7.59 | Q84: 4.18 | R84: 5.2 | S84: 4.66 | T84: 3.95 | U84: 4.99 | V84: 0 | X84: =COUNTIF(P84:V84,0) -> 1 | Y84: =IF(X84>1,"NO LOGUEO","LOGUEO") -> LOGUEO
A85: INZUNZA VAZQUEZ RUBEN | B85: 0 | C85: 0 | D85: 1.65 | E85: 0 | F85: 2.45 | G85: 4.82 | H85: 8.04 | I85: 1.6 | J85: 2.59 | K85: 3.67 | L85: 2.03 | M85: 4.91 | N85: 8.4799 | O85: 0 | P85: 3.5599 | Q85: 5.4499 | R85: 4.05 | S85: 7.94 | T85: 6.83 | U85: 3.7699 | V85: 5.01 | X85: =COUNTIF(P85:V85,0) -> 0 | Y85: =IF(X85>1,"NO LOGUEO","LOGUEO") -> LOGUEO
A86: NORIEGA CASILLAS MAURO | B86: 7.97 | C86: 0 | D86: 10.19 | E86: 9.96 | F86: 0 | G86: 8.43 | H86: 9.3799 | I86: 0 | J86: 5.91 | K86: 10.95 | L86: 10.76 | M86: 10.41 | N86: 11.16 | O86: 9.99 | P86: 0 | Q86: 7.6599 | R86: 10.13 | S86: 6.85 | T86: 8.42 | U86: 5.82 | V86: 1.08 | X86: =COUNTIF(P86:V86,0) -> 1 | Y86: =IF(X86>1,"NO LOGUEO","LOGUEO") -> LOGUEO
A87: YANEZ DE LUNA CARLOS | B87: 2.74 | C87: 5.62 | D87: 6.49 | E87: 3.5 | F87: 2.39 | G87: 6.67 | H87: 4.4 | I87: 3.6 | J87: 4.99 | K87: 7.81 | L87: 6.86 | M87: 8.07 | N87: 7.73 | O87: 4.26 | P87: 2.8699 | Q87: 10.86 | R87: 6.56 | S87: 7.24 | T87: 6.96 | U87: 7.02 | V87: 3.58 | X87: =COUNTIF(P87:V87,0) -> 0 | Y87: =IF(X87>1,"NO LOGUEO","LOGUEO") -> LOGUEO
A88: HERNANDEZ SANCHEZ DAVID SALOMON | B88: 0 | C88: 8.3899 | D88: 7.88 | E88: 6.74 | F88: 6.55 | G88: 8.68 | H88: 6.2699 | I88: 5.66 | J88: 6.7 | K88: 7.64 | L88: 7.83 | M88: 7.49 | N88: 10.35 | O88: 8.43 | P88: 0 | Q88: 0.85 | R88: 7.17 | S88: 7.63 | T88: 7.8 | U88: 8.37 | V88: 6.88 | X88: =COUNTIF(P88:V88,0) -> 1 | Y88: =IF(X88>1,"NO LOGUEO","LOGUEO") -> LOGUEO
A89: P.HERNANDEZ SANCHEZ DAVID SALOMON | B89: 0 | C89: 0 | D89: 0 | E89: 0 | F89: 0 | G89: 0 | H89: 0 | I89: 0 | J89: 0 | K89: 0 | L89: 0 | M89: 0 | N89: 0 | O89: 0 | P89: 0 | Q89: 0 | R89: 0 | S89: 0 | T89: 0 | U89: 0 | V89: 0 | X89: =COUNTIF(P89:V89,0) -> 7 | Y89: =IF(X89>1,"NO LOGUEO","LOGUEO") -> NO LOGUEO
A90: MAGDALENO RAMIREZ EDGAR ANTONI | B90: 5.3299 | C90: 9.2 | D90: 9.18 | E90: 13.14 | F90: 0 | G90: 9.55 | H90: 4.3 | I90: 10.8999 | J90: 0.58 | K90: 4.42 | L90: 6.47 | M90: 0.17 | N90: 10.09 | O90: 11.78 | P90: 10.1599 | Q90: 0.95 | R90: 8.72 | S90: 11.7 | T90: 9.42 | U90: 11.2999 | V90: 9.59 | W90: 14121860 | X90: =COUNTIF(P90:V90,0) -> 0 | Y90: =IF(X90>1,"NO LOGUEO","LOGUEO") -> LOGUEO
A91: P.DOMINGUEZ BERJAN LUIS FERNANDO | B91: 0 | C91: 0 | D91: 0 | E91: 0 | F91: 0 | G91: 0 | H91: 0 | I91: 0 | J91: 0 | K91: 0 | L91: 0 | M91: 0 | N91: 0 | O91: 0 | P91: 0 | Q91: 0 | R91: 0 | S91: 0 | T91: 0 | U91: 0 | V91: 0 | X91: =COUNTIF(P91:V91,0) -> 7 | Y91: =IF(X91>1,"NO LOGUEO","LOGUEO") -> NO LOGUEO
A92: ALFARO VELAZQUEZ MARCO ANTONIO | B92: 4.6999 | C92: 4.6 | D92: 5.09 | E92: 0 | F92: 6.42 | G92: 9.57 | H92: 9.12 | I92: 8.38 | J92: 2.01 | K92: 2.1 | L92: 11.93 | M92: 11.2899 | N92: 10.62 | O92: 10.73 | P92: 10.78 | Q92: 0 | R92: 11.32 | S92: 12.16 | T92: 11.33 | U92: 11.25 | V92: 10.7 | X92: =COUNTIF(P92:V92,0) -> 1 | Y92: =IF(X92>1,"NO LOGUEO","LOGUEO") -> LOGUEO
A93: P.ALFARO VELAZQUEZ MARCO ANTONIO | B93: 0 | C93: 0 | D93: 0 | E93: 0 | F93: 0 | G93: 0 | H93: 0 | I93: 0 | J93: 0 | K93: 0 | L93: 0 | M93: 0 | N93: 0 | O93: 0 | P93: 0 | Q93: 0 | R93: 0 | S93: 0 | T93: 0 | U93: 0 | V93: 0 | X93: =COUNTIF(P93:V93,0) -> 7 | Y93: =IF(X93>1,"NO LOGUEO","LOGUEO") -> NO LOGUEO
A94: NUNEZ ROSALES REYNALDO | B94: 3.87 | C94: 4.09 | D94: 0 | E94: 0 | F94: 0 | G94: 0 | H94: 0 | I94: 0 | J94: 0 | K94: 0 | L94: 2.67 | M94: 6.83 | N94: 8.9 | O94: 7.58 | P94: 5.26 | Q94: 7.49 | R94: 7.98 | S94: 7.98 | T94: 8.57 | U94: 7.84 | V94: 6.89 | X94: =COUNTIF(P94:V94,0) -> 0 | Y94: =IF(X94>1,"NO LOGUEO","LOGUEO") -> LOGUEO
A95: LARA SANDOVAL JOSE MIGUEL | B95: 5.47 | C95: 8.27 | D95: 10.3299 | E95: 0 | F95: 0 | G95: 9.12 | H95: 8.61 | I95: 5.0299 | J95: 10.79 | K95: 9.31 | L95: 6.73 | M95: 8.44 | N95: 8.4699 | O95: 8.64 | P95: 0 | Q95: 0 | R95: 9.89 | S95: 8.5499 | T95: 6.72 | U95: 8.61 | V95: 8.61 | W95: 14123332 | X95: =COUNTIF(P95:V95,0) -> 2 | Y95: =IF(X95>1,"NO LOGUEO","LOGUEO") -> NO LOGUEO
A96: HERRERA NAVARRO FRANCISCO JAVIER | B96: 8.59 | C96: 7.9 | D96: 7.46 | E96: 8.36 | F96: 3.95 | G96: 4.9499 | H96: 0 | I96: 0 | J96: 0 | K96: 0 | L96: 2.95 | M96: 7.02 | N96: 7.33 | O96: 10.4 | P96: 0 | Q96: 2.0099 | R96: 9.32 | S96: 5.7299 | T96: 10.73 | U96: 7.14 | V96: 8.85 | X96: =COUNTIF(P96:V96,0) -> 1 | Y96: =IF(X96>1,"NO LOGUEO","LOGUEO") -> LOGUEO
A97: MARTINEZ SANDOVAL NOE GUADALUP | B97: 0 | C97: 3.87 | D97: 4.26 | E97: 3.74 | F97: 1.75 | G97: 4.57 | H97: 2.64 | I97: 1.12 | J97: 3.4 | K97: 4.2999 | L97: 3.0199 | M97: 4.1 | N97: 8 | O97: 3.52 | P97: 2 | Q97: 13.48 | R97: 4.67 | S97: 4.48 | T97: 4.82 | U97: 4.34 | V97: 3.03 | W97: 14121785 | X97: =COUNTIF(P97:V97,0) -> 0 | Y97: =IF(X97>1,"NO LOGUEO","LOGUEO") -> LOGUEO
A98: PALESTINA VELAZQUEZ EDWIN | B98: 0 | C98: 6.63 | D98: 7.69 | E98: 6.3099 | F98: 0 | G98: 6.72 | H98: 7.07 | I98: 8.37 | J98: 6.99 | K98: 7.77 | L98: 4.9 | M98: 7.67 | N98: 7.6 | O98: 7.02 | P98: 0 | Q98: 7.29 | R98: 7.8299 | S98: 7.83 | T98: 6.42 | U98: 0 | V98: 7.28 | W98: 14119787 | X98: =COUNTIF(P98:V98,0) -> 2 | Y98: =IF(X98>1,"NO LOGUEO","LOGUEO") -> NO LOGUEO
A99: GARCIA RODRIGUEZ JOSE ARMANDO | B99: 6.43 | C99: 8.6 | D99: 10.19 | E99: 10.3 | F99: 7.84 | G99: 2.63 | H99: 0 | I99: 0 | J99: 0 | K99: 7.84 | L99: 9.41 | M99: 9.03 | N99: 8.94 | O99: 5 | P99: 5.59 | Q99: 0.88 | R99: 8.8699 | S99: 8.6199 | T99: 9.37 | U99: 6.41 | V99: 6.16 | X99: =COUNTIF(P99:V99,0) -> 0 | Y99: =IF(X99>1,"NO LOGUEO","LOGUEO") -> LOGUEO
A100: P.GARCIA RODRIGUEZ JOSE ARMANDO | B100: 0 | C100: 0 | D100: 0 | E100: 0 | F100: 0 | G100: 0 | H100: 0 | I100: 0 | J100: 0 | K100: 0 | L100: 0 | M100: 0 | N100: 0 | O100: 0 | P100: 0 | Q100: 0 | R100: 0 | S100: 0 | T100: 0 | U100: 0 | V100: 0 | X100: =COUNTIF(P100:V100,0) -> 7 | Y100: =IF(X100>1,"NO LOGUEO","LOGUEO") -> NO LOGUEO
...

Sheet RENDIMIENTO
A2: CLAVE | B2: NOMBRE | C2: F.INGRESO | D2: UNIDAD | E2: META | F2: REDIMIENTO OBTENIDO | G2: TOTAL A PAGAR | H2: SEMANA DE RETROACTIVO
A3: 14100716 | B3: AMBRIZ MERCADO MARTIN | C3: 2017-05-01 | D3: LIPU | F3: #N/A
A4: 14100718 | B4: MARTINEZ OCHOA PAULO | C4: 2017-05-01 | D4: LIPU | E4: 11.418646 | F4: 11.4715 | G4: 355.58
A5: 14100721 | B5: GUTIERREZ VELEZ FRANCISCO | C5: 2021-07-08 | D5: LIPU | E5: 4.3532522 | F5: 4.1853333 | G5: 0
A6: 14100724 | B6: ORTIZ GARCIA LUIS ALBERTO | C6: 2017-05-01 | D6: LIPU | E6: 3.55 | F6: 3.7375 | G6: 355.58
A7: 14100725 | B7: NAJAR LOPEZ JOSE SERGIO | C7: 2017-05-01 | D7: LIPU | F7: #N/A
A8: 14100726 | B8: GUZMAN MUNGUIA LUIS JAVIER | C8: 2017-05-01 | D8: LIPU | E8: 3.96182 | F8: 4.224 | G8: 355.58
A9: 14100727 | B9: ALONZO PEREZ JOSE REYES | C9: 2017-05-01 | D9: LIPU | E9: 3.55 | F9: 3.9963333 | G9: 355.58
A10: 14100729 | B10: LARIOS ALCARAZ EDUARDO | C10: 2017-05-01 | D10: LIPU | E10: 4.6324259 | F10: 4.444 | G10: 0
A11: 14100731 | B11: TABARES FLORES OSCAR ALEJANDRO | C11: 2022-09-02 | D11: LIPU | E11: 4.4326521 | F11: 4.66 | G11: 355.58
A12: 14100732 | B12: ROBLES DEADEL LAZARO | C12: 2017-05-01 | D12: LIPU | E12: 3.7835575 | F12: 3.804 | G12: 355.58
A13: 14100733 | B13: LINARES CISNEROS JOSE ANTONIO | C13: 2017-05-01 | D13: LIPU | F13: #N/A
A14: 14100740 | B14: OLIVARES HERNANDEZ GABRIEL | C14: 2021-11-17 | D14: LIPU | E14: 4.4923786 | F14: 4.6565 | G14: 355.58
A15: 14100751 | B15: FLORES GARCIA PEDRO | C15: 2025-10-10 | D15: LIPU | E15: 3.9643828 | F15: 3.8515 | G15: 0
A16: 14100777 | B16: GONZALEZ MANZO JAVIER OSWALDO | C16: 2017-05-01 | D16: LIPU | F16: #N/A
A17: 14100787 | B17: YEPEZ VAZQUEZ JOAN | C17: 2017-05-01 | D17: LIPU | E17: 3.7922536 | F17: 4.308 | G17: 355.58
A18: 14100795 | B18: BALTAZAR MENDOZA HORACIO | C18: 2017-05-01 | D18: LIPU | E18: 4.662251 | F18: 4.7065 | G18: 355.58
A19: 14100798 | B19: CARRILLO REYNOSO JESUS ALEJANDRO | C19: 2017-05-01 | D19: LIPU | E19: 4.0644462 | F19: 4.3165 | G19: 355.58
A20: 14100807 | B20: OSORIO HERNANDEZ DOMINGO | C20: 2023-05-12 | D20: LIPU | E20: 4.7317431 | F20: 4.80625 | G20: 355.58
A21: 14100823 | B21: FLORES ENRIQUEZ JUAN PABLO | C21: 2024-08-05 | D21: LIPU | E21: 4.14 | F21: 4.0935 | G21: 355.58
A22: 14100842 | B22: BECERRA LUNA GUILLERMO | C22: 2017-05-01 | D22: LIPU | E22: 4.1596 | F22: 4.101 | G22: 355.58
A23: 14100843 | B23: LOPEZ RAYMUNDO ROBERTO | C23: 2025-03-07 | D23: LIPU | E23: 3.5970917 | F23: 3.703 | G23: 355.58
A24: 14100858 | B24: REYNAGA SANCHEZ MARIO | C24: 2025-06-06 | D24: LIPU | E24: 3.7394146 | F24: 3.866 | G24: 355.58
A25: 14100863 | B25: MARTINEZ ZAVALA FRANCISCO ESPIRIDION | C25: 2017-05-01 | D25: LIPU | E25: 4.2266718 | F25: 4.27325 | G25: 355.58
A26: 14100902 | B26: SANCHEZ PONCE JOSE ALBERTO | C26: 2025-12-31 | D26: LIPU | E26: Descansero | F26: Descansero | G26: 355.58
A27: 14101881 | B27: MORALES AGUILAR ALBERTO | C27: 2017-05-24 | D27: LIPU | E27: 3.9 | F27: 4.235 | G27: 355.58
A28: 14101984 | B28: TABARES VAZQUEZ MARTIN | C28: 2018-11-29 | D28: LIPU | E28: Descansero | F28: Descansero | G28: 355.58
A29: 14102081 | B29: OLEA SANCHEZ JOSE LUIS | C29: 2017-07-07 | D29: LIPU | E29: 8.4446762 | F29: 7.244 | G29: 0
A30: 14102288 | B30: RAMOS ANGUIANO SERGIO DAVID | C30: 2017-08-15 | D30: LIPU | E30: 3.9448622 | F30: 4.3516667 | G30: 355.58
A31: 14102701 | B31: ORTIZ HERNANDEZ JESUS GUADALUPE | C31: 2017-11-06 | D31: LIPU | E31: 3.9 | F31: 3.97 | G31: 355.58
A32: 14102730 | B32: ESTRADA ALVAREZ FERNANDO | C32: 2017-11-13 | D32: LIPU | E32: 3.9751644 | F32: 4.338 | G32: 355.58
A33: 14102875 | B33: LARIOS SANCHEZ HECTOR ALEXANDER | C33: 2017-12-20 | D33: LIPU | E33: 3.1315812 | F33: 4.419 | G33: 355.58
A34: 14102890 | B34: GONZALEZ VALENCIA BARTOLO | C34: 2017-12-21 | D34: LIPU | F34: #N/A
A35: 14103061 | B35: SANCHEZ PEREZ CARLOS FORTINO | C35: 2023-06-01 | D35: LIPU | E35: 3.6322725 | F35: 3.471 | G35: 0
A36: 14103106 | B36: CORTES ARMENTA HERNAN | C36: 2018-02-02 | D36: LIPU | E36: 4.0644255 | F36: 4.396 | G36: 355.58
A37: 14103183 | B37: HERNANDEZ RON BLANCA HERLINDA | C37: 2018-02-27 | D37: LIPU | F37: #N/A
A38: 14103335 | B38: RIVERA MARTINEZ GUSTAVO | C38: 2018-04-09 | D38: LIPU | E38: 3.55 | F38: 3.607 | G38: 355.58
A39: 14103679 | B39: BAUTISTA SOLORIO JAIME | C39: 2018-06-29 | D39: LIPU | E39: 9.2205582 | F39: 10.199 | G39: 355.58
A40: 14103936 | B40: GUTIERREZ GALINDO CARLOS DE JESUS | C40: 2025-08-23 | D40: LIPU | E40: 3.9908682 | F40: 3.782 | G40: 0
A41: 14103952 | B41: HERNANDEZ ORTEGA RAUL | C41: 2018-08-23 | D41: LIPU | F41: #N/A
A42: 14104315 | B42: SERRANO MACHUCA MARTIN DE JESUS | C42: 2025-10-31 | D42: LIPU | E42: 3.8607063 | F42: 4.1633333 | G42: 355.58
A43: 14104316 | B43: COBIAN AYALA EDGAR | C43: 2022-11-16 | D43: LIPU | E43: 3.55 | F43: 3.712 | G43: 355.58
A44: 14104599 | B44: TORRES GUARDADO JOSE LUIS | C44: 2023-03-09 | D44: LIPU | E44: 3.7183339 | F44: 4.1795 | G44: 355.58
A45: 14104822 | B45: HERNANDEZ CRUZ ERNESTO | C45: 2019-03-06 | D45: LIPU | E45: 3.7501358 | F45: 3.801 | G45: 355.58
A46: 14104839 | B46: CASTRO GUIZAR DANIEL HUMBERTO | C46: 2025-03-14 | D46: LIPU | E46: 3.4191053 | F46: 3.724 | G46: 355.58
A47: 14104853 | B47: CAUDILLO CORONADO MARTIN | C47: 2024-11-12 | D47: LIPU | E47: 9.5058736 | F47: 9.73575 | G47: 355.58
A48: 14104932 | B48: MARROQUIN ACEVES MARCOS GUILLERMO | C48: 2019-04-01 | D48: LIPU | E48: 4.9931033 | F48: 4.653 | G48: 0
A49: 14104957 | B49: RODRIGUEZ ORTIZ JOSE MANUEL | C49: 2025-09-13 | D49: LIPU | E49: 3.1 | F49: 3.417 | G49: 355.58
A50: 14105437 | B50: VAZQUEZ SALAS GILBERTO | C50: 2023-04-01 | D50: LIPU | E50: 4.1343215 | F50: 3.9025 | G50: 355.58
A51: 14105531 | B51: RANGEL RAMIREZ RODOLFO IVAN | C51: 2023-03-24 | D51: LIPU | E51: 10.54 | F51: 9.1875 | G51: 0
A52: 14105586 | B52: RAMIREZ FLORES JOSE DE JESUS | C52: 2019-09-06 | D52: LIPU | E52: 4.0616272 | F52: 3.9965 | G52: 355.58
A53: 14105645 | B53: DIAZ RAMOS ISMAEL | C53: 2024-06-12 | D53: LIPU | E53: 3.7338982 | F53: 3.603 | G53: 0
A54: 14106033 | B54: HERNANDEZ PEREZ FRANCISCO JAVIER | C54: 2020-01-22 | D54: LIPU | E54: 3.55 | F54: 3.7653333 | G54: 355.58
A55: 14106035 | B55: TAMAYO GONZALEZ CHRISTIAN JESUS | C55: 2020-01-23 | D55: LIPU | F55: #N/A
A56: 14106066 | B56: PLASCENCIA ESQUIVEL FRANCISCO | C56: 2020-01-30 | D56: LIPU | E56: 9.9629711 | F56: 8.5343333 | G56: 0
A57: 14106233 | B57: ACEVEDO MARTINEZ JORGE | C57: 2025-11-22 | D57: LIPU | E57: Descansero | F57: Descansero | G57: 355.58
A58: 14106368 | B58: SANTANA ARAIZA SANTIAGO | C58: 2020-04-07 | D58: LIPU | E58: 4.4326521 | F58: 4.4155 | G58: 355.58
A59: 14106438 | B59: GAYTAN PINEDO CARLOS ENRIQUE | C59: 2020-05-19 | D59: LIPU | E59: 3.5516893 | F59: 3.0925 | G59: 0
A60: 14106778 | B60: CABALLERO ANGUIANO SERGIO | C60: 2020-07-24 | D60: LIPU | E60: 3.8204949 | F60: 3.701 | G60: 0
A61: 14106949 | B61: SOTELO AVIÑA MICHEL ALEJANDRO | C61: 2020-09-21 | D61: LIPU | E61: 4.6202446 | F61: 4.297 | G61: 0
A62: 14106980 | B62: LOPEZ GODOY ENRIQUE | C62: 2020-09-28 | D62: LIPU | E62: 3.6795202 | F62: 3.6873333 | G62: 355.58
A63: 14107081 | B63: RAMIREZ RUIZ RAUL | C63: 2020-11-01 | D63: LIPU | E63: 3.835801 | F63: 4.382 | G63: 355.58
A64: 14107167 | B64: MENDEZ RUIZ BENJAMIN FRANCISCO | C64: 2020-11-20 | D64: LIPU | E64: 3.8162874 | F64: 4.0693333 | G64: 355.58
A65: 14107202 | B65: ANGUIANO OCAMPO JOSE GUADALUPE | C65: 2023-03-17 | D65: LIPU | E65: 3.3380522 | F65: 4.1585 | G65: 355.58
A66: 14107206 | B66: HERNANDEZ CHAVEZ FERNANDO | C66: 2020-12-07 | D66: LIPU | E66: 3.9 | F66: 1.775 | G66: 0
A67: 14107271 | B67: PEREZ CASTILLO GABRIEL | C67: 2020-12-23 | D67: LIPU | E67: 6.5421656 | F67: 7.982 | G67: 355.58
A68: 14107293 | B68: MAGAÑA CONTRERAS JOSE LUIS | C68: 2025-01-16 | D68: LIPU | F68: #N/A
A69: 14107393 | B69: GUERRERO CORTES SERGIO RICARDO | C69: 2021-01-28 | D69: LIPU | E69: 4.1079668 | F69: 4.042 | G69: 0
A70: 14107484 | B70: LOPEZ VELASCO MARIO | C70: 2021-02-18 | D70: LIPU | E70: 4.8481517 | F70: 4.855 | G70: 355.58
A71: 14107552 | B71: PACHECO SALCEDO FERNANDO | C71: 2021-03-04 | D71: LIPU | E71: 4.4563436 | F71: 4.4624 | G71: 355.58
A72: 14107735 | B72: ZEPEDA GUERRERO JUAN CARLOS | C72: 2021-04-16 | D72: LIPU | F72: #N/A
A73: 14107754 | B73: GARCIA DE LA TORRE LEONARDO | C73: 2021-04-22 | D73: LIPU | E73: 4.8052375 | F73: 4.655 | G73: 0
A74: 14107840 | B74: CONTRERAS DAVILA DANIEL | C74: 2021-05-12 | D74: LIPU | E74: 11.204975 | F74: 12.836 | G74: 355.58
A75: 14107967 | B75: VAZQUEZ FLORES FABIAN | C75: 2021-06-10 | D75: LIPU | F75: #N/A
A76: 14107978 | B76: LIRA LOPEZ LUIS ANGEL | C76: 2021-06-11 | D76: LIPU | E76: 4.3692556 | F76: 4.6265 | G76: 355.58
A77: 14108111 | B77: LUNA SANDOVAL DAVID | C77: 2021-07-02 | D77: LIPU | E77: 3.55 | F77: 4.1263333 | G77: 355.58
A78: 14108150 | B78: IBARRA PEREZ MARTIN | C78: 2021-07-09 | D78: LIPU | E78: 3.55 | F78: 3.322 | G78: 0
A79: 14108222 | B79: TELLES PADILLA JOSE MANUEL | C79: 2021-07-21 | D79: LIPU | E79: 3.7547561 | F79: 3.1285 | G79: 0
A80: 14108267 | B80: MUÑOZ SANTACRUZ JUAN PABLO | C80: 2021-07-28 | D80: LIPU | E80: 7.7937372 | F80: 8.32775 | G80: 711.16 | H80: semana 36
A81: 14108271 | B81: DE LA ROSA OCEGUEDA JUAN GUADALUPE | C81: 2021-07-28 | D81: LIPU | F81: #N/A
A82: 14108361 | B82: VILLEGAS HUIZAR FERNANDO | C82: 2021-08-06 | D82: LIPU | E82: 7.9774987 | F82: 5.687 | G82: 0
A83: 14108382 | B83: ROSALES SANDOVAL LUIS AARON | C83: 2021-08-06 | D83: LIPU | E83: 8.8207769 | F83: 7.305 | G83: 0
A84: 14108483 | B84: ZAVALA NAVARRO SAUL | C84: 2021-08-13 | D84: LIPU | E84: 3.5514511 | F84: 3.345 | G84: 0
A85: 14108552 | B85: ZUÑIGA HERNANDEZ OSCAR FRANCISCO | C85: 2023-11-14 | D85: LIPU | E85: 8.7869923 | F85: 8.6033333 | G85: 0
A86: 14108553 | B86: MARTINEZ LOPEZ JORGE ANTONIO | C86: 2024-06-03 | D86: LIPU | F86: #N/A
A87: 14108571 | B87: BELTRAN OLIVARES NESTOR ARMANDO | C87: 2021-08-20 | D87: LIPU | E87: 4.4036493 | F87: 4.375 | G87: 355.58
A88: 14108775 | B88: PARRA COBIAN OSCAR | C88: 2024-10-25 | D88: LIPU | E88: 7.9219754 | F88: 7.917 | G88: 355.58
A89: 14108828 | B89: BARAJAS SALDAÑA JUAN | C89: 2025-03-14 | D89: LIPU | E89: 10.744593 | F89: 9.62 | G89: 0
A90: 14108916 | B90: RAMOS DELGADO FRANCISCO | C90: 2021-10-06 | D90: LIPU | E90: 4.6175668 | F90: 4.3885 | G90: 0
A91: 14109032 | B91: GARCIA PRECIADO ANTONIO | C91: 2021-10-28 | D91: LIPU | E91: 3.8710509 | F91: 4.11 | G91: 355.58
A92: 14109097 | B92: VAZQUEZ CERVANTES JOSE MAURICIO | C92: 2021-11-08 | D92: LIPU | E92: 4.6120013 | F92: 4.858 | G92: 355.58
A93: 14109131 | B93: GONZALEZ FLOREZ SALVADOR | C93: 2021-11-08 | D93: LIPU | E93: 4.813229 | F93: 4.15 | G93: 0
A94: 14109133 | B94: RENTERIA GUTIERREZ JUAN MANUEL | C94: 2021-11-08 | D94: LIPU | E94: 3.55 | F94: 3.238 | G94: 0
A95: 14109134 | B95: GODINEZ CONTRERAS SERGIO ALEJANDRO | C95: 2021-11-08 | D95: LIPU | E95: 3.55 | F95: 4.2006667 | G95: 355.58
A96: 14109378 | B96: NAVARRO MEZA JULIAN | C96: 2021-12-21 | D96: LIPU | E96: 4.3904208 | F96: 4.4505 | G96: 355.58
A97: 14109408 | B97: DE LA CRUZ CHAVEZ LUIS DAVID | C97: 2022-01-04 | D97: LIPU | E97: 9.5058736 | F97: 9.664 | G97: 355.58
A98: 14109435 | B98: MEDINA ALVAREZ CUAUHTEMOC | C98: 2022-01-12 | D98: LIPU | F98: #N/A
A99: 14109436 | B99: GARCIA SALCEDO FRANCISCO JAVIER | C99: 2026-01-09 | D99: LIPU | E99: 3.304 | F99: 4.4675 | G99: 355.58
A100: 14109648 | B100: SANCHEZ CANDELARIO GUSTAVO | C100: 2025-02-22 | D100: LIPU | E100: 3.7345154 | F100: 3.2786667 | G100: 0
A101: 14109664 | B101: ALVARADO LOPEZ GERARDO | C101: 2022-02-09 | D101: LIPU | F101: #N/A
...

Sheet CONSULTA
B1: NÓMINA
B2: 14107293
B3: NOMBRE | C3: =IFERROR(VLOOKUP(CONSULTA!$B$2,BONOS!$A$6:$BM$650,$H3,FALSE),"") -> MAGAÑA CONTRERAS JOSE LUIS | H3: =IFERROR(MATCH("NOMBRE ",BONOS!$A$6:$BM$6,0),"") -> 2
B4: SINIESTROS | C4: =IFERROR(VLOOKUP(CONSULTA!$B$2,BONOS!$A$6:$BM$650,$D4,FALSE),"") -> SIN SINIESTRO | D4: =IFERROR(MATCH("SINIESTROS",BONOS!$A$6:$BM$6,0),"") -> 5 | E4: BONO DE SCORE | G4: =IFERROR(VLOOKUP(CONSULTA!$B$2,BONOS!$A$6:$BM$650,$H4,FALSE),"") -> NO | H4: =IFERROR(MATCH("BONO SCORE",BONOS!$A$6:$BM$6,0),"") -> 8
B5: QUEJAS | C5: =IFERROR(VLOOKUP(CONSULTA!$B$2,BONOS!$A$6:$BM$650,$D5,FALSE),"") -> SIN QUEJA | D5: =IFERROR(MATCH("QUEJAS",BONOS!$A$6:$BM$6,0),"") -> 6 | E5: PUNTUALIDAD | G5: =IFERROR(VLOOKUP(CONSULTA!$B$2,BONOS!$A$6:$BM$650,$H5,FALSE),"") -> OK | H5: =IFERROR(MATCH("PUNTUALIDAD",BONOS!$A$6:$BM$6,0),"") -> 9
B6: SCORE OBTENIDO | C6: =IFERROR(VLOOKUP(CONSULTA!$B$2,BONOS!$A$6:$BM$650,$D6,FALSE),"") | D6: =IFERROR(MATCH("SCORE OBTENIDO",BONOS!$A$6:$BM$6,0),"") -> 7 | E6: BONO LOGUEO | G6: =IFERROR(VLOOKUP(CONSULTA!$B$2,BONOS!$A$6:$BM$650,$H6,FALSE),"") -> NO LOGUEO | H6: =IFERROR(MATCH("BONO LOGUEO",BONOS!$A$6:$BM$6,0),"") -> 10
B8: RENDIMEINTO META | C8: =IFERROR(VLOOKUP(CONSULTA!$B$2,RENDIMIENTO!$A$2:$BM$650,$D8,FALSE),"") -> 0 | D8: =IFERROR(MATCH("META",RENDIMIENTO!$A$2:$BM$2,0),"") -> 5 | E8: BONO 0 SINIESTROS | G8: =IFERROR(VLOOKUP(CONSULTA!$B$2,BONOS!$A$6:$BM$650,$H8,FALSE),"") -> 0 | H8: =IFERROR(MATCH("BONO SINIESTROS",BONOS!$A$6:$BM$6,0),"") -> 11
B9: REDIMIENTO OBTENIDO | C9: =IFERROR(VLOOKUP(CONSULTA!$B$2,RENDIMIENTO!$A$2:$BM$650,$D9,FALSE),"") | D9: =IFERROR(MATCH("REDIMIENTO OBTENIDO ",RENDIMIENTO!$A$2:$BM$2,0),"") -> 6 | E9: BONO 0 QUEJAS | G9: =IFERROR(VLOOKUP(CONSULTA!$B$2,BONOS!$A$6:$BM$650,$H9,FALSE),"") -> 0 | H9: =IFERROR(MATCH("BONO QUEJAS",BONOS!$A$6:$BM$6,0),"") -> 12
B10: SEMANA 38 | E10: BONO SCORE | G10: =IFERROR(VLOOKUP(CONSULTA!$B$2,BONOS!$A$6:$BM$650,$H10,FALSE),"") -> 0 | H10: =IFERROR(MATCH("BONO SCORE1",BONOS!$A$6:$BM$6,0),"") -> 14
E11: BONO LOGUEO | G11: =IFERROR(VLOOKUP(CONSULTA!$B$2,BONOS!$A$6:$BM$650,$H11,FALSE),"") -> 0 | H11: =IFERROR(MATCH("BONO LOGUEO1",BONOS!$A$6:$BM$6,0),"") -> 15
E12: BONO RENDIMIENTO | G12: =IFERROR(VLOOKUP(CONSULTA!$B$2,RENDIMIENTO!$A$2:$BM$650,$H12,FALSE),"") -> 0 | H12: =IFERROR(MATCH("TOTAL A PAGAR ",RENDIMIENTO!$A$2:$BM$2,0),"") -> 7
E14: TOTAL BONO DESEMPEÑO | G14: =IFERROR(VLOOKUP(CONSULTA!$B$2,BONOS!$A$6:$BM$650,$H14,FALSE),"") -> 0 | H14: =IFERROR(MATCH("TOTAL B.DESEMPEÑO ",BONOS!$A$6:$BM$6,0),"") -> 19
E15: TOTAL BONO RENDIMIENTO | G15: =G12 -> 0
B17: Este documento es de carácter informativo. Su contenido carece de valor oficial, por lo que de requerir su “recibo de nómina”, favor de solicitarlo en oficinas de Transportes LIPU.

Sheet BONOS
F1: 2002 AL 2015 4.30 | K1: SINIESTROS | L1: QUEJAS | M1: PUNTUALIDAD | N1: SCORE | O1: LOGUEO
A2: SEMANA 38 | F2: camion | K2: 134.18 | L2: 134.18 | N2: 200 | O2: 177.44
K4: 70712.86 | L4: 70310.32 | M4: 0 | N4: 46000 | O4: 44714.88 | P4: 0 | Q4: 0 | R4: 0 | S4: 231738.06
E5: CON/SIN | F5: CON/SIN | G5: TOTAL | H5: OK/NO | I5: OK/NO | J5: LOGUEO/NO LOGUEO | K5: TOTAL FORMULADO OBTENIDO | S5: TOTAL FORMULADO
A6: CLAVE | B6: NOMBRE | C6: F.INGRESO | D6: UNIDAD | E6: SINIESTROS | F6: QUEJAS | G6: SCORE OBTENIDO | H6: BONO SCORE | I6: PUNTUALIDAD | J6: BONO LOGUEO | K6: BONO SINIESTROS | L6: BONO QUEJAS | M6: BONO PUNTUALIDAD | N6: BONO SCORE1 | O6: BONO LOGUEO1 | P6: TOTAL BONO | Q6: DETALLE(FECHA DE SINIESTRO) | R6: OBSERVACIONES | S6: TOTAL B.DESEMPEÑO | U6: CONFIRMACIÓN DE VIAJE | V6: Guardia/Ddescansero
A7: 14100716 | B7: AMBRIZ MERCADO MARTIN | C7: 2017-05-01 | D7: LIPU | E7: SIN SINIESTRO | F7: SIN QUEJA | H7: NO | I7: OK | J7: NO LOGUEO | K7: 0 | L7: 0 | N7: 0 | O7: 0 | S7: 0 | U7: NO | V7: NO
A8: 14100718 | B8: MARTINEZ OCHOA PAULO | C8: 2017-05-01 | D8: LIPU | E8: SIN SINIESTRO | F8: SIN QUEJA | G8: 92 | H8: OK | I8: OK | J8: LOGUEO | K8: 134.18 | L8: 134.18 | N8: 200 | O8: 177.44 | S8: 645.8 | U8: BONO | V8: NO
A9: 14100721 | B9: GUTIERREZ VELEZ FRANCISCO | C9: 2021-07-08 | D9: LIPU | E9: SIN SINIESTRO | F9: SIN QUEJA | G9: 85 | H9: NO | I9: No | J9: LOGUEO | K9: 134.18 | L9: 134.18 | N9: 0 | O9: 0 | S9: 268.36 | U9: BONO | V9: NO
A10: 14100724 | B10: ORTIZ GARCIA LUIS ALBERTO | C10: 2017-05-01 | D10: LIPU | E10: SIN SINIESTRO | F10: SIN QUEJA | G10: 95 | H10: OK | I10: No | J10: LOGUEO | K10: 134.18 | L10: 134.18 | N10: 0 | O10: 0 | S10: 268.36 | U10: BONO | V10: NO
A11: 14100725 | B11: NAJAR LOPEZ JOSE SERGIO | C11: 2017-05-01 | D11: LIPU | E11: SIN SINIESTRO | F11: SIN QUEJA | H11: NO | I11: OK | J11: NO LOGUEO | K11: 0 | L11: 0 | N11: 0 | O11: 0 | S11: 0 | U11: NO | V11: NO
A12: 14100726 | B12: GUZMAN MUNGUIA LUIS JAVIER | C12: 2017-05-01 | D12: LIPU | E12: SIN SINIESTRO | F12: SIN QUEJA | G12: 95 | H12: OK | I12: OK | J12: LOGUEO | K12: 134.18 | L12: 134.18 | N12: 200 | O12: 177.44 | S12: 645.8 | U12: BONO | V12: NO
A13: 14100727 | B13: ALONZO PEREZ JOSE REYES | C13: 2017-05-01 | D13: LIPU | E13: SIN SINIESTRO | F13: SIN QUEJA | G13: 92 | H13: OK | I13: No | J13: LOGUEO | K13: 134.18 | L13: 134.18 | N13: 0 | O13: 0 | S13: 268.36 | U13: BONO | V13: NO
A14: 14100729 | B14: LARIOS ALCARAZ EDUARDO | C14: 2017-05-01 | D14: LIPU | E14: SIN SINIESTRO | F14: SIN QUEJA | G14: 88 | H14: NO | I14: No | J14: LOGUEO | K14: 134.18 | L14: 134.18 | N14: 0 | O14: 0 | S14: 268.36 | U14: BONO | V14: NO
A15: 14100731 | B15: TABARES FLORES OSCAR ALEJANDRO | C15: 2022-09-02 | D15: LIPU | E15: SIN SINIESTRO | F15: SIN QUEJA | G15: 84 | H15: NO | I15: OK | J15: NO LOGUEO | K15: 0 | L15: 0 | N15: 0 | O15: 0 | S15: 0 | U15: NO | V15: NO
A16: 14100732 | B16: ROBLES DEADEL LAZARO | C16: 2017-05-01 | D16: LIPU | E16: SIN SINIESTRO | F16: SIN QUEJA | G16: 92 | H16: OK | I16: OK | J16: LOGUEO | K16: 134.18 | L16: 134.18 | N16: 200 | O16: 177.44 | S16: 645.8 | U16: BONO | V16: NO
A17: 14100733 | B17: LINARES CISNEROS JOSE ANTONIO | C17: 2017-05-01 | D17: LIPU | E17: SIN SINIESTRO | F17: SIN QUEJA | G17: 95 | H17: OK | I17: No | J17: LOGUEO | K17: 134.18 | L17: 134.18 | N17: 0 | O17: 0 | S17: 268.36 | U17: BONO | V17: NO
A18: 14100740 | B18: OLIVARES HERNANDEZ GABRIEL | C18: 2021-11-17 | D18: LIPU | E18: SIN SINIESTRO | F18: SIN QUEJA | G18: 92 | H18: OK | I18: No | J18: LOGUEO | K18: 134.18 | L18: 134.18 | N18: 0 | O18: 0 | S18: 268.36 | U18: BONO | V18: NO
A19: 14100751 | B19: FLORES GARCIA PEDRO | C19: 2025-10-10 | D19: LIPU | E19: SIN SINIESTRO | F19: SIN QUEJA | G19: 91 | H19: OK | I19: OK | J19: LOGUEO | K19: 134.18 | L19: 134.18 | N19: 200 | O19: 177.44 | S19: 645.8 | U19: BONO | V19: NO
A20: 14100777 | B20: GONZALEZ MANZO JAVIER OSWALDO | C20: 2017-05-01 | D20: LIPU | E20: SIN SINIESTRO | F20: SIN QUEJA | H20: NO | I20: OK | J20: NO LOGUEO | K20: 0 | L20: 0 | N20: 0 | O20: 0 | S20: 0 | U20: NO | V20: NO
A21: 14100787 | B21: YEPEZ VAZQUEZ JOAN | C21: 2017-05-01 | D21: LIPU | E21: SIN SINIESTRO | F21: SIN QUEJA | G21: 93 | H21: OK | I21: No | J21: LOGUEO | K21: 134.18 | L21: 134.18 | N21: 0 | O21: 0 | S21: 268.36 | U21: BONO | V21: NO
A22: 14100795 | B22: BALTAZAR MENDOZA HORACIO | C22: 2017-05-01 | D22: LIPU | E22: SIN SINIESTRO | F22: SIN QUEJA | G22: 94 | H22: OK | I22: OK | J22: NO LOGUEO | K22: 134.18 | L22: 134.18 | N22: 200 | O22: 0 | S22: 468.36 | U22: BONO | V22: NO
A23: 14100798 | B23: CARRILLO REYNOSO JESUS ALEJANDRO | C23: 2017-05-01 | D23: LIPU | E23: SIN SINIESTRO | F23: SIN QUEJA | G23: 94 | H23: OK | I23: OK | J23: LOGUEO | K23: 134.18 | L23: 134.18 | N23: 200 | O23: 177.44 | S23: 645.8 | U23: BONO | V23: NO
A24: 14100807 | B24: OSORIO HERNANDEZ DOMINGO | C24: 2023-05-12 | D24: LIPU | E24: SIN SINIESTRO | F24: SIN QUEJA | G24: 93 | H24: OK | I24: No | J24: LOGUEO | K24: 134.18 | L24: 134.18 | N24: 0 | O24: 0 | S24: 268.36 | U24: BONO | V24: NO
A25: 14100823 | B25: FLORES ENRIQUEZ JUAN PABLO | C25: 2024-08-05 | D25: LIPU | E25: SIN SINIESTRO | F25: SIN QUEJA | G25: 95 | H25: OK | I25: OK | J25: LOGUEO | K25: 134.18 | L25: 134.18 | N25: 200 | O25: 177.44 | S25: 645.8 | U25: BONO | V25: Guardia
A26: 14100842 | B26: BECERRA LUNA GUILLERMO | C26: 2017-05-01 | D26: LIPU | E26: SIN SINIESTRO | F26: SIN QUEJA | G26: 93 | H26: OK | I26: No | J26: LOGUEO | K26: 134.18 | L26: 134.18 | N26: 0 | O26: 0 | S26: 268.36 | U26: BONO | V26: NO
A27: 14100843 | B27: LOPEZ RAYMUNDO ROBERTO | C27: 2025-03-07 | D27: LIPU | E27: SIN SINIESTRO | F27: SIN QUEJA | G27: 94 | H27: OK | I27: OK | J27: LOGUEO | K27: 134.18 | L27: 134.18 | N27: 200 | O27: 177.44 | S27: 645.8 | U27: BONO | V27: Guardia
A28: 14100858 | B28: REYNAGA SANCHEZ MARIO | C28: 2025-06-06 | D28: LIPU | E28: SIN SINIESTRO | F28: SIN QUEJA | G28: 92 | H28: OK | I28: No | J28: LOGUEO | K28: 134.18 | L28: 134.18 | N28: 0 | O28: 0 | S28: 268.36 | U28: BONO | V28: NO
A29: 14100863 | B29: MARTINEZ ZAVALA FRANCISCO ESPIRIDION | C29: 2017-05-01 | D29: LIPU | E29: SIN SINIESTRO | F29: SIN QUEJA | G29: 95 | H29: OK | I29: No | J29: LOGUEO | K29: 134.18 | L29: 134.18 | N29: 0 | O29: 0 | S29: 268.36 | U29: BONO | V29: NO
A30: 14100902 | B30: SANCHEZ PONCE JOSE ALBERTO | C30: 2025-12-31 | D30: LIPU | E30: SIN SINIESTRO | F30: SIN QUEJA | G30: 87 | H30: NO | I30: No | J30: NO LOGUEO | K30: 134.18 | L30: 134.18 | N30: 0 | O30: 0 | S30: 268.36 | U30: BONO | V30: Descansero
A31: 14101881 | B31: MORALES AGUILAR ALBERTO | C31: 2017-05-24 | D31: LIPU | E31: SIN SINIESTRO | F31: SIN QUEJA | G31: 91 | H31: OK | I31: No | J31: LOGUEO | K31: 134.18 | L31: 134.18 | N31: 0 | O31: 0 | S31: 268.36 | U31: BONO | V31: NO
A32: 14101984 | B32: TABARES VAZQUEZ MARTIN | C32: 2018-11-29 | D32: LIPU | E32: SIN SINIESTRO | F32: SIN QUEJA | G32: 72 | H32: NO | I32: OK | J32: LOGUEO | K32: 134.18 | L32: 134.18 | N32: 0 | O32: 177.44 | S32: 445.8 | U32: BONO | V32: Descansero
... A37: 14102875 | B37: LARIOS SANCHEZ HECTOR ALEXANDER | C37: 2017-12-20 | D37: LIPU | E37: SIN SINIESTRO | F37: SIN QUEJA | G37: 93 | H37: OK | I37: OK | J37: LOGUEO | K37: 134.18 | L37: 134.18 | N37: 200 | O37: 177.44 | S37: 645.8 | U37: BONO | V37: Guardia
A38: 14102890 | B38: GONZALEZ VALENCIA BARTOLO | C38: 2017-12-21 | D38: LIPU | E38: SIN SINIESTRO | F38: SIN QUEJA | H38: NO | I38: OK | J38: NO LOGUEO | K38: 0 | L38: 0 | N38: 0 | O38: 0 | S38: 0 | U38: NO | V38: NO
A39: 14103061 | B39: SANCHEZ PEREZ CARLOS FORTINO | C39: 2023-06-01 | D39: LIPU | E39: SIN SINIESTRO | F39: SIN QUEJA | G39: 94 | H39: OK | I39: OK | J39: NO LOGUEO | K39: 134.18 | L39: 134.18 | N39: 200 | O39: 0 | S39: 468.36 | U39: BONO | V39: NO
A40: 14103106 | B40: CORTES ARMENTA HERNAN | C40: 2018-02-02 | D40: LIPU | E40: SIN SINIESTRO | F40: SIN QUEJA | G40: 93 | H40: OK | I40: No | J40: LOGUEO | K40: 134.18 | L40: 134.18 | N40: 0 | O40: 0 | S40: 268.36 | U40: BONO | V40: NO
A41: 14103183 | B41: HERNANDEZ RON BLANCA HERLINDA | C41: 2018-02-27 | D41: LIPU | E41: SIN SINIESTRO | F41: SIN QUEJA | G41: 95 | H41: OK | I41: No | J41: LOGUEO | K41: 134.18 | L41: 134.18 | N41: 0 | O41: 0 | S41: 268.36 | U41: BONO | V41: NO
A42: 14103335 | B42: RIVERA MARTINEZ GUSTAVO | C42: 2018-04-09 | D42: LIPU | E42: SIN SINIESTRO | F42: SIN QUEJA | G42: 93 | H42: OK | I42: No | J42: LOGUEO | K42: 134.18 | L42: 134.18 | N42: 0 | O42: 0 | S42: 268.36 | U42: BONO | V42: NO
A43: 14103679 | B43: BAUTISTA SOLORIO JAIME | C43: 2018-06-29 | D43: LIPU | E43: SIN SINIESTRO | F43: SIN QUEJA | G43: 90 | H43: OK | I43: OK | J43: LOGUEO | K43: 134.18 | L43: 134.18 | N43: 200 | O43: 177.44 | S43: 645.8 | U43: BONO | V43: NO
A44: 14103936 | B44: GUTIERREZ GALINDO CARLOS DE JESUS | C44: 2025-08-23 | D44: LIPU | E44: SIN SINIESTRO | F44: SIN QUEJA | G44: 86 | H44: NO | I44: OK | J44: LOGUEO | K44: 134.18 | L44: 134.18 | N44: 0 | O44: 177.44 | S44: 445.8 | U44: BONO | V44: NO
A45: 14103952 | B45: HERNANDEZ ORTEGA RAUL | C45: 2018-08-23 | D45: LIPU | E45: SIN SINIESTRO | F45: SIN QUEJA | H45: NO | I45: OK | J45: NO LOGUEO | K45: 0 | L45: 0 | N45: 0 | O45: 0 | S45: 0 | U45: NO | V45: NO
A46: 14104315 | B46: SERRANO MACHUCA MARTIN DE JESUS | C46: 2025-10-31 | D46: LIPU | E46: SIN SINIESTRO | F46: SIN QUEJA | G46: 87 | H46: NO | I46: OK | J46: NO LOGUEO | K46: 0 | L46: 0 | N46: 0 | O46: 0 | S46: 0 | U46: NO | V46: NO
A47: 14104316 | B47: COBIAN AYALA EDGAR | C47: 2022-11-16 | D47: LIPU | E47: SIN SINIESTRO | F47: SIN QUEJA | G47: 94 | H47: OK | I47: OK | J47: NO LOGUEO | K47: 0 | L47: 0 | N47: 0 | O47: 0 | S47: 0 | U47: NO | V47: NO
A48: 14104599 | B48: TORRES GUARDADO JOSE LUIS | C48: 2023-03-09 | D48: LIPU | E48: SIN SINIESTRO | F48: SIN QUEJA | G48: 92 | H48: OK | I48: No | J48: LOGUEO | K48: 134.18 | L48: 134.18 | N48: 0 | O48: 0 | S48: 268.36 | U48: BONO | V48: NO
A49: 14104822 | B49: HERNANDEZ CRUZ ERNESTO | C49: 2019-03-06 | D49: LIPU | E49: SIN SINIESTRO | F49: SIN QUEJA | G49: 94 | H49: OK | I49: OK | J49: LOGUEO | K49: 134.18 | L49: 134.18 | N49: 200 | O49: 177.44 | S49: 645.8 | U49: BONO | V49: Guardia
A50: 14104839 | B50: CASTRO GUIZAR DANIEL HUMBERTO | C50: 2025-03-14 | D50: LIPU | E50: SIN SINIESTRO | F50: CON QUEJA | G50: 93 | H50: OK | I50: OK | J50: LOGUEO | K50: 134.18 | L50: 0 | N50: 200 | O50: 177.44 | S50: 511.62 | U50: BONO | V50: NO
A51: 14104853 | B51: CAUDILLO CORONADO MARTIN | C51: 2024-11-12 | D51: LIPU | E51: SIN SINIESTRO | F51: SIN QUEJA | G51: 92 | H51: OK | I51: OK | J51: LOGUEO | K51: 134.18 | L51: 134.18 | N51: 200 | O51: 177.44 | S51: 645.8 | U51: BONO | V51: NO
A52: 14104932 | B52: MARROQUIN ACEVES MARCOS GUILLERMO | C52: 2019-04-01 | D52: LIPU | E52: SIN SINIESTRO | F52: SIN QUEJA | G52: 86 | H52: NO | I52: No | J52: LOGUEO | K52: 134.18 | L52: 134.18 | N52: 0 | O52: 0 | S52: 268.36 | U52: BONO | V52: NO
A53: 14104957 | B53: RODRIGUEZ ORTIZ JOSE MANUEL | C53: 2025-09-13 | D53: LIPU | E53: SIN SINIESTRO | F53: SIN QUEJA | G53: 95 | H53: OK | I53: OK | J53: LOGUEO | K53: 134.18 | L53: 134.18 | N53: 200 | O53: 177.44 | S53: 645.8 | U53: BONO | V53: NO
A54: 14105437 | B54: VAZQUEZ SALAS GILBERTO | C54: 2023-04-01 | D54: LIPU | E54: SIN SINIESTRO | F54: SIN QUEJA | G54: 94 | H54: OK | I54: No | J54: LOGUEO | K54: 134.18 | L54: 134.18 | N54: 0 | O54: 0 | S54: 268.36 | U54: BONO | V54: NO
A55: 14105531 | B55: RANGEL RAMIREZ RODOLFO IVAN | C55: 2023-03-24 | D55: LIPU | E55: SIN SINIESTRO | F55: SIN QUEJA | G55: 80 | H55: NO | I55: OK | J55: LOGUEO | K55: 134.18 | L55: 134.18 | N55: 0 | O55: 177.44 | S55: 445.8 | U55: BONO | V55: NO
A56: 14105586 | B56: RAMIREZ FLORES JOSE DE JESUS | C56: 2019-09-06 | D56: LIPU | E56: SIN SINIESTRO | F56: SIN QUEJA | G56: 93 | H56: OK | I56: OK | J56: LOGUEO | K56: 134.18 | L56: 134.18 | N56: 200 | O56: 177.44 | S56: 645.8 | U56: BONO | V56: NO
A57: 14105645 | B57: DIAZ RAMOS ISMAEL | C57: 2024-06-12 | D57: LIPU | E57: SIN SINIESTRO | F57: SIN QUEJA | G57: 92 | H57: OK | I57: OK | J57: LOGUEO | K57: 134.18 | L57: 134.18 | N57: 200 | O57: 177.44 | S57: 645.8 | U57: BONO | V57: Guardia
A58: 14106033 | B58: HERNANDEZ PEREZ FRANCISCO JAVIER | C58: 2020-01-22 | D58: LIPU | E58: SIN SINIESTRO | F58: SIN QUEJA | G58: 90 | H58: OK | I58: OK | J58: LOGUEO | K58: 134.18 | L58: 134.18 | N58: 200 | O58: 177.44 | S58: 645.8 | U58: BONO | V58: NO
A59: 14106035 | B59: TAMAYO GONZALEZ CHRISTIAN JESUS | C59: 2020-01-23 | D59: LIPU | E59: SIN SINIESTRO | F59: SIN QUEJA | H59: NO | I59: OK | J59: NO LOGUEO | K59: 0 | L59: 0 | N59: 0 | O59: 0 | S59: 0 | U59: NO | V59: NO
A60: 14106066 | B60: PLASCENCIA ESQUIVEL FRANCISCO | C60: 2020-01-30 | D60: LIPU | E60: SIN SINIESTRO | F60: SIN QUEJA | G60: 84 | H60: NO | I60: OK | J60: LOGUEO | K60: 134.18 | L60: 134.18 | N60: 0 | O60: 177.44 | S60: 445.8 | U60: BONO | V60: NO
A61: 14106233 | B61: ACEVEDO MARTINEZ JORGE | C61: 2025-11-22 | D61: LIPU | E61: SIN SINIESTRO | F61: SIN QUEJA | G61: 94 | H61: OK | I61: OK | J61: NO LOGUEO | K61: 134.18 | L61: 134.18 | N61: 200 | O61: 0 | S61: 468.36 | U61: BONO | V61: Descansero
A62: 14106368 | B62: SANTANA ARAIZA SANTIAGO | C62: 2020-04-07 | D62: LIPU | E62: SIN SINIESTRO | F62: SIN QUEJA | G62: 91 | H62: OK | I62: No | J62: LOGUEO | K62: 134.18 | L62: 134.18 | N62: 0 | O62: 0 | S62: 268.36 | U62: BONO | V62: NO
A63: 14106438 | B63: GAYTAN PINEDO CARLOS ENRIQUE | C63: 2020-05-19 | D63: LIPU | E63: SIN SINIESTRO | F63: SIN QUEJA | G63: 95 | H63: OK | I63: No | J63: LOGUEO | K63: 134.18 | L63: 134.18 | N63: 0 | O63: 0 | S63: 268.36 | U63: BONO | V63: NO
A64: 14106778 | B64: CABALLERO ANGUIANO SERGIO | C64: 2020-07-24 | D64: LIPU | E64: SIN SINIESTRO | F64: SIN QUEJA | G64: 93 | H64: OK | I64: No | J64: NO LOGUEO | K64: 134.18 | L64: 134.18 | N64: 0 | O64: 0 | S64: 268.36 | U64: BONO | V64: NO
A65: 14106949 | B65: SOTELO AVIÑA MICHEL ALEJANDRO | C65: 2020-09-21 | D65: LIPU | E65: SIN SINIESTRO | F65: SIN QUEJA | G65: 94 | H65: OK | I65: OK | J65: LOGUEO | K65: 134.18 | L65: 134.18 | N65: 200 | O65: 177.44 | S65: 645.8 | U65: BONO | V65: NO
A66: 14106980 | B66: LOPEZ GODOY ENRIQUE | C66: 2020-09-28 | D66: LIPU | E66: SIN SINIESTRO | F66: SIN QUEJA | G66: 95 | H66: OK | I66: OK | J66: LOGUEO | K66: 134.18 | L66: 134.18 | N66: 200 | O66: 177.44 | S66: 645.8 | U66: BONO | V66: NO
A67: 14107081 | B67: RAMIREZ RUIZ RAUL | C67: 2020-11-01 | D67: LIPU | E67: SIN SINIESTRO | F67: SIN QUEJA | G67: 94 | H67: OK | I67: OK | J67: NO LOGUEO | K67: 0 | L67: 0 | N67: 0 | O67: 0 | S67: 0 | U67: NO | V67: NO
A68: 14107167 | B68: MENDEZ RUIZ BENJAMIN FRANCISCO | C68: 2020-11-20 | D68: LIPU | E68: SIN SINIESTRO | F68: SIN QUEJA | G68: 94 | H68: OK | I68: No | J68: LOGUEO | K68: 134.18 | L68: 134.18 | N68: 0 | O68: 0 | S68: 268.36 | U68: BONO | V68: NO
A69: 14107202 | B69: ANGUIANO OCAMPO JOSE GUADALUPE | C69: 2023-03-17 | D69: LIPU | E69: SIN SINIESTRO | F69: SIN QUEJA | G69: 89 | H69: NO | I69: OK | J69: LOGUEO | K69: 134.18 | L69: 134.18 | N69: 0 | O69: 177.44 | S69: 445.8 | U69: BONO | V69: NO
A70: 14107206 | B70: HERNANDEZ CHAVEZ FERNANDO | C70: 2020-12-07 | D70: LIPU | E70: SIN SINIESTRO | F70: SIN QUEJA | G70: 91 | H70: OK | I70: OK | J70: LOGUEO | K70: 134.18 | L70: 134.18 | N70: 200 | O70: 177.44 | S70: 645.8 | U70: BONO | V70: Guardia
A71: 14107271 | B71: PEREZ CASTILLO GABRIEL | C71: 2020-12-23 | D71: LIPU | E71: SIN SINIESTRO | F71: SIN QUEJA | G71: 84 | H71: NO | I71: OK | J71: NO LOGUEO | K71: 134.18 | L71: 134.18 | N71: 0 | O71: 0 | S71: 268.36 | U71: BONO | V71: NO
A72: 14107293 | B72: MAGAÑA CONTRERAS JOSE LUIS | C72: 2025-01-16 | D72: LIPU | E72: SIN SINIESTRO | F72: SIN QUEJA | H72: NO | I72: OK | J72: NO LOGUEO | K72: 0 | L72: 0 | N72: 0 | O72: 0 | S72: 0 | U72: NO | V72: NO
A73: 14107393 | B73: GUERRERO CORTES SERGIO RICARDO | C73: 2021-01-28 | D73: LIPU | E73: SIN SINIESTRO | F73: SIN QUEJA | G73: 91 | H73: OK | I73: No | J73: LOGUEO | K73: 134.18 | L73: 134.18 | N73: 0 | O73: 0 | S73: 268.36 | U73: BONO | V73: NO
A74: 14107484 | B74: LOPEZ VELASCO MARIO | C74: 2021-02-18 | D74: LIPU | E74: SIN SINIESTRO | F74: SIN QUEJA | G74: 95 | H74: OK | I74: OK | J74: LOGUEO | K74: 134.18 | L74: 134.18 | N74: 200 | O74: 177.44 | S74: 645.8 | U74: BONO | V74: NO
A75: 14107552 | B75: PACHECO SALCEDO FERNANDO | C75: 2021-03-04 | D75: LIPU | E75: SIN SINIESTRO | F75: SIN QUEJA | G75: 90 | H75: OK | I75: No | J75: NO LOGUEO | K75: 134.18 | L75: 134.18 | N75: 0 | O75: 0 | S75: 268.36 | U75: BONO | V75: NO
A76: 14107735 | B76: ZEPEDA GUERRERO JUAN CARLOS | C76: 2021-04-16 | D76: LIPU | E76: SIN SINIESTRO | F76: SIN QUEJA | G76: 95 | H76: OK | I76: OK | J76: LOGUEO | K76: 134.18 | L76: 134.18 | N76: 200 | O76: 177.44 | S76: 645.8 | U76: BONO | V76: NO
A77: 14107754 | B77: GARCIA DE LA TORRE LEONARDO | C77: 2021-04-22 | D77: LIPU | E77: SIN SINIESTRO | F77: SIN QUEJA | G77: 93 | H77: OK | I77: OK | J77: LOGUEO | K77: 134.18 | L77: 134.18 | N77: 200 | O77: 177.44 | S77: 645.8 | U77: BONO | V77: NO
A78: 14107840 | B78: CONTRERAS DAVILA DANIEL | C78: 2021-05-12 | D78: LIPU | E78: SIN SINIESTRO | F78: SIN QUEJA | G78: 94 | H78: OK | I78: OK | J78: NO LOGUEO | K78: 134.18 | L78: 134.18 | N78: 200 | O78: 0 | S78: 468.36 | U78: BONO | V78: NO
A79: 14107967 | B79: VAZQUEZ FLORES FABIAN | C79: 2021-06-10 | D79: LIPU | E79: SIN SINIESTRO | F79: SIN QUEJA | G79: 95 | H79: OK | I79: No | J79: NO LOGUEO | K79: 0 | L79: 0 | N79: 0 | O79: 0 | S79: 0 | U79: NO | V79: NO
A80: 14107978 | B80: LIRA LOPEZ LUIS ANGEL | C80: 2021-06-11 | D80: LIPU | E80: SINIESTRO | F80: SIN QUEJA | G80: 91 | H80: OK | I80: OK | J80: LOGUEO | K80: 0 | L80: 134.18 | N80: 200 | O80: 177.44 | S80: 511.62 | U80: BONO | V80: NO
A81: 14108111 | B81: LUNA SANDOVAL DAVID | C81: 2021-07-02 | D81: LIPU | E81: SIN SINIESTRO | F81: SIN QUEJA | G81: 92 | H81: OK | I81: No | J81: LOGUEO | K81: 134.18 | L81: 134.18 | N81: 0 | O81: 0 | S81: 268.36 | U81: BONO | V81: NO
A82: 14108150 | B82: IBARRA PEREZ MARTIN | C82: 2021-07-09 | D82: LIPU | E82: SIN SINIESTRO | F82: SIN QUEJA | G82: 92 | H82: OK | I82: OK | J82: NO LOGUEO | K82: 0 | L82: 0 | N82: 0 | O82: 0 | S82: 0 | U82: NO | V82: NO
A83: 14108222 | B83: TELLES PADILLA JOSE MANUEL | C83: 2021-07-21 | D83: LIPU | E83: SIN SINIESTRO | F83: SIN QUEJA | G83: 91 | H83: OK | I83: No | J83: LOGUEO | K83: 134.18 | L83: 134.18 | N83: 0 | O83: 0 | S83: 268.36 | U83: BONO | V83: NO
A84: 14108267 | B84: MUÑOZ SANTACRUZ JUAN PABLO | C84: 2021-07-28 | D84: LIPU | E84: SIN SINIESTRO | F84: SIN QUEJA | G84: 83 | H84: NO | I84: No | J84: LOGUEO | K84: 134.18 | L84: 134.18 | N84: 0 | O84: 0 | S84: 268.36 | U84: BONO | V84: NO
... A89: 14108552 | B89: ZUÑIGA HERNANDEZ OSCAR FRANCISCO | C89: 2023-11-14 | D89: LIPU | E89: SIN SINIESTRO | F89: SIN QUEJA | G89: 87 | H89: NO | I89: No | J89: LOGUEO | K89: 134.18 | L89: 134.18 | N89: 0 | O89: 0 | S89: 268.36 | U89: BONO | V89: Guardia
A90: 14108553 | B90: MARTINEZ LOPEZ JORGE ANTONIO | C90: 2024-06-03 | D90: LIPU | E90: SIN SINIESTRO | F90: SIN QUEJA | H90: NO | I90: OK | J90: NO LOGUEO | K90: 0 | L90: 0 | N90: 0 | O90: 0 | S90: 0 | U90: NO | V90: NO
A91: 14108571 | B91: BELTRAN OLIVARES NESTOR ARMANDO | C91: 2021-08-20 | D91: LIPU | E91: SIN SINIESTRO | F91: SIN QUEJA | G91: 88 | H91: NO | I91: OK | J91: LOGUEO | K91: 134.18 | L91: 134.18 | N91: 0 | O91: 177.44 | S91: 445.8 | U91: BONO | V91: NO
A92: 14108775 | B92: PARRA COBIAN OSCAR | C92: 2024-10-25 | D92: LIPU | E92: SIN SINIESTRO | F92: SIN QUEJA | H92: NO | I92: OK | J92: NO LOGUEO | K92: 0 | L92: 0 | N92: 0 | O92: 0 | S92: 0 | U92: NO | V92: NO
A93: 14108828 | B93: BARAJAS SALDAÑA JUAN | C93: 2025-03-14 | D93: LIPU | E93: SIN SINIESTRO | F93: SIN QUEJA | G93: 93 | H93: OK | I93: OK | J93: LOGUEO | K93: 134.18 | L93: 134.18 | N93: 200 | O93: 177.44 | S93: 645.8 | U93: BONO | V93: NO
A94: 14108916 | B94: RAMOS DELGADO FRANCISCO | C94: 2021-10-06 | D94: LIPU | E94: SIN SINIESTRO | F94: SIN QUEJA | G94: 75 | H94: NO | I94: No | J94: LOGUEO | K94: 134.18 | L94: 134.18 | N94: 0 | O94: 0 | S94: 268.36 | U94: BONO | V94: NO
A95: 14109032 | B95: GARCIA PRECIADO ANTONIO | C95: 2021-10-28 | D95: LIPU | E95: SIN SINIESTRO | F95: SIN QUEJA | G95: 94 | H95: OK | I95: OK | J95: LOGUEO | K95: 134.18 | L95: 134.18 | N95: 200 | O95: 177.44 | S95: 645.8 | U95: BONO | V95: NO
A96: 14109097 | B96: VAZQUEZ CERVANTES JOSE MAURICIO | C96: 2021-11-08 | D96: LIPU | E96: SIN SINIESTRO | F96: SIN QUEJA | G96: 94 | H96: OK | I96: OK | J96: LOGUEO | K96: 134.18 | L96: 134.18 | N96: 200 | O96: 177.44 | S96: 645.8 | U96: BONO | V96: NO
A97: 14109131 | B97: GONZALEZ FLOREZ SALVADOR | C97: 2021-11-08 | D97: LIPU | E97: SIN SINIESTRO | F97: SIN QUEJA | G97: 93 | H97: OK | I97: OK | J97: LOGUEO | K97: 134.18 | L97: 134.18 | N97: 200 | O97: 177.44 | S97: 645.8 | U97: BONO | V97: NO
A98: 14109133 | B98: RENTERIA GUTIERREZ JUAN MANUEL | C98: 2021-11-08 | D98: LIPU | E98: SIN SINIESTRO | F98: SIN QUEJA | G98: 92 | H98: OK | I98: OK | J98: LOGUEO | K98: 134.18 | L98: 134.18 | N98: 200 | O98: 177.44 | S98: 645.8 | U98: BONO | V98: NO
A99: 14109134 | B99: GODINEZ CONTRERAS SERGIO ALEJANDRO | C99: 2021-11-08 | D99: LIPU | E99: SIN SINIESTRO | F99: SIN QUEJA | G99: 94 | H99: OK | I99: No | J99: LOGUEO | K99: 134.18 | L99: 134.18 | N99: 0 | O99: 0 | S99: 268.36 | U99: BONO | V99: NO
A100: 14109378 | B100: NAVARRO MEZA JULIAN | C100: 2021-12-21 | D100: LIPU | E100: SIN SINIESTRO | F100: SIN QUEJA | G100: 95 | H100: OK | I100: OK | J100: LOGUEO | K100: 134.18 | L100: 134.18 | N100: 200 | O100: 177.44 | S100: 645.8 | U100: BONO | V100: NO
A101: 14109408 | B101: DE LA CRUZ CHAVEZ LUIS DAVID | C101: 2022-01-04 | D101: LIPU | E101: SIN SINIESTRO | F101: SIN QUEJA | G101: 93 | H101: OK | I101: OK | J101: NO LOGUEO | K101: 134.18 | L101: 134.18 | N101: 200 | O101: 0 | S101: 468.36 | U101: BONO | V101: NO
A102: 14109435 | B102: MEDINA ALVAREZ CUAUHTEMOC | C102: 2022-01-12 | D102: LIPU | E102: SIN SINIESTRO | F102: SIN QUEJA | G102: 95 | H102: OK | I102: OK | J102: LOGUEO | K102: 134.18 | L102: 134.18 | N102: 200 | O102: 177.44 | S102: 645.8 | U102: BONO | V102: Guardia
A103: 14109436 | B103: GARCIA SALCEDO FRANCISCO JAVIER | C103: 2026-01-09 | D103: LIPU | E103: SIN SINIESTRO | F103: SIN QUEJA | G103: 93 | H103: OK | I103: OK | J103: LOGUEO | K103: 134.18 | L103: 134.18 | N103: 200 | O103: 177.44 | S103: 645.8 | U103: BONO | V103: NO
A104: 14109648 | B104: SANCHEZ CANDELARIO GUSTAVO | C104: 2025-02-22 | D104: LIPU | E104: SIN SINIESTRO | F104: SIN QUEJA | G104: 94 | H104: OK | I104: OK | J104: LOGUEO | K104: 134.18 | L104: 134.18 | N104: 200 | O104: 177.44 | S104: 645.8 | U104: BONO | V104: NO
A105: 14109664 | B105: ALVARADO LOPEZ GERARDO | C105: 2022-02-09 | D105: LIPU | E105: SIN SINIESTRO | F105: SIN QUEJA | H105: NO | I105: OK | J105: NO LOGUEO | K105: 0 | L105: 0 | N105: 0 | O105: 0 | S105: 0 | U105: NO | V105: NO
A106: 14109674 | B106: BARRERA HERNANDEZ JOSE SALVADOR | C106: 2022-02-11 | D106: LIPU | E106: SIN SINIESTRO | F106: SIN QUEJA | G106: 90 | H106: OK | I106: OK | J106: LOGUEO | K106: 134.18 | L106: 134.18 | N106: 200 | O106: 177.44 | S106: 645.8 | U106: BONO | V106: NO
A107: 14109677 | B107: MARTINEZ RAMIREZ CARLOS ENRIQUE | C107: 2022-02-11 | D107: LIPU | E107: SIN SINIESTRO | F107: SIN QUEJA | H107: NO | I107: OK | J107: NO LOGUEO | K107: 0 | L107: 0 | N107: 0 | O107: 0 | S107: 0 | U107: NO | V107: NO
A108: 14109707 | B108: JIMENEZ LOPEZ ARMANDO | C108: 2022-02-16 | D108: LIPU | E108: SIN SINIESTRO | F108: SIN QUEJA | G108: 95 | H108: OK | I108: OK | J108: LOGUEO | K108: 134.18 | L108: 134.18 | N108: 200 | O108: 177.44 | S108: 645.8 | U108: BONO | V108: NO
A109: 14109738 | B109: DIAZ DE SANDI DIAZ MARTIN ALEJANDRO | C109: 2022-02-23 | D109: LIPU | E109: SIN SINIESTRO | F109: SIN QUEJA | G109: 89 | H109: NO | I109: OK | J109: NO LOGUEO | K109: 134.18 | L109: 134.18 | N109: 0 | O109: 0 | S109: 268.36 | U109: BONO | V109: NO
...
